[
  {
    "X": 9.679638,
    "Y": 10.7488108,
    "Floor": 3
  },
  {
    "X": 9.654224,
    "Y": 10.9026594,
    "Floor": 3
  },
  {
    "X": 9.635401,
    "Y": 11.0259266,
    "Floor": 3
  },
  {
    "X": 9.619796,
    "Y": 11.1496592,
    "Floor": 3
  },
  {
    "X": 9.595621,
    "Y": 11.2719116,
    "Floor": 3
  },
  {
    "X": 9.556945,
    "Y": 11.3904562,
    "Floor": 3
  },
  {
    "X": 9.525323,
    "Y": 11.5110283,
    "Floor": 3
  },
  {
    "X": 9.501283,
    "Y": 11.6333971,
    "Floor": 3
  },
  {
    "X": 9.401292,
    "Y": 9.765822,
    "Floor": 3
  },
  {
    "X": 9.384194,
    "Y": 9.857939,
    "Floor": 3
  },
  {
    "X": 9.361011,
    "Y": 9.948736,
    "Floor": 3
  },
  {
    "X": 9.33007,
    "Y": 10.0371914,
    "Floor": 3
  },
  {
    "X": 9.299158,
    "Y": 10.1256628,
    "Floor": 3
  },
  {
    "X": 9.274391,
    "Y": 10.2160378,
    "Floor": 3
  },
  {
    "X": 9.250804,
    "Y": 10.30674,
    "Floor": 3
  },
  {
    "X": 9.219091,
    "Y": 10.3948727,
    "Floor": 3
  },
  {
    "X": 9.181462,
    "Y": 10.4807129,
    "Floor": 3
  },
  {
    "X": 9.093616,
    "Y": 8.95183849,
    "Floor": 3
  },
  {
    "X": 9.058739,
    "Y": 9.031334,
    "Floor": 3
  },
  {
    "X": 9.0238,
    "Y": 9.110772,
    "Floor": 3
  },
  {
    "X": 9.001827,
    "Y": 9.194773,
    "Floor": 3
  },
  {
    "X": 8.983007,
    "Y": 9.279714,
    "Floor": 3
  },
  {
    "X": 8.954872,
    "Y": 9.361716,
    "Floor": 3
  },
  {
    "X": 8.924759,
    "Y": 9.44337,
    "Floor": 3
  },
  {
    "X": 8.893499,
    "Y": 9.524421,
    "Floor": 3
  },
  {
    "X": 8.872968,
    "Y": 9.608491,
    "Floor": 3
  },
  {
    "X": 9.026798,
    "Y": 9.232837,
    "Floor": 3
  },
  {
    "X": 9.027476,
    "Y": 9.415029,
    "Floor": 3
  },
  {
    "X": 9.006349,
    "Y": 9.595807,
    "Floor": 3
  },
  {
    "X": 8.977685,
    "Y": 9.775706,
    "Floor": 3
  },
  {
    "X": 8.965837,
    "Y": 9.957515,
    "Floor": 3
  },
  {
    "X": 8.959788,
    "Y": 10.1396132,
    "Floor": 3
  },
  {
    "X": 8.961525,
    "Y": 10.3221426,
    "Floor": 3
  },
  {
    "X": 8.962162,
    "Y": 10.504281,
    "Floor": 3
  },
  {
    "X": 8.934661,
    "Y": 10.6842089,
    "Floor": 3
  },
  {
    "X": 8.899652,
    "Y": 10.86299,
    "Floor": 3
  },
  {
    "X": 9.058207,
    "Y": 10.2613926,
    "Floor": 3
  },
  {
    "X": 9.04276848,
    "Y": 10.3880043,
    "Floor": 3
  },
  {
    "X": 9.034338,
    "Y": 10.515254,
    "Floor": 3
  },
  {
    "X": 9.026153,
    "Y": 10.6425228,
    "Floor": 3
  },
  {
    "X": 9.014032,
    "Y": 10.76949,
    "Floor": 3
  },
  {
    "X": 9.007825,
    "Y": 10.8968906,
    "Floor": 3
  },
  {
    "X": 8.996555,
    "Y": 11.0239363,
    "Floor": 3
  },
  {
    "X": 8.988146,
    "Y": 11.1511869,
    "Floor": 3
  },
  {
    "X": 8.988555,
    "Y": 11.2787075,
    "Floor": 3
  },
  {
    "X": 9.133738,
    "Y": 10.5613966,
    "Floor": 3
  },
  {
    "X": 9.125758,
    "Y": 10.6503191,
    "Floor": 3
  },
  {
    "X": 9.112617,
    "Y": 10.738574,
    "Floor": 3
  },
  {
    "X": 9.091308,
    "Y": 10.8252783,
    "Floor": 3
  },
  {
    "X": 9.07058,
    "Y": 10.9122849,
    "Floor": 3
  },
  {
    "X": 9.05413,
    "Y": 11.0000381,
    "Floor": 3
  },
  {
    "X": 9.033671,
    "Y": 11.0869217,
    "Floor": 3
  },
  {
    "X": 9.004924,
    "Y": 11.1714306,
    "Floor": 3
  },
  {
    "X": 8.978587,
    "Y": 11.2566891,
    "Floor": 3
  },
  {
    "X": 9.067707,
    "Y": 10.9059381,
    "Floor": 3
  },
  {
    "X": 9.062632,
    "Y": 11.014534,
    "Floor": 3
  },
  {
    "X": 9.063572,
    "Y": 11.1234751,
    "Floor": 3
  },
  {
    "X": 9.049913,
    "Y": 11.2315407,
    "Floor": 3
  },
  {
    "X": 9.031154,
    "Y": 11.3390837,
    "Floor": 3
  },
  {
    "X": 9.027293,
    "Y": 11.447875,
    "Floor": 3
  },
  {
    "X": 9.0359,
    "Y": 11.5565023,
    "Floor": 3
  },
  {
    "X": 9.051455,
    "Y": 11.6643648,
    "Floor": 3
  },
  {
    "X": 9.060192,
    "Y": 11.7729521,
    "Floor": 3
  },
  {
    "X": 8.935865,
    "Y": 11.2072992,
    "Floor": 3
  },
  {
    "X": 8.9497385,
    "Y": 11.3148279,
    "Floor": 3
  },
  {
    "X": 8.967109,
    "Y": 11.4218454,
    "Floor": 3
  },
  {
    "X": 8.988269,
    "Y": 11.5281811,
    "Floor": 3
  },
  {
    "X": 9.00709152,
    "Y": 11.6349287,
    "Floor": 3
  },
  {
    "X": 9.020196,
    "Y": 11.7425585,
    "Floor": 3
  },
  {
    "X": 9.035738,
    "Y": 11.8498545,
    "Floor": 3
  },
  {
    "X": 9.051591,
    "Y": 11.9573088,
    "Floor": 3
  },
  {
    "X": 9.068875,
    "Y": 12.0643415,
    "Floor": 3
  },
  {
    "X": 9.088805,
    "Y": 12.170907,
    "Floor": 3
  },
  {
    "X": 8.960416,
    "Y": 11.5361919,
    "Floor": 3
  },
  {
    "X": 8.979461,
    "Y": 11.6096582,
    "Floor": 3
  },
  {
    "X": 9.000448,
    "Y": 11.6825933,
    "Floor": 3
  },
  {
    "X": 9.019794,
    "Y": 11.7559834,
    "Floor": 3
  },
  {
    "X": 9.041341,
    "Y": 11.8288774,
    "Floor": 3
  },
  {
    "X": 9.069049,
    "Y": 11.8995152,
    "Floor": 3
  },
  {
    "X": 9.09923649,
    "Y": 11.969142,
    "Floor": 3
  },
  {
    "X": 9.120027,
    "Y": 12.0420656,
    "Floor": 3
  },
  {
    "X": 9.138106,
    "Y": 12.1157722,
    "Floor": 3
  },
  {
    "X": 9.350647,
    "Y": 14.68561,
    "Floor": 3
  },
  {
    "X": 9.476304,
    "Y": 15.1550407,
    "Floor": 3
  },
  {
    "X": 9.644708,
    "Y": 15.6108,
    "Floor": 3
  },
  {
    "X": 9.784123,
    "Y": 16.0758724,
    "Floor": 3
  },
  {
    "X": 9.867707,
    "Y": 16.555378,
    "Floor": 3
  },
  {
    "X": 9.916786,
    "Y": 17.0388813,
    "Floor": 3
  },
  {
    "X": 9.980319,
    "Y": 17.5207024,
    "Floor": 3
  },
  {
    "X": 10.0314589,
    "Y": 18.0040035,
    "Floor": 3
  },
  {
    "X": 10.0923767,
    "Y": 18.4870129,
    "Floor": 3
  },
  {
    "X": 10.1834373,
    "Y": 20.8245773,
    "Floor": 3
  },
  {
    "X": 10.247756,
    "Y": 21.3020935,
    "Floor": 3
  },
  {
    "X": 10.2820988,
    "Y": 21.7815952,
    "Floor": 3
  },
  {
    "X": 10.2770958,
    "Y": 22.2625237,
    "Floor": 3
  },
  {
    "X": 10.2770433,
    "Y": 22.7434349,
    "Floor": 3
  },
  {
    "X": 10.3374,
    "Y": 23.2201958,
    "Floor": 3
  },
  {
    "X": 10.4458513,
    "Y": 23.6886959,
    "Floor": 3
  },
  {
    "X": 10.5710182,
    "Y": 24.1530914,
    "Floor": 3
  },
  {
    "X": 10.69018,
    "Y": 24.61906,
    "Floor": 3
  },
  {
    "X": 10.7178268,
    "Y": 25.339222,
    "Floor": 3
  },
  {
    "X": 10.8121376,
    "Y": 25.7048759,
    "Floor": 3
  },
  {
    "X": 10.9215813,
    "Y": 26.06623,
    "Floor": 3
  },
  {
    "X": 11.0385942,
    "Y": 26.42526,
    "Floor": 3
  },
  {
    "X": 11.1367807,
    "Y": 26.7897453,
    "Floor": 3
  },
  {
    "X": 11.2105446,
    "Y": 27.1607723,
    "Floor": 3
  },
  {
    "X": 11.2729015,
    "Y": 27.5331936,
    "Floor": 3
  },
  {
    "X": 11.3340511,
    "Y": 27.905817,
    "Floor": 3
  },
  {
    "X": 11.41139,
    "Y": 28.2754154,
    "Floor": 3
  },
  {
    "X": 11.4869308,
    "Y": 28.64603,
    "Floor": 3
  },
  {
    "X": 11.2641211,
    "Y": 28.3871,
    "Floor": 3
  },
  {
    "X": 11.2743874,
    "Y": 28.65123,
    "Floor": 3
  },
  {
    "X": 11.2870436,
    "Y": 28.91526,
    "Floor": 3
  },
  {
    "X": 11.2985029,
    "Y": 29.1793365,
    "Floor": 3
  },
  {
    "X": 11.3263168,
    "Y": 29.442625,
    "Floor": 3
  },
  {
    "X": 11.339118,
    "Y": 29.7062912,
    "Floor": 3
  },
  {
    "X": 11.3144464,
    "Y": 29.969902,
    "Floor": 3
  },
  {
    "X": 11.2744551,
    "Y": 30.2311325,
    "Floor": 3
  },
  {
    "X": 11.2314777,
    "Y": 30.4918823,
    "Floor": 3
  },
  {
    "X": 11.0032358,
    "Y": 29.6607285,
    "Floor": 3
  },
  {
    "X": 10.9944286,
    "Y": 29.8458748,
    "Floor": 3
  },
  {
    "X": 10.9676714,
    "Y": 30.02887,
    "Floor": 3
  },
  {
    "X": 10.9349718,
    "Y": 30.2109852,
    "Floor": 3
  },
  {
    "X": 10.9067469,
    "Y": 30.393856,
    "Floor": 3
  },
  {
    "X": 10.8816814,
    "Y": 30.5771751,
    "Floor": 3
  },
  {
    "X": 10.8730354,
    "Y": 30.762228,
    "Floor": 3
  },
  {
    "X": 10.8658466,
    "Y": 30.9470749,
    "Floor": 3
  },
  {
    "X": 10.85612,
    "Y": 31.1318474,
    "Floor": 3
  },
  {
    "X": 10.8413134,
    "Y": 31.2814255,
    "Floor": 3
  },
  {
    "X": 10.7124166,
    "Y": 30.3429832,
    "Floor": 3
  },
  {
    "X": 10.7110968,
    "Y": 30.48646,
    "Floor": 3
  },
  {
    "X": 10.7239809,
    "Y": 30.6297989,
    "Floor": 3
  },
  {
    "X": 10.723175,
    "Y": 30.7733631,
    "Floor": 3
  },
  {
    "X": 10.7308464,
    "Y": 30.9164963,
    "Floor": 3
  },
  {
    "X": 10.7408743,
    "Y": 31.0596676,
    "Floor": 3
  },
  {
    "X": 10.7314472,
    "Y": 31.2029076,
    "Floor": 3
  },
  {
    "X": 10.7493343,
    "Y": 31.34531,
    "Floor": 3
  },
  {
    "X": 10.774332,
    "Y": 31.4867439,
    "Floor": 3
  },
  {
    "X": 10.6892366,
    "Y": 30.772625,
    "Floor": 3
  },
  {
    "X": 10.6966162,
    "Y": 30.9142342,
    "Floor": 3
  },
  {
    "X": 10.70777,
    "Y": 31.0553436,
    "Floor": 3
  },
  {
    "X": 10.7082987,
    "Y": 31.19689,
    "Floor": 3
  },
  {
    "X": 10.7110872,
    "Y": 31.3384113,
    "Floor": 3
  },
  {
    "X": 10.7125912,
    "Y": 31.48019,
    "Floor": 3
  },
  {
    "X": 10.7042351,
    "Y": 31.6214943,
    "Floor": 3
  },
  {
    "X": 10.6973324,
    "Y": 31.7628784,
    "Floor": 3
  },
  {
    "X": 10.6997795,
    "Y": 31.9043026,
    "Floor": 3
  },
  {
    "X": 10.6393824,
    "Y": 31.1003036,
    "Floor": 3
  },
  {
    "X": 10.6584606,
    "Y": 31.2059574,
    "Floor": 3
  },
  {
    "X": 10.6711445,
    "Y": 31.312748,
    "Floor": 3
  },
  {
    "X": 10.6762877,
    "Y": 31.419981,
    "Floor": 3
  },
  {
    "X": 10.676342,
    "Y": 31.5273361,
    "Floor": 3
  },
  {
    "X": 10.677762,
    "Y": 31.6346817,
    "Floor": 3
  },
  {
    "X": 10.6828394,
    "Y": 31.7419281,
    "Floor": 3
  },
  {
    "X": 10.6872835,
    "Y": 31.849184,
    "Floor": 3
  },
  {
    "X": 10.6841383,
    "Y": 31.9564953,
    "Floor": 3
  },
  {
    "X": 10.6281633,
    "Y": 31.1339054,
    "Floor": 3
  },
  {
    "X": 10.6257944,
    "Y": 31.2090244,
    "Floor": 3
  },
  {
    "X": 10.6221256,
    "Y": 31.2840881,
    "Floor": 3
  },
  {
    "X": 10.6235723,
    "Y": 31.3592033,
    "Floor": 3
  },
  {
    "X": 10.6252222,
    "Y": 31.4342957,
    "Floor": 3
  },
  {
    "X": 10.6200256,
    "Y": 31.5092716,
    "Floor": 3
  },
  {
    "X": 10.6144638,
    "Y": 31.584343,
    "Floor": 3
  },
  {
    "X": 10.606328,
    "Y": 31.6590271,
    "Floor": 3
  },
  {
    "X": 10.60257,
    "Y": 31.7340889,
    "Floor": 3
  },
  {
    "X": 10.6014109,
    "Y": 31.8092213,
    "Floor": 3
  },
  {
    "X": 10.5665159,
    "Y": 30.9916439,
    "Floor": 3
  },
  {
    "X": 10.56338,
    "Y": 31.04416,
    "Floor": 3
  },
  {
    "X": 10.560729,
    "Y": 31.0967,
    "Floor": 3
  },
  {
    "X": 10.5603418,
    "Y": 31.1492863,
    "Floor": 3
  },
  {
    "X": 10.5671873,
    "Y": 31.2014065,
    "Floor": 3
  },
  {
    "X": 10.5759373,
    "Y": 31.25325,
    "Floor": 3
  },
  {
    "X": 10.57591,
    "Y": 31.3058319,
    "Floor": 3
  },
  {
    "X": 10.5747452,
    "Y": 31.35843,
    "Floor": 3
  },
  {
    "X": 10.57449,
    "Y": 31.41114,
    "Floor": 3
  },
  {
    "X": 10.5626564,
    "Y": 30.3594322,
    "Floor": 3
  },
  {
    "X": 10.5666256,
    "Y": 30.4022675,
    "Floor": 3
  },
  {
    "X": 10.5684643,
    "Y": 30.4452324,
    "Floor": 3
  },
  {
    "X": 10.5680962,
    "Y": 30.49631,
    "Floor": 3
  },
  {
    "X": 10.5665293,
    "Y": 30.5419979,
    "Floor": 3
  },
  {
    "X": 10.563036,
    "Y": 30.5849571,
    "Floor": 3
  },
  {
    "X": 10.56037,
    "Y": 30.6278915,
    "Floor": 3
  },
  {
    "X": 10.5605536,
    "Y": 30.6709042,
    "Floor": 3
  },
  {
    "X": 10.5577488,
    "Y": 30.7137623,
    "Floor": 3
  },
  {
    "X": 10.8676386,
    "Y": 30.8949413,
    "Floor": 3
  },
  {
    "X": 10.8506861,
    "Y": 31.08132,
    "Floor": 3
  },
  {
    "X": 10.830759,
    "Y": 31.2674046,
    "Floor": 3
  },
  {
    "X": 10.8123655,
    "Y": 31.4536533,
    "Floor": 3
  },
  {
    "X": 10.8049736,
    "Y": 31.6405716,
    "Floor": 3
  },
  {
    "X": 10.7928314,
    "Y": 31.82741,
    "Floor": 3
  },
  {
    "X": 10.7583113,
    "Y": 32.01135,
    "Floor": 3
  },
  {
    "X": 10.7277164,
    "Y": 32.19597,
    "Floor": 3
  },
  {
    "X": 10.6885014,
    "Y": 32.3789444,
    "Floor": 3
  },
  {
    "X": 10.9835234,
    "Y": 32.3517952,
    "Floor": 3
  },
  {
    "X": 10.9488506,
    "Y": 32.47809,
    "Floor": 3
  },
  {
    "X": 10.8953638,
    "Y": 32.5974579,
    "Floor": 3
  },
  {
    "X": 10.8167391,
    "Y": 32.7021027,
    "Floor": 3
  },
  {
    "X": 10.7129784,
    "Y": 32.7817078,
    "Floor": 3
  },
  {
    "X": 10.60153,
    "Y": 32.85057,
    "Floor": 3
  },
  {
    "X": 10.48456,
    "Y": 32.90945,
    "Floor": 3
  },
  {
    "X": 10.3557568,
    "Y": 32.93157,
    "Floor": 3
  },
  {
    "X": 10.2255507,
    "Y": 32.94554,
    "Floor": 3
  },
  {
    "X": 10.0810118,
    "Y": 32.9750824,
    "Floor": 3
  },
  {
    "X": 10.1462145,
    "Y": 34.3377533,
    "Floor": 3
  },
  {
    "X": 9.837531,
    "Y": 34.35445,
    "Floor": 3
  },
  {
    "X": 9.534381,
    "Y": 34.4126549,
    "Floor": 3
  },
  {
    "X": 9.237457,
    "Y": 34.49875,
    "Floor": 3
  },
  {
    "X": 8.940143,
    "Y": 34.5831032,
    "Floor": 3
  },
  {
    "X": 8.667393,
    "Y": 34.72843,
    "Floor": 3
  },
  {
    "X": 8.398354,
    "Y": 34.8800278,
    "Floor": 3
  },
  {
    "X": 8.114474,
    "Y": 35.00209,
    "Floor": 3
  },
  {
    "X": 7.855805,
    "Y": 35.1712761,
    "Floor": 3
  },
  {
    "X": 8.104696,
    "Y": 36.82514,
    "Floor": 3
  },
  {
    "X": 7.80692863,
    "Y": 36.9214134,
    "Floor": 3
  },
  {
    "X": 7.499966,
    "Y": 36.9828224,
    "Floor": 3
  },
  {
    "X": 7.18784332,
    "Y": 37.00838,
    "Floor": 3
  },
  {
    "X": 6.875303,
    "Y": 37.0362434,
    "Floor": 3
  },
  {
    "X": 6.563503,
    "Y": 37.0661049,
    "Floor": 3
  },
  {
    "X": 6.250645,
    "Y": 37.0806541,
    "Floor": 3
  },
  {
    "X": 5.93907452,
    "Y": 37.1155548,
    "Floor": 3
  },
  {
    "X": 5.629655,
    "Y": 37.1636848,
    "Floor": 3
  },
  {
    "X": 5.966009,
    "Y": 38.52117,
    "Floor": 3
  },
  {
    "X": 5.68443966,
    "Y": 38.5735359,
    "Floor": 3
  },
  {
    "X": 5.405019,
    "Y": 38.6368866,
    "Floor": 3
  },
  {
    "X": 5.123936,
    "Y": 38.6947746,
    "Floor": 3
  },
  {
    "X": 4.84796667,
    "Y": 38.7717,
    "Floor": 3
  },
  {
    "X": 4.575551,
    "Y": 38.8603325,
    "Floor": 3
  },
  {
    "X": 4.29321671,
    "Y": 38.9112053,
    "Floor": 3
  },
  {
    "X": 4.013004,
    "Y": 38.9694138,
    "Floor": 3
  },
  {
    "X": 3.73647642,
    "Y": 39.0432053,
    "Floor": 3
  },
  {
    "X": 4.56644,
    "Y": 40.01633,
    "Floor": 3
  },
  {
    "X": 4.366021,
    "Y": 40.02172,
    "Floor": 3
  },
  {
    "X": 4.16617966,
    "Y": 40.0054321,
    "Floor": 3
  },
  {
    "X": 3.965592,
    "Y": 39.9966469,
    "Floor": 3
  },
  {
    "X": 3.76509356,
    "Y": 40.00177,
    "Floor": 3
  },
  {
    "X": 3.5642128,
    "Y": 39.99764,
    "Floor": 3
  },
  {
    "X": 3.36380768,
    "Y": 40.0056343,
    "Floor": 3
  },
  {
    "X": 3.16333961,
    "Y": 40.0041733,
    "Floor": 3
  },
  {
    "X": 2.96314454,
    "Y": 39.992794,
    "Floor": 3
  },
  {
    "X": 3.480229,
    "Y": 40.9121246,
    "Floor": 3
  },
  {
    "X": 3.25708413,
    "Y": 40.9051628,
    "Floor": 3
  },
  {
    "X": 3.0340488,
    "Y": 40.90358,
    "Floor": 3
  },
  {
    "X": 2.81144881,
    "Y": 40.92631,
    "Floor": 3
  },
  {
    "X": 2.5882504,
    "Y": 40.92982,
    "Floor": 3
  },
  {
    "X": 2.364658,
    "Y": 40.9239273,
    "Floor": 3
  },
  {
    "X": 2.14151978,
    "Y": 40.9312973,
    "Floor": 3
  },
  {
    "X": 1.92014813,
    "Y": 40.90251,
    "Floor": 3
  },
  {
    "X": 1.698143,
    "Y": 40.8833122,
    "Floor": 3
  },
  {
    "X": 1.6253289,
    "Y": 41.44753,
    "Floor": 3
  },
  {
    "X": 1.34164274,
    "Y": 41.40914,
    "Floor": 3
  },
  {
    "X": 1.057089,
    "Y": 41.37944,
    "Floor": 3
  },
  {
    "X": 0.770518541,
    "Y": 41.37953,
    "Floor": 3
  },
  {
    "X": 0.4834567,
    "Y": 41.3748856,
    "Floor": 3
  },
  {
    "X": 0.1969074,
    "Y": 41.3710976,
    "Floor": 3
  },
  {
    "X": -0.08869558,
    "Y": 41.3514023,
    "Floor": 3
  },
  {
    "X": -0.368787527,
    "Y": 41.291153,
    "Floor": 3
  },
  {
    "X": -0.6543571,
    "Y": 41.2647,
    "Floor": 3
  },
  {
    "X": -0.8747034,
    "Y": 41.739418,
    "Floor": 3
  },
  {
    "X": -1.17124021,
    "Y": 41.725502,
    "Floor": 3
  },
  {
    "X": -1.46880937,
    "Y": 41.7264671,
    "Floor": 3
  },
  {
    "X": -1.76450121,
    "Y": 41.698513,
    "Floor": 3
  },
  {
    "X": -2.05952144,
    "Y": 41.65921,
    "Floor": 3
  },
  {
    "X": -2.35570669,
    "Y": 41.6372833,
    "Floor": 3
  },
  {
    "X": -2.64993262,
    "Y": 41.5977745,
    "Floor": 3
  },
  {
    "X": -2.94625139,
    "Y": 41.6015053,
    "Floor": 3
  },
  {
    "X": -3.24262476,
    "Y": 41.62076,
    "Floor": 3
  },
  {
    "X": -3.54006553,
    "Y": 41.6126976,
    "Floor": 3
  },
  {
    "X": -3.10244632,
    "Y": 42.050602,
    "Floor": 3
  },
  {
    "X": -3.30943131,
    "Y": 42.0706635,
    "Floor": 3
  },
  {
    "X": -3.51745319,
    "Y": 42.0816,
    "Floor": 3
  },
  {
    "X": -3.72511935,
    "Y": 42.09252,
    "Floor": 3
  },
  {
    "X": -3.93293023,
    "Y": 42.0994835,
    "Floor": 3
  },
  {
    "X": -4.14088058,
    "Y": 42.0876236,
    "Floor": 3
  },
  {
    "X": -4.34876,
    "Y": 42.0829926,
    "Floor": 3
  },
  {
    "X": -4.55661154,
    "Y": 42.07618,
    "Floor": 3
  },
  {
    "X": -4.764214,
    "Y": 42.08466,
    "Floor": 3
  },
  {
    "X": -4.787526,
    "Y": 42.35422,
    "Floor": 3
  },
  {
    "X": -5.03513527,
    "Y": 42.3650322,
    "Floor": 3
  },
  {
    "X": -5.282799,
    "Y": 42.37476,
    "Floor": 3
  },
  {
    "X": -5.531063,
    "Y": 42.3771553,
    "Floor": 3
  },
  {
    "X": -5.77876425,
    "Y": 42.384037,
    "Floor": 3
  },
  {
    "X": -6.02461672,
    "Y": 42.414875,
    "Floor": 3
  },
  {
    "X": -6.27100039,
    "Y": 42.44508,
    "Floor": 3
  },
  {
    "X": -6.51869,
    "Y": 42.4432755,
    "Floor": 3
  },
  {
    "X": -6.766128,
    "Y": 42.4290161,
    "Floor": 3
  },
  {
    "X": -6.38642263,
    "Y": 42.6470642,
    "Floor": 3
  },
  {
    "X": -6.57195234,
    "Y": 42.6553154,
    "Floor": 3
  },
  {
    "X": -6.75725174,
    "Y": 42.6676064,
    "Floor": 3
  },
  {
    "X": -6.9427557,
    "Y": 42.6613541,
    "Floor": 3
  },
  {
    "X": -7.12772846,
    "Y": 42.64516,
    "Floor": 3
  },
  {
    "X": -7.313338,
    "Y": 42.65502,
    "Floor": 3
  },
  {
    "X": -7.497961,
    "Y": 42.6717224,
    "Floor": 3
  },
  {
    "X": -7.68358755,
    "Y": 42.68416,
    "Floor": 3
  },
  {
    "X": -7.86824226,
    "Y": 42.70316,
    "Floor": 3
  },
  {
    "X": -8.051903,
    "Y": 42.73068,
    "Floor": 3
  },
  {
    "X": -7.317441,
    "Y": 42.7345352,
    "Floor": 3
  },
  {
    "X": -7.44746637,
    "Y": 42.73115,
    "Floor": 3
  },
  {
    "X": -7.57559872,
    "Y": 42.7528725,
    "Floor": 3
  },
  {
    "X": -7.70510244,
    "Y": 42.7632561,
    "Floor": 3
  },
  {
    "X": -7.834658,
    "Y": 42.7733536,
    "Floor": 3
  },
  {
    "X": -7.963343,
    "Y": 42.7918167,
    "Floor": 3
  },
  {
    "X": -8.092689,
    "Y": 42.8047638,
    "Floor": 3
  },
  {
    "X": -8.221921,
    "Y": 42.818737,
    "Floor": 3
  },
  {
    "X": -8.351343,
    "Y": 42.83049,
    "Floor": 3
  },
  {
    "X": -7.640768,
    "Y": 42.78007,
    "Floor": 3
  },
  {
    "X": -7.74651527,
    "Y": 42.7960358,
    "Floor": 3
  },
  {
    "X": -7.85240126,
    "Y": 42.8109,
    "Floor": 3
  },
  {
    "X": -7.95952749,
    "Y": 42.813343,
    "Floor": 3
  },
  {
    "X": -8.066054,
    "Y": 42.82027,
    "Floor": 3
  },
  {
    "X": -8.1731205,
    "Y": 42.8238258,
    "Floor": 3
  },
  {
    "X": -8.279846,
    "Y": 42.8261147,
    "Floor": 3
  },
  {
    "X": -8.386549,
    "Y": 42.83605,
    "Floor": 3
  },
  {
    "X": -8.493429,
    "Y": 42.83686,
    "Floor": 3
  },
  {
    "X": -8.59015751,
    "Y": 42.7568474,
    "Floor": 3
  },
  {
    "X": -8.78088951,
    "Y": 42.7458725,
    "Floor": 3
  },
  {
    "X": -8.971719,
    "Y": 42.7367477,
    "Floor": 3
  },
  {
    "X": -9.162634,
    "Y": 42.7300148,
    "Floor": 3
  },
  {
    "X": -9.353485,
    "Y": 42.7383,
    "Floor": 3
  },
  {
    "X": -9.544304,
    "Y": 42.7315,
    "Floor": 3
  },
  {
    "X": -9.733797,
    "Y": 42.70729,
    "Floor": 3
  },
  {
    "X": -9.92414951,
    "Y": 42.6875534,
    "Floor": 3
  },
  {
    "X": -10.1134462,
    "Y": 42.6620178,
    "Floor": 3
  },
  {
    "X": -9.908698,
    "Y": 42.6229019,
    "Floor": 3
  },
  {
    "X": -10.0420713,
    "Y": 42.6133575,
    "Floor": 3
  },
  {
    "X": -10.1747065,
    "Y": 42.59538,
    "Floor": 3
  },
  {
    "X": -10.3046474,
    "Y": 42.56478,
    "Floor": 3
  },
  {
    "X": -10.4370871,
    "Y": 42.5449944,
    "Floor": 3
  },
  {
    "X": -10.5705528,
    "Y": 42.53696,
    "Floor": 3
  },
  {
    "X": -10.7042255,
    "Y": 42.53292,
    "Floor": 3
  },
  {
    "X": -10.83785,
    "Y": 42.5368729,
    "Floor": 3
  },
  {
    "X": -10.9716234,
    "Y": 42.5340462,
    "Floor": 3
  },
  {
    "X": -14.2551918,
    "Y": 43.15897,
    "Floor": 3
  },
  {
    "X": -14.8858652,
    "Y": 43.1630936,
    "Floor": 3
  },
  {
    "X": -15.5173206,
    "Y": 43.156498,
    "Floor": 3
  },
  {
    "X": -16.1451,
    "Y": 43.09656,
    "Floor": 3
  },
  {
    "X": -16.7672176,
    "Y": 42.99442,
    "Floor": 3
  },
  {
    "X": -17.3523827,
    "Y": 42.7657547,
    "Floor": 3
  },
  {
    "X": -17.87539,
    "Y": 42.4136734,
    "Floor": 3
  },
  {
    "X": -18.3984013,
    "Y": 42.0613937,
    "Floor": 3
  },
  {
    "X": -18.940403,
    "Y": 41.7367058,
    "Floor": 3
  },
  {
    "X": -19.976664351567894,
    "Y": 43.32828639898805,
    "Floor": 3
  },
  {
    "X": -20.373669551567893,
    "Y": 43.13573959898805,
    "Floor": 3
  },
  {
    "X": -20.777074351567894,
    "Y": 42.95656709898805,
    "Floor": 3
  },
  {
    "X": -21.147900451567892,
    "Y": 42.71839639898805,
    "Floor": 3
  },
  {
    "X": -21.483771251567894,
    "Y": 42.43195459898805,
    "Floor": 3
  },
  {
    "X": -21.803986451567894,
    "Y": 42.12807969898805,
    "Floor": 3
  },
  {
    "X": -22.104128751567895,
    "Y": 41.803292298988055,
    "Floor": 3
  },
  {
    "X": -22.474764351567895,
    "Y": 41.57450599898805,
    "Floor": 3
  },
  {
    "X": -22.907644351567892,
    "Y": 41.61074949898805,
    "Floor": 3
  },
  {
    "X": -23.118931651567895,
    "Y": 42.829396498988054,
    "Floor": 3
  },
  {
    "X": -23.349669351567893,
    "Y": 43.105260098988055,
    "Floor": 3
  },
  {
    "X": -23.513928351567895,
    "Y": 43.42403529898805,
    "Floor": 3
  },
  {
    "X": -23.643804351567894,
    "Y": 43.75931669898805,
    "Floor": 3
  },
  {
    "X": -23.766205651567894,
    "Y": 44.09742859898805,
    "Floor": 3
  },
  {
    "X": -23.926766251567894,
    "Y": 44.41912229898805,
    "Floor": 3
  },
  {
    "X": -24.089110251567895,
    "Y": 44.740006698988054,
    "Floor": 3
  },
  {
    "X": -24.266664351567893,
    "Y": 45.052752298988054,
    "Floor": 3
  },
  {
    "X": -24.413363351567895,
    "Y": 45.381572298988054,
    "Floor": 3
  },
  {
    "X": -24.532721451567895,
    "Y": 45.72012449898805,
    "Floor": 3
  },
  {
    "X": -24.6220455,
    "Y": 45.0200958,
    "Floor": 3
  },
  {
    "X": -24.7314873,
    "Y": 45.30092,
    "Floor": 3
  },
  {
    "X": -24.8393936,
    "Y": 45.5817451,
    "Floor": 3
  },
  {
    "X": -24.9549236,
    "Y": 45.8595352,
    "Floor": 3
  },
  {
    "X": -25.0566158,
    "Y": 46.142662,
    "Floor": 3
  },
  {
    "X": -25.1420631,
    "Y": 46.4309273,
    "Floor": 3
  },
  {
    "X": -25.1975975,
    "Y": 46.7265968,
    "Floor": 3
  },
  {
    "X": -25.29767,
    "Y": 47.0097847,
    "Floor": 3
  },
  {
    "X": -25.43353,
    "Y": 47.27878,
    "Floor": 3
  },
  {
    "X": -24.7695942,
    "Y": 46.9049339,
    "Floor": 3
  },
  {
    "X": -24.88953,
    "Y": 47.0785027,
    "Floor": 3
  },
  {
    "X": -25.00218,
    "Y": 47.2564278,
    "Floor": 3
  },
  {
    "X": -25.12972,
    "Y": 47.4237976,
    "Floor": 3
  },
  {
    "X": -25.2728767,
    "Y": 47.5782051,
    "Floor": 3
  },
  {
    "X": -25.43397,
    "Y": 47.7135735,
    "Floor": 3
  },
  {
    "X": -25.60513,
    "Y": 47.8362846,
    "Floor": 3
  },
  {
    "X": -25.7746,
    "Y": 47.96194,
    "Floor": 3
  },
  {
    "X": -25.9464245,
    "Y": 48.0835762,
    "Floor": 3
  },
  {
    "X": -26.1274815,
    "Y": 48.1910744,
    "Floor": 3
  },
  {
    "X": -25.7130089,
    "Y": 47.5176125,
    "Floor": 3
  },
  {
    "X": -25.8795242,
    "Y": 47.61385,
    "Floor": 3
  },
  {
    "X": -26.06196,
    "Y": 47.6758461,
    "Floor": 3
  },
  {
    "X": -26.2457256,
    "Y": 47.733284,
    "Floor": 3
  },
  {
    "X": -26.4275742,
    "Y": 47.79672,
    "Floor": 3
  },
  {
    "X": -26.6141186,
    "Y": 47.8441429,
    "Floor": 3
  },
  {
    "X": -26.8006268,
    "Y": 47.891468,
    "Floor": 3
  },
  {
    "X": -26.9867039,
    "Y": 47.9406357,
    "Floor": 3
  },
  {
    "X": -27.1781311,
    "Y": 47.9273,
    "Floor": 3
  },
  {
    "X": -26.5695381,
    "Y": 47.1857758,
    "Floor": 3
  },
  {
    "X": -26.7094612,
    "Y": 47.1685448,
    "Floor": 3
  },
  {
    "X": -26.85065,
    "Y": 47.1707649,
    "Floor": 3
  },
  {
    "X": -26.99182,
    "Y": 47.17176,
    "Floor": 3
  },
  {
    "X": -27.1316357,
    "Y": 47.1913071,
    "Floor": 3
  },
  {
    "X": -27.2726288,
    "Y": 47.19385,
    "Floor": 3
  },
  {
    "X": -27.41035,
    "Y": 47.164196,
    "Floor": 3
  },
  {
    "X": -27.5506439,
    "Y": 47.14862,
    "Floor": 3
  },
  {
    "X": -27.691824,
    "Y": 47.1460533,
    "Floor": 3
  },
  {
    "X": -27.1292439,
    "Y": 46.9512,
    "Floor": 3
  },
  {
    "X": -27.28472,
    "Y": 46.9495049,
    "Floor": 3
  },
  {
    "X": -27.4395332,
    "Y": 46.96602,
    "Floor": 3
  },
  {
    "X": -27.59534,
    "Y": 46.96357,
    "Floor": 3
  },
  {
    "X": -27.7509365,
    "Y": 46.9617767,
    "Floor": 3
  },
  {
    "X": -27.90524,
    "Y": 46.98149,
    "Floor": 3
  },
  {
    "X": -28.0585575,
    "Y": 47.0083046,
    "Floor": 3
  },
  {
    "X": -28.21257,
    "Y": 47.0306168,
    "Floor": 3
  },
  {
    "X": -28.3633041,
    "Y": 47.070694,
    "Floor": 3
  },
  {
    "X": -27.5540524,
    "Y": 46.9219742,
    "Floor": 3
  },
  {
    "X": -27.6620255,
    "Y": 46.9380646,
    "Floor": 3
  },
  {
    "X": -27.7674732,
    "Y": 46.96542,
    "Floor": 3
  },
  {
    "X": -27.8715076,
    "Y": 46.99727,
    "Floor": 3
  },
  {
    "X": -27.9765377,
    "Y": 47.02706,
    "Floor": 3
  },
  {
    "X": -28.079998,
    "Y": 47.0610962,
    "Floor": 3
  },
  {
    "X": -28.1840286,
    "Y": 47.09319,
    "Floor": 3
  },
  {
    "X": -28.29128,
    "Y": 47.11254,
    "Floor": 3
  },
  {
    "X": -28.39544,
    "Y": 47.1448059,
    "Floor": 3
  },
  {
    "X": -29.5309677,
    "Y": 47.0148735,
    "Floor": 3
  },
  {
    "X": -29.871767,
    "Y": 47.1371651,
    "Floor": 3
  },
  {
    "X": -30.2150478,
    "Y": 47.25023,
    "Floor": 3
  },
  {
    "X": -30.5612946,
    "Y": 47.35376,
    "Floor": 3
  },
  {
    "X": -30.9158955,
    "Y": 47.4224434,
    "Floor": 3
  },
  {
    "X": -31.2763348,
    "Y": 47.447403,
    "Floor": 3
  },
  {
    "X": -31.6340523,
    "Y": 47.49616,
    "Floor": 3
  },
  {
    "X": -31.98614,
    "Y": 47.58062,
    "Floor": 3
  },
  {
    "X": -32.3431854,
    "Y": 47.64025,
    "Floor": 3
  },
  {
    "X": -32.70238,
    "Y": 47.6803131,
    "Floor": 3
  },
  {
    "X": -32.7681732,
    "Y": 47.3548279,
    "Floor": 3
  },
  {
    "X": -33.02735,
    "Y": 47.36509,
    "Floor": 3
  },
  {
    "X": -33.28558,
    "Y": 47.33757,
    "Floor": 3
  },
  {
    "X": -33.5446854,
    "Y": 47.31954,
    "Floor": 3
  },
  {
    "X": -33.8045731,
    "Y": 47.3068848,
    "Floor": 3
  },
  {
    "X": -34.0634651,
    "Y": 47.2872,
    "Floor": 3
  },
  {
    "X": -34.32083,
    "Y": 47.2521973,
    "Floor": 3
  },
  {
    "X": -34.5801544,
    "Y": 47.2308273,
    "Floor": 3
  },
  {
    "X": -34.8357773,
    "Y": 47.18586,
    "Floor": 3
  },
  {
    "X": -34.565052,
    "Y": 47.0231361,
    "Floor": 3
  },
  {
    "X": -34.77306,
    "Y": 46.9797745,
    "Floor": 3
  },
  {
    "X": -34.98478,
    "Y": 46.9607849,
    "Floor": 3
  },
  {
    "X": -35.1966743,
    "Y": 46.94392,
    "Floor": 3
  },
  {
    "X": -35.4091148,
    "Y": 46.93622,
    "Floor": 3
  },
  {
    "X": -35.619545,
    "Y": 46.904583,
    "Floor": 3
  },
  {
    "X": -35.8262253,
    "Y": 46.85327,
    "Floor": 3
  },
  {
    "X": -36.036026,
    "Y": 46.820343,
    "Floor": 3
  },
  {
    "X": -36.2485161,
    "Y": 46.8221779,
    "Floor": 3
  },
  {
    "X": -35.71841,
    "Y": 46.75252,
    "Floor": 3
  },
  {
    "X": -35.86611,
    "Y": 46.7328835,
    "Floor": 3
  },
  {
    "X": -36.0149,
    "Y": 46.7316628,
    "Floor": 3
  },
  {
    "X": -36.16282,
    "Y": 46.71674,
    "Floor": 3
  },
  {
    "X": -36.3109245,
    "Y": 46.700882,
    "Floor": 3
  },
  {
    "X": -36.45974,
    "Y": 46.6999626,
    "Floor": 3
  },
  {
    "X": -36.60855,
    "Y": 46.7000275,
    "Floor": 3
  },
  {
    "X": -36.7573051,
    "Y": 46.7088432,
    "Floor": 3
  },
  {
    "X": -36.90541,
    "Y": 46.723278,
    "Floor": 3
  },
  {
    "X": -36.47341,
    "Y": 46.69656,
    "Floor": 3
  },
  {
    "X": -36.61194,
    "Y": 46.6859131,
    "Floor": 3
  },
  {
    "X": -36.75087,
    "Y": 46.6862068,
    "Floor": 3
  },
  {
    "X": -36.8899345,
    "Y": 46.68074,
    "Floor": 3
  },
  {
    "X": -37.028614,
    "Y": 46.6723328,
    "Floor": 3
  },
  {
    "X": -37.1678047,
    "Y": 46.6724358,
    "Floor": 3
  },
  {
    "X": -37.30524,
    "Y": 46.654274,
    "Floor": 3
  },
  {
    "X": -37.4381065,
    "Y": 46.6136742,
    "Floor": 3
  },
  {
    "X": -37.5740128,
    "Y": 46.5839233,
    "Floor": 3
  },
  {
    "X": -37.70967,
    "Y": 46.555275,
    "Floor": 3
  },
  {
    "X": -37.24745,
    "Y": 46.5346451,
    "Floor": 3
  },
  {
    "X": -37.3651466,
    "Y": 46.5121155,
    "Floor": 3
  },
  {
    "X": -37.48502,
    "Y": 46.5068,
    "Floor": 3
  },
  {
    "X": -37.6014557,
    "Y": 46.4784279,
    "Floor": 3
  },
  {
    "X": -37.7109871,
    "Y": 46.4294662,
    "Floor": 3
  },
  {
    "X": -37.8237572,
    "Y": 46.3888359,
    "Floor": 3
  },
  {
    "X": -37.9398041,
    "Y": 46.3574638,
    "Floor": 3
  },
  {
    "X": -38.0519638,
    "Y": 46.3148842,
    "Floor": 3
  },
  {
    "X": -38.16051,
    "Y": 46.2636871,
    "Floor": 3
  },
  {
    "X": -37.37485,
    "Y": 46.37051,
    "Floor": 3
  },
  {
    "X": -37.46986,
    "Y": 46.3081932,
    "Floor": 3
  },
  {
    "X": -37.5459328,
    "Y": 46.223732,
    "Floor": 3
  },
  {
    "X": -37.6185837,
    "Y": 46.1359367,
    "Floor": 3
  },
  {
    "X": -37.6664162,
    "Y": 46.0331459,
    "Floor": 3
  },
  {
    "X": -37.6903343,
    "Y": 45.92197,
    "Floor": 3
  },
  {
    "X": -37.71613,
    "Y": 45.81097,
    "Floor": 3
  },
  {
    "X": -37.73751,
    "Y": 45.6993561,
    "Floor": 3
  },
  {
    "X": -37.73123,
    "Y": 45.58599,
    "Floor": 3
  },
  {
    "X": -36.9366646,
    "Y": 45.8247337,
    "Floor": 3
  },
  {
    "X": -36.9089928,
    "Y": 45.75005,
    "Floor": 3
  },
  {
    "X": -36.88758,
    "Y": 45.673214,
    "Floor": 3
  },
  {
    "X": -36.8750038,
    "Y": 45.5945969,
    "Floor": 3
  },
  {
    "X": -36.86292,
    "Y": 45.51572,
    "Floor": 3
  },
  {
    "X": -36.8484039,
    "Y": 45.4374046,
    "Floor": 3
  },
  {
    "X": -36.8325,
    "Y": 45.3593979,
    "Floor": 3
  },
  {
    "X": -36.8136749,
    "Y": 45.2818756,
    "Floor": 3
  },
  {
    "X": -36.7996,
    "Y": 45.203476,
    "Floor": 3
  },
  {
    "X": -36.54423,
    "Y": 45.2268181,
    "Floor": 3
  },
  {
    "X": -36.5424,
    "Y": 45.110775,
    "Floor": 3
  },
  {
    "X": -36.5331421,
    "Y": 44.99486,
    "Floor": 3
  },
  {
    "X": -36.51785,
    "Y": 44.879837,
    "Floor": 3
  },
  {
    "X": -36.4972229,
    "Y": 44.7654076,
    "Floor": 3
  },
  {
    "X": -36.4785271,
    "Y": 44.650856,
    "Floor": 3
  },
  {
    "X": -36.4613266,
    "Y": 44.53593,
    "Floor": 3
  },
  {
    "X": -36.4185448,
    "Y": 44.4281158,
    "Floor": 3
  },
  {
    "X": -36.39416,
    "Y": 44.314682,
    "Floor": 3
  },
  {
    "X": -36.5427856,
    "Y": 44.0120049,
    "Floor": 3
  },
  {
    "X": -36.4783859,
    "Y": 43.85589,
    "Floor": 3
  },
  {
    "X": -36.4258156,
    "Y": 43.695076,
    "Floor": 3
  },
  {
    "X": -36.36581,
    "Y": 43.5372849,
    "Floor": 3
  },
  {
    "X": -36.3064346,
    "Y": 43.3789444,
    "Floor": 3
  },
  {
    "X": -36.2447281,
    "Y": 43.2214546,
    "Floor": 3
  },
  {
    "X": -36.17745,
    "Y": 43.06689,
    "Floor": 3
  },
  {
    "X": -36.1071548,
    "Y": 42.9133377,
    "Floor": 3
  },
  {
    "X": -36.03937,
    "Y": 42.758316,
    "Floor": 3
  },
  {
    "X": -36.2723122,
    "Y": 41.4963264,
    "Floor": 3
  },
  {
    "X": -36.17051,
    "Y": 41.21248,
    "Floor": 3
  },
  {
    "X": -36.05945,
    "Y": 40.9315453,
    "Floor": 3
  },
  {
    "X": -35.950737,
    "Y": 40.6496925,
    "Floor": 3
  },
  {
    "X": -35.8229523,
    "Y": 40.37657,
    "Floor": 3
  },
  {
    "X": -35.71288,
    "Y": 40.09529,
    "Floor": 3
  },
  {
    "X": -35.61369,
    "Y": 39.81052,
    "Floor": 3
  },
  {
    "X": -35.51755,
    "Y": 39.5246964,
    "Floor": 3
  },
  {
    "X": -35.4288177,
    "Y": 39.236496,
    "Floor": 3
  },
  {
    "X": -35.89057,
    "Y": 38.7449532,
    "Floor": 3
  },
  {
    "X": -35.8126068,
    "Y": 38.54882,
    "Floor": 3
  },
  {
    "X": -35.75007,
    "Y": 38.3468361,
    "Floor": 3
  },
  {
    "X": -35.6921844,
    "Y": 38.14384,
    "Floor": 3
  },
  {
    "X": -35.65328,
    "Y": 37.93607,
    "Floor": 3
  },
  {
    "X": -35.62084,
    "Y": 37.72748,
    "Floor": 3
  },
  {
    "X": -35.5743866,
    "Y": 37.52167,
    "Floor": 3
  },
  {
    "X": -35.517334,
    "Y": 37.318428,
    "Floor": 3
  },
  {
    "X": -35.4746,
    "Y": 37.1114044,
    "Floor": 3
  },
  {
    "X": -36.0613632,
    "Y": 36.9683456,
    "Floor": 3
  },
  {
    "X": -36.0527763,
    "Y": 36.79969,
    "Floor": 3
  },
  {
    "X": -36.01741,
    "Y": 36.6345177,
    "Floor": 3
  },
  {
    "X": -35.97616,
    "Y": 36.4704475,
    "Floor": 3
  },
  {
    "X": -35.92564,
    "Y": 36.30927,
    "Floor": 3
  },
  {
    "X": -35.8822823,
    "Y": 36.14604,
    "Floor": 3
  },
  {
    "X": -35.8464127,
    "Y": 35.9806747,
    "Floor": 3
  },
  {
    "X": -35.8148232,
    "Y": 35.8150635,
    "Floor": 3
  },
  {
    "X": -35.7836266,
    "Y": 35.64883,
    "Floor": 3
  },
  {
    "X": -36.3532944,
    "Y": 35.86394,
    "Floor": 3
  },
  {
    "X": -36.3308,
    "Y": 35.747654,
    "Floor": 3
  },
  {
    "X": -36.3124924,
    "Y": 35.63084,
    "Floor": 3
  },
  {
    "X": -36.3012733,
    "Y": 35.51297,
    "Floor": 3
  },
  {
    "X": -36.29248,
    "Y": 35.3948631,
    "Floor": 3
  },
  {
    "X": -36.273983,
    "Y": 35.2780838,
    "Floor": 3
  },
  {
    "X": -36.25655,
    "Y": 35.1611328,
    "Floor": 3
  },
  {
    "X": -36.23892,
    "Y": 35.044014,
    "Floor": 3
  },
  {
    "X": -36.22573,
    "Y": 34.9263039,
    "Floor": 3
  },
  {
    "X": -36.2162628,
    "Y": 34.8084526,
    "Floor": 3
  },
  {
    "X": -36.8056145,
    "Y": 34.8487167,
    "Floor": 3
  },
  {
    "X": -36.7814522,
    "Y": 34.71149,
    "Floor": 3
  },
  {
    "X": -36.7423553,
    "Y": 34.5777321,
    "Floor": 3
  },
  {
    "X": -36.7137947,
    "Y": 34.44117,
    "Floor": 3
  },
  {
    "X": -36.7053375,
    "Y": 34.3022232,
    "Floor": 3
  },
  {
    "X": -36.7190742,
    "Y": 34.1632919,
    "Floor": 3
  },
  {
    "X": -36.7094269,
    "Y": 34.0246544,
    "Floor": 3
  },
  {
    "X": -36.68174,
    "Y": 33.8877869,
    "Floor": 3
  },
  {
    "X": -36.6604729,
    "Y": 33.75005,
    "Floor": 3
  },
  {
    "X": -37.1563034,
    "Y": 34.0363464,
    "Floor": 3
  },
  {
    "X": -37.1272278,
    "Y": 33.9432831,
    "Floor": 3
  },
  {
    "X": -37.1142273,
    "Y": 33.8467,
    "Floor": 3
  },
  {
    "X": -37.1022644,
    "Y": 33.7497673,
    "Floor": 3
  },
  {
    "X": -37.0802,
    "Y": 33.6547241,
    "Floor": 3
  },
  {
    "X": -37.0553322,
    "Y": 33.56038,
    "Floor": 3
  },
  {
    "X": -37.0374451,
    "Y": 33.46411,
    "Floor": 3
  },
  {
    "X": -37.01488,
    "Y": 33.3692,
    "Floor": 3
  },
  {
    "X": -37.00842,
    "Y": 33.27183,
    "Floor": 3
  },
  {
    "X": -37.5250473,
    "Y": 32.68835,
    "Floor": 3
  },
  {
    "X": -37.48014,
    "Y": 32.4827461,
    "Floor": 3
  },
  {
    "X": -37.4068642,
    "Y": 32.2857437,
    "Floor": 3
  },
  {
    "X": -37.34222,
    "Y": 32.0853462,
    "Floor": 3
  },
  {
    "X": -37.2922134,
    "Y": 31.88082,
    "Floor": 3
  },
  {
    "X": -37.2565346,
    "Y": 31.67365,
    "Floor": 3
  },
  {
    "X": -37.2033234,
    "Y": 31.469944,
    "Floor": 3
  },
  {
    "X": -37.1367149,
    "Y": 31.2701836,
    "Floor": 3
  },
  {
    "X": -37.0598,
    "Y": 31.0745335,
    "Floor": 3
  },
  {
    "X": -36.99576,
    "Y": 30.874485,
    "Floor": 3
  },
  {
    "X": -37.5423546,
    "Y": 30.71208,
    "Floor": 3
  },
  {
    "X": -37.5133667,
    "Y": 30.5613422,
    "Floor": 3
  },
  {
    "X": -37.4663,
    "Y": 30.4153233,
    "Floor": 3
  },
  {
    "X": -37.4074326,
    "Y": 30.2732525,
    "Floor": 3
  },
  {
    "X": -37.3508,
    "Y": 30.1305733,
    "Floor": 3
  },
  {
    "X": -37.3026581,
    "Y": 29.9845333,
    "Floor": 3
  },
  {
    "X": -37.25748,
    "Y": 29.8378315,
    "Floor": 3
  },
  {
    "X": -37.1967239,
    "Y": 29.696888,
    "Floor": 3
  },
  {
    "X": -37.13526,
    "Y": 29.555912,
    "Floor": 3
  },
  {
    "X": -37.99688,
    "Y": 29.5141621,
    "Floor": 3
  },
  {
    "X": -37.9355927,
    "Y": 29.3538036,
    "Floor": 3
  },
  {
    "X": -37.87684,
    "Y": 29.1928844,
    "Floor": 3
  },
  {
    "X": -37.82757,
    "Y": 29.0287971,
    "Floor": 3
  },
  {
    "X": -37.7616234,
    "Y": 28.8703289,
    "Floor": 3
  },
  {
    "X": -37.6880836,
    "Y": 28.7155647,
    "Floor": 3
  },
  {
    "X": -37.62409,
    "Y": 28.556797,
    "Floor": 3
  },
  {
    "X": -37.5758629,
    "Y": 28.3920441,
    "Floor": 3
  },
  {
    "X": -37.53801,
    "Y": 28.2250423,
    "Floor": 3
  },
  {
    "X": -37.51033,
    "Y": 28.0559311,
    "Floor": 3
  },
  {
    "X": -38.3214149,
    "Y": 28.25826,
    "Floor": 3
  },
  {
    "X": -38.29041,
    "Y": 28.12582,
    "Floor": 3
  },
  {
    "X": -38.26376,
    "Y": 27.992712,
    "Floor": 3
  },
  {
    "X": -38.25497,
    "Y": 27.8573532,
    "Floor": 3
  },
  {
    "X": -38.2480927,
    "Y": 27.7215519,
    "Floor": 3
  },
  {
    "X": -38.2287025,
    "Y": 27.586937,
    "Floor": 3
  },
  {
    "X": -38.21145,
    "Y": 27.45228,
    "Floor": 3
  },
  {
    "X": -38.20065,
    "Y": 27.31692,
    "Floor": 3
  },
  {
    "X": -38.1840172,
    "Y": 27.181921,
    "Floor": 3
  },
  {
    "X": -38.8456078,
    "Y": 27.715044,
    "Floor": 3
  },
  {
    "X": -38.8378,
    "Y": 27.6203423,
    "Floor": 3
  },
  {
    "X": -38.8208961,
    "Y": 27.5268345,
    "Floor": 3
  },
  {
    "X": -38.8032379,
    "Y": 27.43327,
    "Floor": 3
  },
  {
    "X": -38.7863579,
    "Y": 27.3397312,
    "Floor": 3
  },
  {
    "X": -38.77024,
    "Y": 27.2459,
    "Floor": 3
  },
  {
    "X": -38.7634163,
    "Y": 27.151104,
    "Floor": 3
  },
  {
    "X": -38.74686,
    "Y": 27.05739,
    "Floor": 3
  },
  {
    "X": -38.7289,
    "Y": 26.9640617,
    "Floor": 3
  },
  {
    "X": -38.70813,
    "Y": 26.8772888,
    "Floor": 3
  },
  {
    "X": -38.63969,
    "Y": 26.3580074,
    "Floor": 3
  },
  {
    "X": -38.5852928,
    "Y": 26.1305256,
    "Floor": 3
  },
  {
    "X": -38.5587845,
    "Y": 25.8977222,
    "Floor": 3
  },
  {
    "X": -38.5617638,
    "Y": 25.66388,
    "Floor": 3
  },
  {
    "X": -38.5782738,
    "Y": 25.4300423,
    "Floor": 3
  },
  {
    "X": -38.5875664,
    "Y": 25.1963081,
    "Floor": 3
  },
  {
    "X": -38.566925,
    "Y": 24.9633942,
    "Floor": 3
  },
  {
    "X": -38.5235252,
    "Y": 24.7331161,
    "Floor": 3
  },
  {
    "X": -38.4361267,
    "Y": 24.5171547,
    "Floor": 3
  },
  {
    "X": -37.99044,
    "Y": 23.17295,
    "Floor": 3
  },
  {
    "X": -37.72546,
    "Y": 22.9363155,
    "Floor": 3
  },
  {
    "X": -37.49279,
    "Y": 22.6687775,
    "Floor": 3
  },
  {
    "X": -37.2902374,
    "Y": 22.3768673,
    "Floor": 3
  },
  {
    "X": -37.1311226,
    "Y": 22.0601444,
    "Floor": 3
  },
  {
    "X": -36.9888458,
    "Y": 21.7344532,
    "Floor": 3
  },
  {
    "X": -36.866024,
    "Y": 21.4018536,
    "Floor": 3
  },
  {
    "X": -36.7777328,
    "Y": 21.0577679,
    "Floor": 3
  },
  {
    "X": -36.693512,
    "Y": 20.7134132,
    "Floor": 3
  },
  {
    "X": -36.71923,
    "Y": 19.7648659,
    "Floor": 3
  },
  {
    "X": -36.60522,
    "Y": 19.4921246,
    "Floor": 3
  },
  {
    "X": -36.472496,
    "Y": 19.22854,
    "Floor": 3
  },
  {
    "X": -36.360363,
    "Y": 18.955658,
    "Floor": 3
  },
  {
    "X": -36.2704926,
    "Y": 18.67418,
    "Floor": 3
  },
  {
    "X": -36.2212677,
    "Y": 18.38278,
    "Floor": 3
  },
  {
    "X": -36.1662369,
    "Y": 18.0930767,
    "Floor": 3
  },
  {
    "X": -36.09024,
    "Y": 17.8079166,
    "Floor": 3
  },
  {
    "X": -36.0191841,
    "Y": 17.5209274,
    "Floor": 3
  },
  {
    "X": -36.2243652,
    "Y": 17.3413544,
    "Floor": 3
  },
  {
    "X": -36.18984,
    "Y": 17.1374989,
    "Floor": 3
  },
  {
    "X": -36.1700859,
    "Y": 16.9318619,
    "Floor": 3
  },
  {
    "X": -36.1469345,
    "Y": 16.7262039,
    "Floor": 3
  },
  {
    "X": -36.1253662,
    "Y": 16.5207443,
    "Floor": 3
  },
  {
    "X": -36.0977821,
    "Y": 16.3156738,
    "Floor": 3
  },
  {
    "X": -36.0806961,
    "Y": 16.110199,
    "Floor": 3
  },
  {
    "X": -36.0973244,
    "Y": 15.9043045,
    "Floor": 3
  },
  {
    "X": -36.10901,
    "Y": 15.6976843,
    "Floor": 3
  },
  {
    "X": -36.36186,
    "Y": 15.7661352,
    "Floor": 3
  },
  {
    "X": -36.360405,
    "Y": 15.59398,
    "Floor": 3
  },
  {
    "X": -36.3667,
    "Y": 15.4219456,
    "Floor": 3
  },
  {
    "X": -36.372982,
    "Y": 15.2502127,
    "Floor": 3
  },
  {
    "X": -36.3859138,
    "Y": 15.07858,
    "Floor": 3
  },
  {
    "X": -36.37384,
    "Y": 14.9072962,
    "Floor": 3
  },
  {
    "X": -36.3356743,
    "Y": 14.739831,
    "Floor": 3
  },
  {
    "X": -36.29147,
    "Y": 14.5734434,
    "Floor": 3
  },
  {
    "X": -36.2559128,
    "Y": 14.4053144,
    "Floor": 3
  },
  {
    "X": -36.44596,
    "Y": 14.2332525,
    "Floor": 3
  },
  {
    "X": -36.43419,
    "Y": 14.0173988,
    "Floor": 3
  },
  {
    "X": -36.41008,
    "Y": 13.8030663,
    "Floor": 3
  },
  {
    "X": -36.3665,
    "Y": 13.5913172,
    "Floor": 3
  },
  {
    "X": -36.3266258,
    "Y": 13.3792744,
    "Floor": 3
  },
  {
    "X": -36.3131256,
    "Y": 13.1635857,
    "Floor": 3
  },
  {
    "X": -36.312355,
    "Y": 12.9478188,
    "Floor": 3
  },
  {
    "X": -36.3212242,
    "Y": 12.73182,
    "Floor": 3
  },
  {
    "X": -36.3172379,
    "Y": 12.5160666,
    "Floor": 3
  },
  {
    "X": -36.3017273,
    "Y": 12.3004436,
    "Floor": 3
  },
  {
    "X": -36.49228,
    "Y": 12.0541487,
    "Floor": 3
  },
  {
    "X": -36.4763336,
    "Y": 11.84128,
    "Floor": 3
  },
  {
    "X": -36.4600258,
    "Y": 11.62882,
    "Floor": 3
  },
  {
    "X": -36.4485664,
    "Y": 11.41567,
    "Floor": 3
  },
  {
    "X": -36.4141464,
    "Y": 11.205513,
    "Floor": 3
  },
  {
    "X": -36.3694839,
    "Y": 10.9971552,
    "Floor": 3
  },
  {
    "X": -36.3196945,
    "Y": 10.7895746,
    "Floor": 3
  },
  {
    "X": -36.2716942,
    "Y": 10.5819674,
    "Floor": 3
  },
  {
    "X": -36.2295723,
    "Y": 10.3731079,
    "Floor": 3
  },
  {
    "X": -36.37493,
    "Y": 10.6055241,
    "Floor": 3
  },
  {
    "X": -36.33619,
    "Y": 10.46154,
    "Floor": 3
  },
  {
    "X": -36.2924843,
    "Y": 10.31868,
    "Floor": 3
  },
  {
    "X": -36.2584534,
    "Y": 10.1831369,
    "Floor": 3
  },
  {
    "X": -36.2131081,
    "Y": 10.0407753,
    "Floor": 3
  },
  {
    "X": -36.1647034,
    "Y": 9.899694,
    "Floor": 3
  },
  {
    "X": -36.1307678,
    "Y": 9.754259,
    "Floor": 3
  },
  {
    "X": -36.1002,
    "Y": 9.608285,
    "Floor": 3
  },
  {
    "X": -36.0706367,
    "Y": 9.461835,
    "Floor": 3
  },
  {
    "X": -36.2414,
    "Y": 9.072697,
    "Floor": 3
  },
  {
    "X": -36.1902542,
    "Y": 8.855822,
    "Floor": 3
  },
  {
    "X": -36.1542931,
    "Y": 8.636522,
    "Floor": 3
  },
  {
    "X": -36.1638069,
    "Y": 8.41418,
    "Floor": 3
  },
  {
    "X": -36.1808548,
    "Y": 8.192441,
    "Floor": 3
  },
  {
    "X": -36.1823235,
    "Y": 7.96964073,
    "Floor": 3
  },
  {
    "X": -36.18138,
    "Y": 7.7472167,
    "Floor": 3
  },
  {
    "X": -36.18586,
    "Y": 7.524445,
    "Floor": 3
  },
  {
    "X": -36.18671,
    "Y": 7.30203772,
    "Floor": 3
  },
  {
    "X": -36.357708,
    "Y": 7.314077,
    "Floor": 3
  },
  {
    "X": -36.3626328,
    "Y": 7.15223026,
    "Floor": 3
  },
  {
    "X": -36.3595,
    "Y": 6.990395,
    "Floor": 3
  },
  {
    "X": -36.3499336,
    "Y": 6.828478,
    "Floor": 3
  },
  {
    "X": -36.34336,
    "Y": 6.66640425,
    "Floor": 3
  },
  {
    "X": -36.34288,
    "Y": 6.50450754,
    "Floor": 3
  },
  {
    "X": -36.3469429,
    "Y": 6.34240675,
    "Floor": 3
  },
  {
    "X": -36.3599739,
    "Y": 6.1810956,
    "Floor": 3
  },
  {
    "X": -36.3393631,
    "Y": 6.020384,
    "Floor": 3
  },
  {
    "X": -36.51791,
    "Y": 6.35684252,
    "Floor": 3
  },
  {
    "X": -36.506443,
    "Y": 6.22898674,
    "Floor": 3
  },
  {
    "X": -36.48962,
    "Y": 6.10181,
    "Floor": 3
  },
  {
    "X": -36.4662857,
    "Y": 5.975345,
    "Floor": 3
  },
  {
    "X": -36.4631844,
    "Y": 5.84674644,
    "Floor": 3
  },
  {
    "X": -36.45435,
    "Y": 5.718648,
    "Floor": 3
  },
  {
    "X": -36.4314461,
    "Y": 5.59208441,
    "Floor": 3
  },
  {
    "X": -36.38934,
    "Y": 5.47089052,
    "Floor": 3
  },
  {
    "X": -36.34971,
    "Y": 5.34885073,
    "Floor": 3
  },
  {
    "X": -36.5521431,
    "Y": 5.96248674,
    "Floor": 3
  },
  {
    "X": -36.5238075,
    "Y": 5.87701845,
    "Floor": 3
  },
  {
    "X": -36.49292,
    "Y": 5.79257536,
    "Floor": 3
  },
  {
    "X": -36.4590569,
    "Y": 5.70931244,
    "Floor": 3
  },
  {
    "X": -36.4228935,
    "Y": 5.626832,
    "Floor": 3
  },
  {
    "X": -36.3926239,
    "Y": 5.54216862,
    "Floor": 3
  },
  {
    "X": -36.3668633,
    "Y": 5.45592976,
    "Floor": 3
  },
  {
    "X": -36.349865,
    "Y": 5.36763954,
    "Floor": 3
  },
  {
    "X": -36.3264732,
    "Y": 5.28067732,
    "Floor": 3
  },
  {
    "X": -36.2988358,
    "Y": 5.19511747,
    "Floor": 3
  },
  {
    "X": -36.4581223,
    "Y": 5.04283953,
    "Floor": 3
  },
  {
    "X": -36.4001045,
    "Y": 4.884266,
    "Floor": 3
  },
  {
    "X": -36.3664055,
    "Y": 4.71856833,
    "Floor": 3
  },
  {
    "X": -36.3403244,
    "Y": 4.55170631,
    "Floor": 3
  },
  {
    "X": -36.3072357,
    "Y": 4.38576841,
    "Floor": 3
  },
  {
    "X": -36.2838364,
    "Y": 4.218496,
    "Floor": 3
  },
  {
    "X": -36.2614,
    "Y": 4.05109262,
    "Floor": 3
  },
  {
    "X": -36.22609,
    "Y": 3.88565254,
    "Floor": 3
  },
  {
    "X": -36.18661,
    "Y": 3.72113228,
    "Floor": 3
  },
  {
    "X": -36.4415855,
    "Y": 1.70349741,
    "Floor": 3
  },
  {
    "X": -36.3509331,
    "Y": 1.30741084,
    "Floor": 3
  },
  {
    "X": -36.2359467,
    "Y": 0.9175491,
    "Floor": 3
  },
  {
    "X": -36.06979,
    "Y": 0.546781361,
    "Floor": 3
  },
  {
    "X": -35.8929138,
    "Y": 0.180978745,
    "Floor": 3
  },
  {
    "X": -35.6959229,
    "Y": -0.175191268,
    "Floor": 3
  },
  {
    "X": -35.4961281,
    "Y": -0.5290013,
    "Floor": 3
  },
  {
    "X": -35.3082962,
    "Y": -0.8892894,
    "Floor": 3
  },
  {
    "X": -35.14183,
    "Y": -1.25990868,
    "Floor": 3
  },
  {
    "X": -35.5492134,
    "Y": -2.144419,
    "Floor": 3
  },
  {
    "X": -35.39064,
    "Y": -2.38052177,
    "Floor": 3
  },
  {
    "X": -35.23824,
    "Y": -2.62126923,
    "Floor": 3
  },
  {
    "X": -35.0825577,
    "Y": -2.85926723,
    "Floor": 3
  },
  {
    "X": -34.9535637,
    "Y": -3.112458,
    "Floor": 3
  },
  {
    "X": -34.8720665,
    "Y": -3.384737,
    "Floor": 3
  },
  {
    "X": -34.8163834,
    "Y": -3.66416335,
    "Floor": 3
  },
  {
    "X": -34.7610741,
    "Y": -3.94316721,
    "Floor": 3
  },
  {
    "X": -34.6722946,
    "Y": -4.21277,
    "Floor": 3
  },
  {
    "X": -35.2796173,
    "Y": -4.36721754,
    "Floor": 3
  },
  {
    "X": -35.25228,
    "Y": -4.564416,
    "Floor": 3
  },
  {
    "X": -35.21553,
    "Y": -4.76044,
    "Floor": 3
  },
  {
    "X": -35.2036743,
    "Y": -4.959047,
    "Floor": 3
  },
  {
    "X": -35.18519,
    "Y": -5.15722132,
    "Floor": 3
  },
  {
    "X": -35.15106,
    "Y": -5.35334444,
    "Floor": 3
  },
  {
    "X": -35.1197128,
    "Y": -5.55021238,
    "Floor": 3
  },
  {
    "X": -35.0969048,
    "Y": -5.748288,
    "Floor": 3
  },
  {
    "X": -35.03004,
    "Y": -5.93461275,
    "Floor": 3
  },
  {
    "X": -34.9294128,
    "Y": -6.06065464,
    "Floor": 3
  },
  {
    "X": -35.4333,
    "Y": -5.75739765,
    "Floor": 3
  },
  {
    "X": -35.3006058,
    "Y": -5.82317352,
    "Floor": 3
  },
  {
    "X": -35.15701,
    "Y": -5.85885859,
    "Floor": 3
  },
  {
    "X": -35.0112572,
    "Y": -5.88514137,
    "Floor": 3
  },
  {
    "X": -34.8650665,
    "Y": -5.91039228,
    "Floor": 3
  },
  {
    "X": -34.721035,
    "Y": -5.94468832,
    "Floor": 3
  },
  {
    "X": -34.57996,
    "Y": -5.9901185,
    "Floor": 3
  },
  {
    "X": -34.44879,
    "Y": -6.059335,
    "Floor": 3
  },
  {
    "X": -34.31685,
    "Y": -6.1264596,
    "Floor": 3
  },
  {
    "X": -35.0377464,
    "Y": -6.082075,
    "Floor": 3
  },
  {
    "X": -34.9177246,
    "Y": -6.164011,
    "Floor": 3
  },
  {
    "X": -34.77907,
    "Y": -6.20355272,
    "Floor": 3
  },
  {
    "X": -34.6350327,
    "Y": -6.22305536,
    "Floor": 3
  },
  {
    "X": -34.49042,
    "Y": -6.23346758,
    "Floor": 3
  },
  {
    "X": -34.34521,
    "Y": -6.228113,
    "Floor": 3
  },
  {
    "X": -34.2002335,
    "Y": -6.227753,
    "Floor": 3
  },
  {
    "X": -34.05658,
    "Y": -6.247873,
    "Floor": 3
  },
  {
    "X": -33.9122,
    "Y": -6.26444769,
    "Floor": 3
  },
  {
    "X": -33.1472359,
    "Y": -6.02352428,
    "Floor": 3
  },
  {
    "X": -32.8257942,
    "Y": -6.05501556,
    "Floor": 3
  },
  {
    "X": -32.5025864,
    "Y": -6.06867647,
    "Floor": 3
  },
  {
    "X": -32.18002,
    "Y": -6.08420467,
    "Floor": 3
  },
  {
    "X": -31.8578129,
    "Y": -6.105857,
    "Floor": 3
  },
  {
    "X": -31.5344677,
    "Y": -6.096334,
    "Floor": 3
  },
  {
    "X": -31.2116051,
    "Y": -6.09076738,
    "Floor": 3
  },
  {
    "X": -30.88811,
    "Y": -6.09167957,
    "Floor": 3
  },
  {
    "X": -30.56564,
    "Y": -6.07387161,
    "Floor": 3
  },
  {
    "X": -30.5154934,
    "Y": -5.89908028,
    "Floor": 3
  },
  {
    "X": -30.2894726,
    "Y": -5.904412,
    "Floor": 3
  },
  {
    "X": -30.06298,
    "Y": -5.90510368,
    "Floor": 3
  },
  {
    "X": -29.83697,
    "Y": -5.901091,
    "Floor": 3
  },
  {
    "X": -29.6121864,
    "Y": -5.87717,
    "Floor": 3
  },
  {
    "X": -29.3869324,
    "Y": -5.8540287,
    "Floor": 3
  },
  {
    "X": -29.160593,
    "Y": -5.84567356,
    "Floor": 3
  },
  {
    "X": -28.934803,
    "Y": -5.834106,
    "Floor": 3
  },
  {
    "X": -28.708744,
    "Y": -5.83436251,
    "Floor": 3
  },
  {
    "X": -29.1463852,
    "Y": -5.726136,
    "Floor": 3
  },
  {
    "X": -28.9889336,
    "Y": -5.71027136,
    "Floor": 3
  },
  {
    "X": -28.8304787,
    "Y": -5.706887,
    "Floor": 3
  },
  {
    "X": -28.67225,
    "Y": -5.709435,
    "Floor": 3
  },
  {
    "X": -28.51435,
    "Y": -5.6992507,
    "Floor": 3
  },
  {
    "X": -28.35601,
    "Y": -5.69150448,
    "Floor": 3
  },
  {
    "X": -28.1978416,
    "Y": -5.686702,
    "Floor": 3
  },
  {
    "X": -28.04069,
    "Y": -5.668419,
    "Floor": 3
  },
  {
    "X": -27.8836021,
    "Y": -5.64696026,
    "Floor": 3
  },
  {
    "X": -28.17063,
    "Y": -5.5618844,
    "Floor": 3
  },
  {
    "X": -28.0045,
    "Y": -5.53899431,
    "Floor": 3
  },
  {
    "X": -27.8387413,
    "Y": -5.51820374,
    "Floor": 3
  },
  {
    "X": -27.6732178,
    "Y": -5.49148464,
    "Floor": 3
  },
  {
    "X": -27.507246,
    "Y": -5.467949,
    "Floor": 3
  },
  {
    "X": -27.34112,
    "Y": -5.447923,
    "Floor": 3
  },
  {
    "X": -27.1770687,
    "Y": -5.41465235,
    "Floor": 3
  },
  {
    "X": -27.0114,
    "Y": -5.389015,
    "Floor": 3
  },
  {
    "X": -26.84542,
    "Y": -5.3676753,
    "Floor": 3
  },
  {
    "X": -27.3742867,
    "Y": -5.2790246,
    "Floor": 3
  },
  {
    "X": -27.2592659,
    "Y": -5.25559044,
    "Floor": 3
  },
  {
    "X": -27.1461029,
    "Y": -5.225537,
    "Floor": 3
  },
  {
    "X": -27.0351524,
    "Y": -5.18719,
    "Floor": 3
  },
  {
    "X": -26.92348,
    "Y": -5.151667,
    "Floor": 3
  },
  {
    "X": -26.8115025,
    "Y": -5.117144,
    "Floor": 3
  },
  {
    "X": -26.6973839,
    "Y": -5.089851,
    "Floor": 3
  },
  {
    "X": -26.5812,
    "Y": -5.07494545,
    "Floor": 3
  },
  {
    "X": -26.4641342,
    "Y": -5.06973648,
    "Floor": 3
  },
  {
    "X": -27.4084339,
    "Y": -4.920403,
    "Floor": 3
  },
  {
    "X": -27.2822933,
    "Y": -4.916922,
    "Floor": 3
  },
  {
    "X": -27.1566315,
    "Y": -4.928649,
    "Floor": 3
  },
  {
    "X": -27.0320854,
    "Y": -4.94844246,
    "Floor": 3
  },
  {
    "X": -26.9058266,
    "Y": -4.954748,
    "Floor": 3
  },
  {
    "X": -26.7798157,
    "Y": -4.961141,
    "Floor": 3
  },
  {
    "X": -26.6539383,
    "Y": -4.95379734,
    "Floor": 3
  },
  {
    "X": -26.5289326,
    "Y": -4.93658,
    "Floor": 3
  },
  {
    "X": -26.4031353,
    "Y": -4.927211,
    "Floor": 3
  },
  {
    "X": -27.3457146,
    "Y": -4.889212,
    "Floor": 3
  },
  {
    "X": -27.2572384,
    "Y": -4.89021254,
    "Floor": 3
  },
  {
    "X": -27.1700745,
    "Y": -4.90357065,
    "Floor": 3
  },
  {
    "X": -27.08394,
    "Y": -4.923786,
    "Floor": 3
  },
  {
    "X": -26.9965782,
    "Y": -4.936722,
    "Floor": 3
  },
  {
    "X": -26.909256,
    "Y": -4.949959,
    "Floor": 3
  },
  {
    "X": -26.8214588,
    "Y": -4.95840645,
    "Floor": 3
  },
  {
    "X": -26.7330971,
    "Y": -4.95379543,
    "Floor": 3
  },
  {
    "X": -26.6448631,
    "Y": -4.95722342,
    "Floor": 3
  },
  {
    "X": -26.5564289,
    "Y": -4.959937,
    "Floor": 3
  },
  {
    "X": -26.8650532,
    "Y": -4.946761,
    "Floor": 3
  },
  {
    "X": -26.7180729,
    "Y": -4.948655,
    "Floor": 3
  },
  {
    "X": -26.5719414,
    "Y": -4.93740559,
    "Floor": 3
  },
  {
    "X": -26.42617,
    "Y": -4.92164,
    "Floor": 3
  },
  {
    "X": -26.2792015,
    "Y": -4.9202714,
    "Floor": 3
  },
  {
    "X": -26.1340179,
    "Y": -4.90021,
    "Floor": 3
  },
  {
    "X": -25.9894524,
    "Y": -4.87526846,
    "Floor": 3
  },
  {
    "X": -25.8444633,
    "Y": -4.85278559,
    "Floor": 3
  },
  {
    "X": -25.7005749,
    "Y": -4.82283449,
    "Floor": 3
  },
  {
    "X": -26.1776257,
    "Y": -4.85341454,
    "Floor": 3
  },
  {
    "X": -26.0778446,
    "Y": -4.828301,
    "Floor": 3
  },
  {
    "X": -25.9796581,
    "Y": -4.797669,
    "Floor": 3
  },
  {
    "X": -25.8811321,
    "Y": -4.76885939,
    "Floor": 3
  },
  {
    "X": -25.7804337,
    "Y": -4.7477746,
    "Floor": 3
  },
  {
    "X": -25.6791439,
    "Y": -4.730801,
    "Floor": 3
  },
  {
    "X": -25.5777245,
    "Y": -4.71457529,
    "Floor": 3
  },
  {
    "X": -25.4764748,
    "Y": -4.696313,
    "Floor": 3
  },
  {
    "X": -25.3755932,
    "Y": -4.67702675,
    "Floor": 3
  },
  {
    "X": -25.92208,
    "Y": -4.7315464,
    "Floor": 3
  },
  {
    "X": -25.8495159,
    "Y": -4.716257,
    "Floor": 3
  },
  {
    "X": -25.7766628,
    "Y": -4.70240641,
    "Floor": 3
  },
  {
    "X": -25.703577,
    "Y": -4.69065857,
    "Floor": 3
  },
  {
    "X": -25.63016,
    "Y": -4.68019772,
    "Floor": 3
  },
  {
    "X": -25.55685,
    "Y": -4.66990566,
    "Floor": 3
  },
  {
    "X": -25.4835129,
    "Y": -4.659849,
    "Floor": 3
  },
  {
    "X": -25.41009,
    "Y": -4.649402,
    "Floor": 3
  },
  {
    "X": -25.3367,
    "Y": -4.638773,
    "Floor": 3
  },
  {
    "X": -24.7531223,
    "Y": -4.74751759,
    "Floor": 3
  },
  {
    "X": -24.5081825,
    "Y": -4.72278738,
    "Floor": 3
  },
  {
    "X": -24.2633076,
    "Y": -4.70207644,
    "Floor": 3
  },
  {
    "X": -24.0188236,
    "Y": -4.67725372,
    "Floor": 3
  },
  {
    "X": -23.7746811,
    "Y": -4.645573,
    "Floor": 3
  },
  {
    "X": -23.5307655,
    "Y": -4.615692,
    "Floor": 3
  },
  {
    "X": -23.2859287,
    "Y": -4.58987141,
    "Floor": 3
  },
  {
    "X": -23.0416031,
    "Y": -4.56342649,
    "Floor": 3
  },
  {
    "X": -22.7969742,
    "Y": -4.53573465,
    "Floor": 3
  },
  {
    "X": -22.0621738,
    "Y": -4.66135359,
    "Floor": 3
  },
  {
    "X": -21.8157043,
    "Y": -4.637791,
    "Floor": 3
  },
  {
    "X": -21.5697536,
    "Y": -4.6134696,
    "Floor": 3
  },
  {
    "X": -21.3237476,
    "Y": -4.589686,
    "Floor": 3
  },
  {
    "X": -21.0777168,
    "Y": -4.56200171,
    "Floor": 3
  },
  {
    "X": -20.8327866,
    "Y": -4.528989,
    "Floor": 3
  }
]