[
  {
    "X": -28.5348778,
    "Y": -5.90153933,
    "Floor": 3
  },
  {
    "X": -28.3815441,
    "Y": -5.90183,
    "Floor": 3
  },
  {
    "X": -28.2279339,
    "Y": -5.900405,
    "Floor": 3
  },
  {
    "X": -28.0745964,
    "Y": -5.90062475,
    "Floor": 3
  },
  {
    "X": -27.9209843,
    "Y": -5.90200853,
    "Floor": 3
  },
  {
    "X": -27.76769,
    "Y": -5.90549374,
    "Floor": 3
  },
  {
    "X": -27.61481,
    "Y": -5.912767,
    "Floor": 3
  },
  {
    "X": -27.4618168,
    "Y": -5.922952,
    "Floor": 3
  },
  {
    "X": -27.2994022,
    "Y": -5.935561,
    "Floor": 3
  },
  {
    "X": -28.3143024,
    "Y": -5.46177959,
    "Floor": 3
  },
  {
    "X": -28.2076569,
    "Y": -5.47362137,
    "Floor": 3
  },
  {
    "X": -28.1020813,
    "Y": -5.492968,
    "Floor": 3
  },
  {
    "X": -27.9957275,
    "Y": -5.50710726,
    "Floor": 3
  },
  {
    "X": -27.88837,
    "Y": -5.51320362,
    "Floor": 3
  },
  {
    "X": -27.7811756,
    "Y": -5.52162266,
    "Floor": 3
  },
  {
    "X": -27.6741581,
    "Y": -5.52577543,
    "Floor": 3
  },
  {
    "X": -27.566906,
    "Y": -5.52170229,
    "Floor": 3
  },
  {
    "X": -27.45976,
    "Y": -5.52741146,
    "Floor": 3
  },
  {
    "X": -28.358223,
    "Y": -5.21219969,
    "Floor": 3
  },
  {
    "X": -28.28325,
    "Y": -5.207287,
    "Floor": 3
  },
  {
    "X": -28.2081623,
    "Y": -5.20463657,
    "Floor": 3
  },
  {
    "X": -28.13304,
    "Y": -5.200397,
    "Floor": 3
  },
  {
    "X": -28.0582466,
    "Y": -5.19354439,
    "Floor": 3
  },
  {
    "X": -27.9831772,
    "Y": -5.19588757,
    "Floor": 3
  },
  {
    "X": -27.9081459,
    "Y": -5.19983959,
    "Floor": 3
  },
  {
    "X": -27.833168,
    "Y": -5.204553,
    "Floor": 3
  },
  {
    "X": -27.758604,
    "Y": -5.2148,
    "Floor": 3
  },
  {
    "X": -27.68366,
    "Y": -5.21914864,
    "Floor": 3
  },
  {
    "X": -29.2132549,
    "Y": -5.109227,
    "Floor": 3
  },
  {
    "X": -29.0600758,
    "Y": -5.124887,
    "Floor": 3
  },
  {
    "X": -28.9059124,
    "Y": -5.129149,
    "Floor": 3
  },
  {
    "X": -28.7520885,
    "Y": -5.135528,
    "Floor": 3
  },
  {
    "X": -28.598196,
    "Y": -5.138931,
    "Floor": 3
  },
  {
    "X": -28.4442749,
    "Y": -5.13949776,
    "Floor": 3
  },
  {
    "X": -28.291378,
    "Y": -5.157594,
    "Floor": 3
  },
  {
    "X": -28.1381226,
    "Y": -5.17232466,
    "Floor": 3
  },
  {
    "X": -27.9845085,
    "Y": -5.186495,
    "Floor": 3
  },
  {
    "X": -27.8308258,
    "Y": -5.19421434,
    "Floor": 3
  },
  {
    "X": -28.9920673,
    "Y": -5.088246,
    "Floor": 3
  },
  {
    "X": -28.8524017,
    "Y": -5.08738565,
    "Floor": 3
  },
  {
    "X": -28.7127647,
    "Y": -5.084257,
    "Floor": 3
  },
  {
    "X": -28.57305,
    "Y": -5.07578373,
    "Floor": 3
  },
  {
    "X": -28.4334984,
    "Y": -5.068996,
    "Floor": 3
  },
  {
    "X": -28.2942352,
    "Y": -5.05775547,
    "Floor": 3
  },
  {
    "X": -28.15474,
    "Y": -5.062679,
    "Floor": 3
  },
  {
    "X": -28.0160732,
    "Y": -5.079838,
    "Floor": 3
  },
  {
    "X": -27.8782024,
    "Y": -5.10223532,
    "Floor": 3
  },
  {
    "X": -28.6200085,
    "Y": -5.06352949,
    "Floor": 3
  },
  {
    "X": -28.4557419,
    "Y": -5.09058666,
    "Floor": 3
  },
  {
    "X": -28.2957382,
    "Y": -5.136944,
    "Floor": 3
  },
  {
    "X": -28.1387634,
    "Y": -5.192322,
    "Floor": 3
  },
  {
    "X": -27.9771767,
    "Y": -5.23229551,
    "Floor": 3
  },
  {
    "X": -27.8164482,
    "Y": -5.276827,
    "Floor": 3
  },
  {
    "X": -27.65323,
    "Y": -5.30661774,
    "Floor": 3
  },
  {
    "X": -27.4869881,
    "Y": -5.31554651,
    "Floor": 3
  },
  {
    "X": -27.3211384,
    "Y": -5.32935762,
    "Floor": 3
  },
  {
    "X": -27.15438,
    "Y": -5.328498,
    "Floor": 3
  },
  {
    "X": -27.963583,
    "Y": -5.21095,
    "Floor": 3
  },
  {
    "X": -27.8492832,
    "Y": -5.18890333,
    "Floor": 3
  },
  {
    "X": -27.7352982,
    "Y": -5.164955,
    "Floor": 3
  },
  {
    "X": -27.6203327,
    "Y": -5.14602661,
    "Floor": 3
  },
  {
    "X": -27.50693,
    "Y": -5.11920452,
    "Floor": 3
  },
  {
    "X": -27.39255,
    "Y": -5.095817,
    "Floor": 3
  },
  {
    "X": -27.2807388,
    "Y": -5.06307268,
    "Floor": 3
  },
  {
    "X": -27.1678181,
    "Y": -5.034701,
    "Floor": 3
  },
  {
    "X": -27.0526619,
    "Y": -5.01684952,
    "Floor": 3
  },
  {
    "X": -26.9382267,
    "Y": -4.99479,
    "Floor": 3
  },
  {
    "X": -27.8295822,
    "Y": -5.017793,
    "Floor": 3
  },
  {
    "X": -27.7392063,
    "Y": -4.99975824,
    "Floor": 3
  },
  {
    "X": -27.6476135,
    "Y": -4.98839951,
    "Floor": 3
  },
  {
    "X": -27.5556049,
    "Y": -4.983274,
    "Floor": 3
  },
  {
    "X": -27.4636688,
    "Y": -4.97707224,
    "Floor": 3
  },
  {
    "X": -27.3718433,
    "Y": -4.969512,
    "Floor": 3
  },
  {
    "X": -27.2799625,
    "Y": -4.975089,
    "Floor": 3
  },
  {
    "X": -27.1895447,
    "Y": -4.99358463,
    "Floor": 3
  },
  {
    "X": -27.09986,
    "Y": -5.014708,
    "Floor": 3
  },
  {
    "X": -27.00842,
    "Y": -5.025841,
    "Floor": 3
  },
  {
    "X": -27.733305,
    "Y": -5.0635314,
    "Floor": 3
  },
  {
    "X": -27.6494179,
    "Y": -5.06140041,
    "Floor": 3
  },
  {
    "X": -27.5655327,
    "Y": -5.059289,
    "Floor": 3
  },
  {
    "X": -27.4816952,
    "Y": -5.06502056,
    "Floor": 3
  },
  {
    "X": -27.398798,
    "Y": -5.078045,
    "Floor": 3
  },
  {
    "X": -27.3167877,
    "Y": -5.09582853,
    "Floor": 3
  },
  {
    "X": -27.2355289,
    "Y": -5.117381,
    "Floor": 3
  },
  {
    "X": -27.1552811,
    "Y": -5.14195251,
    "Floor": 3
  },
  {
    "X": -27.07611,
    "Y": -5.16974163,
    "Floor": 3
  },
  {
    "X": -26.996315,
    "Y": -5.195521,
    "Floor": 3
  },
  {
    "X": -27.2062359,
    "Y": -5.18954325,
    "Floor": 3
  },
  {
    "X": -27.0856647,
    "Y": -5.21687555,
    "Floor": 3
  },
  {
    "X": -26.963171,
    "Y": -5.231704,
    "Floor": 3
  },
  {
    "X": -26.8406029,
    "Y": -5.246111,
    "Floor": 3
  },
  {
    "X": -26.71822,
    "Y": -5.2618947,
    "Floor": 3
  },
  {
    "X": -26.5948772,
    "Y": -5.26526451,
    "Floor": 3
  },
  {
    "X": -26.47171,
    "Y": -5.275052,
    "Floor": 3
  },
  {
    "X": -26.3497334,
    "Y": -5.29221,
    "Floor": 3
  },
  {
    "X": -26.226757,
    "Y": -5.30262041,
    "Floor": 3
  },
  {
    "X": -26.1036282,
    "Y": -5.310633,
    "Floor": 3
  },
  {
    "X": -26.5940685,
    "Y": -5.25356531,
    "Floor": 3
  },
  {
    "X": -26.5077744,
    "Y": -5.25222969,
    "Floor": 3
  },
  {
    "X": -26.4219952,
    "Y": -5.262383,
    "Floor": 3
  },
  {
    "X": -26.3359032,
    "Y": -5.269321,
    "Floor": 3
  },
  {
    "X": -26.2497444,
    "Y": -5.275574,
    "Floor": 3
  },
  {
    "X": -26.1636257,
    "Y": -5.2823267,
    "Floor": 3
  },
  {
    "X": -26.07724,
    "Y": -5.28743458,
    "Floor": 3
  },
  {
    "X": -25.9922619,
    "Y": -5.30258226,
    "Floor": 3
  },
  {
    "X": -25.9085464,
    "Y": -5.323907,
    "Floor": 3
  },
  {
    "X": -24.7399426,
    "Y": -5.306994,
    "Floor": 3
  },
  {
    "X": -24.4584312,
    "Y": -5.36806965,
    "Floor": 3
  },
  {
    "X": -24.1755486,
    "Y": -5.41884136,
    "Floor": 3
  },
  {
    "X": -23.891058,
    "Y": -5.460188,
    "Floor": 3
  },
  {
    "X": -23.6137123,
    "Y": -5.53569365,
    "Floor": 3
  },
  {
    "X": -23.3354588,
    "Y": -5.609618,
    "Floor": 3
  },
  {
    "X": -23.0512,
    "Y": -5.652993,
    "Floor": 3
  },
  {
    "X": -22.767065,
    "Y": -5.697311,
    "Floor": 3
  },
  {
    "X": -22.4831,
    "Y": -5.73924446,
    "Floor": 3
  },
  {
    "X": -22.1989555,
    "Y": -5.78640652,
    "Floor": 3
  },
  {
    "X": -20.2262726,
    "Y": -5.68375444,
    "Floor": 3
  },
  {
    "X": -19.8433723,
    "Y": -5.77341127,
    "Floor": 3
  },
  {
    "X": -19.4623661,
    "Y": -5.86477661,
    "Floor": 3
  },
  {
    "X": -19.083744,
    "Y": -5.97123861,
    "Floor": 3
  },
  {
    "X": -18.6980724,
    "Y": -6.048182,
    "Floor": 3
  },
  {
    "X": -18.31657,
    "Y": -6.14293242,
    "Floor": 3
  },
  {
    "X": -17.9414673,
    "Y": -6.25623,
    "Floor": 3
  },
  {
    "X": -17.5564022,
    "Y": -6.336283,
    "Floor": 3
  },
  {
    "X": -17.1803417,
    "Y": -6.443183,
    "Floor": 3
  },
  {
    "X": -16.800375,
    "Y": -6.540271,
    "Floor": 3
  },
  {
    "X": -15.8715038,
    "Y": -6.202906,
    "Floor": 3
  },
  {
    "X": -15.5964041,
    "Y": -6.26164532,
    "Floor": 3
  },
  {
    "X": -15.3173571,
    "Y": -6.290695,
    "Floor": 3
  },
  {
    "X": -15.0364075,
    "Y": -6.312776,
    "Floor": 3
  },
  {
    "X": -14.7555952,
    "Y": -6.32547045,
    "Floor": 3
  },
  {
    "X": -14.4759808,
    "Y": -6.29580927,
    "Floor": 3
  },
  {
    "X": -14.1946611,
    "Y": -6.274083,
    "Floor": 3
  },
  {
    "X": -13.9139519,
    "Y": -6.26728439,
    "Floor": 3
  },
  {
    "X": -13.6336088,
    "Y": -6.243685,
    "Floor": 3
  },
  {
    "X": -13.3525276,
    "Y": -6.2229743,
    "Floor": 3
  },
  {
    "X": -12.6090117,
    "Y": -5.883561,
    "Floor": 3
  },
  {
    "X": -12.3339682,
    "Y": -5.872438,
    "Floor": 3
  },
  {
    "X": -12.0586348,
    "Y": -5.882957,
    "Floor": 3
  },
  {
    "X": -11.78261,
    "Y": -5.8808856,
    "Floor": 3
  },
  {
    "X": -11.5070906,
    "Y": -5.87725258,
    "Floor": 3
  },
  {
    "X": -11.231575,
    "Y": -5.87427473,
    "Floor": 3
  },
  {
    "X": -10.9561749,
    "Y": -5.872182,
    "Floor": 3
  },
  {
    "X": -10.6833487,
    "Y": -5.91306448,
    "Floor": 3
  },
  {
    "X": -10.4118576,
    "Y": -5.96001053,
    "Floor": 3
  },
  {
    "X": -10.3209505,
    "Y": -5.74262476,
    "Floor": 3
  },
  {
    "X": -10.1197157,
    "Y": -5.7537384,
    "Floor": 3
  },
  {
    "X": -9.917763,
    "Y": -5.7563653,
    "Floor": 3
  },
  {
    "X": -9.717029,
    "Y": -5.774947,
    "Floor": 3
  },
  {
    "X": -9.516506,
    "Y": -5.795901,
    "Floor": 3
  },
  {
    "X": -9.315282,
    "Y": -5.813466,
    "Floor": 3
  },
  {
    "X": -9.114713,
    "Y": -5.833961,
    "Floor": 3
  },
  {
    "X": -8.913783,
    "Y": -5.84538031,
    "Floor": 3
  },
  {
    "X": -8.715513,
    "Y": -5.88072348,
    "Floor": 3
  },
  {
    "X": -8.519172,
    "Y": -5.926244,
    "Floor": 3
  },
  {
    "X": -8.288828,
    "Y": -5.848517,
    "Floor": 3
  },
  {
    "X": -8.068634,
    "Y": -5.87663126,
    "Floor": 3
  },
  {
    "X": -7.84778738,
    "Y": -5.89363,
    "Floor": 3
  },
  {
    "X": -7.626945,
    "Y": -5.91016531,
    "Floor": 3
  },
  {
    "X": -7.40803671,
    "Y": -5.94691658,
    "Floor": 3
  },
  {
    "X": -7.18761444,
    "Y": -5.968351,
    "Floor": 3
  },
  {
    "X": -6.96671867,
    "Y": -5.9855547,
    "Floor": 3
  },
  {
    "X": -6.745524,
    "Y": -5.99748039,
    "Floor": 3
  },
  {
    "X": -6.52398252,
    "Y": -5.998895,
    "Floor": 3
  },
  {
    "X": -6.303633,
    "Y": -6.02483368,
    "Floor": 3
  },
  {
    "X": -6.49185658,
    "Y": -5.92895269,
    "Floor": 3
  },
  {
    "X": -6.32844639,
    "Y": -5.927984,
    "Floor": 3
  },
  {
    "X": -6.16504669,
    "Y": -5.92991829,
    "Floor": 3
  },
  {
    "X": -6.001593,
    "Y": -5.921313,
    "Floor": 3
  },
  {
    "X": -5.83862734,
    "Y": -5.92799234,
    "Floor": 3
  },
  {
    "X": -5.67819452,
    "Y": -5.958915,
    "Floor": 3
  },
  {
    "X": -5.517261,
    "Y": -5.987198,
    "Floor": 3
  },
  {
    "X": -5.35888958,
    "Y": -6.027902,
    "Floor": 3
  },
  {
    "X": -5.20618439,
    "Y": -6.08607769,
    "Floor": 3
  },
  {
    "X": -5.055545,
    "Y": -6.149138,
    "Floor": 3
  },
  {
    "X": -5.1857,
    "Y": -6.125856,
    "Floor": 3
  },
  {
    "X": -5.04659653,
    "Y": -6.21554327,
    "Floor": 3
  },
  {
    "X": -4.904404,
    "Y": -6.30085754,
    "Floor": 3
  },
  {
    "X": -4.765908,
    "Y": -6.39149332,
    "Floor": 3
  },
  {
    "X": -4.622316,
    "Y": -6.473722,
    "Floor": 3
  },
  {
    "X": -4.48023462,
    "Y": -6.558468,
    "Floor": 3
  },
  {
    "X": -4.345928,
    "Y": -6.655202,
    "Floor": 3
  },
  {
    "X": -4.209591,
    "Y": -6.74957561,
    "Floor": 3
  },
  {
    "X": -4.072806,
    "Y": -6.84276962,
    "Floor": 3
  },
  {
    "X": -3.97293282,
    "Y": -6.85431337,
    "Floor": 3
  },
  {
    "X": -3.79865718,
    "Y": -6.93322945,
    "Floor": 3
  },
  {
    "X": -3.63379717,
    "Y": -7.030338,
    "Floor": 3
  },
  {
    "X": -3.46607685,
    "Y": -7.123069,
    "Floor": 3
  },
  {
    "X": -3.29244423,
    "Y": -7.204355,
    "Floor": 3
  },
  {
    "X": -3.114253,
    "Y": -7.272762,
    "Floor": 3
  },
  {
    "X": -2.93092942,
    "Y": -7.32757473,
    "Floor": 3
  },
  {
    "X": -2.75389147,
    "Y": -7.400842,
    "Floor": 3
  },
  {
    "X": -2.57686734,
    "Y": -7.47325373,
    "Floor": 3
  },
  {
    "X": -2.392341,
    "Y": -7.523816,
    "Floor": 3
  },
  {
    "X": -2.54258323,
    "Y": -7.350222,
    "Floor": 3
  },
  {
    "X": -2.39777637,
    "Y": -7.368054,
    "Floor": 3
  },
  {
    "X": -2.25354624,
    "Y": -7.38841724,
    "Floor": 3
  },
  {
    "X": -2.10933018,
    "Y": -7.40847158,
    "Floor": 3
  },
  {
    "X": -1.96366787,
    "Y": -7.40854073,
    "Floor": 3
  },
  {
    "X": -1.8179785,
    "Y": -7.407874,
    "Floor": 3
  },
  {
    "X": -1.67292893,
    "Y": -7.392527,
    "Floor": 3
  },
  {
    "X": -1.5285567,
    "Y": -7.37308741,
    "Floor": 3
  },
  {
    "X": -1.38339067,
    "Y": -7.3607707,
    "Floor": 3
  },
  {
    "X": -1.265718,
    "Y": -7.43715143,
    "Floor": 3
  },
  {
    "X": -1.06490743,
    "Y": -7.403904,
    "Floor": 3
  },
  {
    "X": -0.867929637,
    "Y": -7.351621,
    "Floor": 3
  },
  {
    "X": -0.6715693,
    "Y": -7.298975,
    "Floor": 3
  },
  {
    "X": -0.468520522,
    "Y": -7.28618336,
    "Floor": 3
  },
  {
    "X": -0.266587138,
    "Y": -7.262078,
    "Floor": 3
  },
  {
    "X": -0.0645536855,
    "Y": -7.234924,
    "Floor": 3
  },
  {
    "X": 0.1385959,
    "Y": -7.22222,
    "Floor": 3
  },
  {
    "X": 0.3417324,
    "Y": -7.21035671,
    "Floor": 3
  },
  {
    "X": 0.543817043,
    "Y": -7.231986,
    "Floor": 3
  },
  {
    "X": 0.15816918,
    "Y": -7.40269041,
    "Floor": 3
  },
  {
    "X": 0.2990198,
    "Y": -7.423872,
    "Floor": 3
  },
  {
    "X": 0.437955618,
    "Y": -7.45659447,
    "Floor": 3
  },
  {
    "X": 0.5779397,
    "Y": -7.48295,
    "Floor": 3
  },
  {
    "X": 0.717553258,
    "Y": -7.51105,
    "Floor": 3
  },
  {
    "X": 0.85389185,
    "Y": -7.55240965,
    "Floor": 3
  },
  {
    "X": 0.9925848,
    "Y": -7.584776,
    "Floor": 3
  },
  {
    "X": 1.13314664,
    "Y": -7.6095376,
    "Floor": 3
  },
  {
    "X": 1.27493167,
    "Y": -7.61238146,
    "Floor": 3
  },
  {
    "X": 1.41472614,
    "Y": -7.58487225,
    "Floor": 3
  },
  {
    "X": 0.6700012,
    "Y": -7.5739913,
    "Floor": 3
  },
  {
    "X": 0.792198062,
    "Y": -7.53658,
    "Floor": 3
  },
  {
    "X": 0.9042659,
    "Y": -7.473363,
    "Floor": 3
  },
  {
    "X": 1.01628673,
    "Y": -7.410676,
    "Floor": 3
  },
  {
    "X": 1.114348,
    "Y": -7.327902,
    "Floor": 3
  },
  {
    "X": 1.21249044,
    "Y": -7.245088,
    "Floor": 3
  },
  {
    "X": 1.303601,
    "Y": -7.154695,
    "Floor": 3
  },
  {
    "X": 1.3753525,
    "Y": -7.048181,
    "Floor": 3
  },
  {
    "X": 1.44110727,
    "Y": -6.937953,
    "Floor": 3
  },
  {
    "X": 1.36343,
    "Y": -7.10051632,
    "Floor": 3
  },
  {
    "X": 1.451555,
    "Y": -6.924673,
    "Floor": 3
  },
  {
    "X": 1.54466343,
    "Y": -6.75271845,
    "Floor": 3
  },
  {
    "X": 1.61743593,
    "Y": -6.570706,
    "Floor": 3
  },
  {
    "X": 1.70207989,
    "Y": -6.39349031,
    "Floor": 3
  },
  {
    "X": 1.77163875,
    "Y": -6.20996237,
    "Floor": 3
  },
  {
    "X": 1.83646512,
    "Y": -6.0250206,
    "Floor": 3
  },
  {
    "X": 1.91555583,
    "Y": -5.84605837,
    "Floor": 3
  },
  {
    "X": 1.9658848,
    "Y": -5.656393,
    "Floor": 3
  },
  {
    "X": 2.013565,
    "Y": -5.466248,
    "Floor": 3
  },
  {
    "X": 2.47599578,
    "Y": -4.96117163,
    "Floor": 3
  },
  {
    "X": 2.5613606,
    "Y": -4.686712,
    "Floor": 3
  },
  {
    "X": 2.66559625,
    "Y": -4.41832352,
    "Floor": 3
  },
  {
    "X": 2.75699687,
    "Y": -4.14485025,
    "Floor": 3
  },
  {
    "X": 2.835821,
    "Y": -3.86788654,
    "Floor": 3
  },
  {
    "X": 2.91946769,
    "Y": -3.5923295,
    "Floor": 3
  },
  {
    "X": 3.00457478,
    "Y": -3.31666732,
    "Floor": 3
  },
  {
    "X": 3.09398675,
    "Y": -3.04294443,
    "Floor": 3
  },
  {
    "X": 3.18207,
    "Y": -2.76884556,
    "Floor": 3
  },
  {
    "X": 3.2568922,
    "Y": -2.49078131,
    "Floor": 3
  },
  {
    "X": 4.18390942,
    "Y": -2.30070043,
    "Floor": 3
  },
  {
    "X": 4.27708626,
    "Y": -2.008927,
    "Floor": 3
  },
  {
    "X": 4.388564,
    "Y": -1.72380185,
    "Floor": 3
  },
  {
    "X": 4.51130342,
    "Y": -1.44322693,
    "Floor": 3
  },
  {
    "X": 4.62120628,
    "Y": -1.15674281,
    "Floor": 3
  },
  {
    "X": 4.74069166,
    "Y": -0.874718547,
    "Floor": 3
  },
  {
    "X": 4.8548727,
    "Y": -0.590508342,
    "Floor": 3
  },
  {
    "X": 4.983531,
    "Y": -0.312056422,
    "Floor": 3
  },
  {
    "X": 5.116515,
    "Y": -0.0361717343,
    "Floor": 3
  },
  {
    "X": 5.08696127,
    "Y": 0.06557516,
    "Floor": 3
  },
  {
    "X": 5.259958,
    "Y": 0.348250568,
    "Floor": 3
  },
  {
    "X": 5.40621662,
    "Y": 0.6462181,
    "Floor": 3
  },
  {
    "X": 5.538377,
    "Y": 0.950169861,
    "Floor": 3
  },
  {
    "X": 5.672999,
    "Y": 1.25299919,
    "Floor": 3
  },
  {
    "X": 5.79712963,
    "Y": 1.56097066,
    "Floor": 3
  },
  {
    "X": 5.91362667,
    "Y": 1.87116265,
    "Floor": 3
  },
  {
    "X": 6.003576,
    "Y": 2.18950272,
    "Floor": 3
  },
  {
    "X": 6.091597,
    "Y": 2.508938,
    "Floor": 3
  },
  {
    "X": 6.18505573,
    "Y": 2.826719,
    "Floor": 3
  },
  {
    "X": 6.877061,
    "Y": 3.090512,
    "Floor": 3
  },
  {
    "X": 7.01339769,
    "Y": 3.46834064,
    "Floor": 3
  },
  {
    "X": 7.131317,
    "Y": 3.8523376,
    "Floor": 3
  },
  {
    "X": 7.243875,
    "Y": 4.237917,
    "Floor": 3
  },
  {
    "X": 7.37512064,
    "Y": 4.61832952,
    "Floor": 3
  },
  {
    "X": 7.47810936,
    "Y": 5.006623,
    "Floor": 3
  },
  {
    "X": 7.613543,
    "Y": 5.384783,
    "Floor": 3
  },
  {
    "X": 7.72804737,
    "Y": 5.769646,
    "Floor": 3
  },
  {
    "X": 7.829518,
    "Y": 6.158264,
    "Floor": 3
  },
  {
    "X": 8.243531,
    "Y": 5.76672745,
    "Floor": 3
  },
  {
    "X": 8.371318,
    "Y": 6.04364,
    "Floor": 3
  },
  {
    "X": 8.493535,
    "Y": 6.32306767,
    "Floor": 3
  },
  {
    "X": 8.614778,
    "Y": 6.6028986,
    "Floor": 3
  },
  {
    "X": 8.719109,
    "Y": 6.88946724,
    "Floor": 3
  },
  {
    "X": 8.805503,
    "Y": 7.18246555,
    "Floor": 3
  },
  {
    "X": 8.850847,
    "Y": 7.48348475,
    "Floor": 3
  },
  {
    "X": 8.816589,
    "Y": 7.78566265,
    "Floor": 3
  },
  {
    "X": 8.702963,
    "Y": 8.068248,
    "Floor": 3
  },
  {
    "X": 8.581032,
    "Y": 8.347669,
    "Floor": 3
  },
  {
    "X": 8.724833,
    "Y": 7.34441662,
    "Floor": 3
  },
  {
    "X": 8.66607952,
    "Y": 7.55598831,
    "Floor": 3
  },
  {
    "X": 8.60012,
    "Y": 7.7654314,
    "Floor": 3
  },
  {
    "X": 8.529607,
    "Y": 7.97338057,
    "Floor": 3
  },
  {
    "X": 8.458188,
    "Y": 8.181447,
    "Floor": 3
  },
  {
    "X": 8.402637,
    "Y": 8.393739,
    "Floor": 3
  },
  {
    "X": 8.358697,
    "Y": 8.608847,
    "Floor": 3
  },
  {
    "X": 8.289971,
    "Y": 8.81767,
    "Floor": 3
  },
  {
    "X": 8.202267,
    "Y": 9.018523,
    "Floor": 3
  },
  {
    "X": 8.119716,
    "Y": 9.237029,
    "Floor": 3
  },
  {
    "X": 8.389736,
    "Y": 8.95319748,
    "Floor": 3
  },
  {
    "X": 8.313954,
    "Y": 9.220602,
    "Floor": 3
  },
  {
    "X": 8.232488,
    "Y": 9.486326,
    "Floor": 3
  },
  {
    "X": 8.132872,
    "Y": 9.746227,
    "Floor": 3
  },
  {
    "X": 8.024254,
    "Y": 10.0020332,
    "Floor": 3
  },
  {
    "X": 7.94451046,
    "Y": 10.2685194,
    "Floor": 3
  },
  {
    "X": 7.895321,
    "Y": 10.542058,
    "Floor": 3
  },
  {
    "X": 7.82751465,
    "Y": 10.8110113,
    "Floor": 3
  },
  {
    "X": 7.736445,
    "Y": 11.0735312,
    "Floor": 3
  },
  {
    "X": 7.73480034,
    "Y": 10.6297455,
    "Floor": 3
  },
  {
    "X": 7.756399,
    "Y": 10.8958406,
    "Floor": 3
  },
  {
    "X": 7.801928,
    "Y": 11.1596756,
    "Floor": 3
  },
  {
    "X": 7.83746862,
    "Y": 11.4245443,
    "Floor": 3
  },
  {
    "X": 7.85730028,
    "Y": 11.6909037,
    "Floor": 3
  },
  {
    "X": 7.8633647,
    "Y": 11.9580669,
    "Floor": 3
  },
  {
    "X": 7.86888027,
    "Y": 12.2252407,
    "Floor": 3
  },
  {
    "X": 7.84718227,
    "Y": 12.4913645,
    "Floor": 3
  },
  {
    "X": 7.7937603,
    "Y": 12.7536812,
    "Floor": 3
  },
  {
    "X": 7.723264,
    "Y": 13.0800858,
    "Floor": 3
  },
  {
    "X": 7.887018,
    "Y": 12.9815779,
    "Floor": 3
  },
  {
    "X": 7.88258553,
    "Y": 13.2767086,
    "Floor": 3
  },
  {
    "X": 7.89369059,
    "Y": 13.5722532,
    "Floor": 3
  },
  {
    "X": 7.906771,
    "Y": 13.8671827,
    "Floor": 3
  },
  {
    "X": 7.922079,
    "Y": 14.1620026,
    "Floor": 3
  },
  {
    "X": 7.94157076,
    "Y": 14.4570656,
    "Floor": 3
  },
  {
    "X": 7.980461,
    "Y": 14.7497015,
    "Floor": 3
  },
  {
    "X": 7.996386,
    "Y": 15.0437279,
    "Floor": 3
  },
  {
    "X": 7.96927547,
    "Y": 15.3378773,
    "Floor": 3
  },
  {
    "X": 7.9012804,
    "Y": 15.625104,
    "Floor": 3
  },
  {
    "X": 8.218226,
    "Y": 15.0573845,
    "Floor": 3
  },
  {
    "X": 8.190688,
    "Y": 15.30055,
    "Floor": 3
  },
  {
    "X": 8.171848,
    "Y": 15.5445681,
    "Floor": 3
  },
  {
    "X": 8.156969,
    "Y": 15.7888565,
    "Floor": 3
  },
  {
    "X": 8.152014,
    "Y": 16.0339947,
    "Floor": 3
  },
  {
    "X": 8.153497,
    "Y": 16.2782745,
    "Floor": 3
  },
  {
    "X": 8.168837,
    "Y": 16.5229568,
    "Floor": 3
  },
  {
    "X": 8.179265,
    "Y": 16.7673149,
    "Floor": 3
  },
  {
    "X": 8.163036,
    "Y": 17.0119686,
    "Floor": 3
  },
  {
    "X": 8.158753,
    "Y": 17.2566643,
    "Floor": 3
  },
  {
    "X": 8.200702,
    "Y": 16.35017,
    "Floor": 3
  },
  {
    "X": 8.221989,
    "Y": 16.5561924,
    "Floor": 3
  },
  {
    "X": 8.239604,
    "Y": 16.7621078,
    "Floor": 3
  },
  {
    "X": 8.235065,
    "Y": 16.968811,
    "Floor": 3
  },
  {
    "X": 8.234177,
    "Y": 17.1755714,
    "Floor": 3
  },
  {
    "X": 8.23369,
    "Y": 17.3827171,
    "Floor": 3
  },
  {
    "X": 8.247001,
    "Y": 17.5889664,
    "Floor": 3
  },
  {
    "X": 8.270693,
    "Y": 17.79436,
    "Floor": 3
  },
  {
    "X": 8.278144,
    "Y": 18.0009651,
    "Floor": 3
  },
  {
    "X": 8.292898,
    "Y": 18.2075119,
    "Floor": 3
  },
  {
    "X": 8.712184,
    "Y": 19.7424984,
    "Floor": 3
  },
  {
    "X": 8.8198185,
    "Y": 20.2149525,
    "Floor": 3
  },
  {
    "X": 8.98204,
    "Y": 20.6716328,
    "Floor": 3
  },
  {
    "X": 9.149843,
    "Y": 21.1273689,
    "Floor": 3
  },
  {
    "X": 9.320987,
    "Y": 21.5809059,
    "Floor": 3
  },
  {
    "X": 9.480887,
    "Y": 22.0384178,
    "Floor": 3
  },
  {
    "X": 9.611823,
    "Y": 22.5051537,
    "Floor": 3
  },
  {
    "X": 9.740146,
    "Y": 22.973547,
    "Floor": 3
  },
  {
    "X": 9.864507,
    "Y": 23.441988,
    "Floor": 3
  },
  {
    "X": 9.955287,
    "Y": 23.9181728,
    "Floor": 3
  },
  {
    "X": 10.1055813,
    "Y": 24.1454258,
    "Floor": 3
  },
  {
    "X": 10.1644258,
    "Y": 24.4802532,
    "Floor": 3
  },
  {
    "X": 10.2310143,
    "Y": 24.8129139,
    "Floor": 3
  },
  {
    "X": 10.3532991,
    "Y": 25.1287,
    "Floor": 3
  },
  {
    "X": 10.4433451,
    "Y": 25.4508457,
    "Floor": 3
  },
  {
    "X": 10.3236027,
    "Y": 25.76723,
    "Floor": 3
  },
  {
    "X": 10.1951447,
    "Y": 26.08092,
    "Floor": 3
  },
  {
    "X": 10.1248894,
    "Y": 26.41268,
    "Floor": 3
  },
  {
    "X": 10.0756664,
    "Y": 26.74902,
    "Floor": 3
  },
  {
    "X": 10.0408449,
    "Y": 26.35129,
    "Floor": 3
  },
  {
    "X": 10.0455666,
    "Y": 26.6009388,
    "Floor": 3
  },
  {
    "X": 10.0584145,
    "Y": 26.8503265,
    "Floor": 3
  },
  {
    "X": 10.0839052,
    "Y": 27.0991077,
    "Floor": 3
  },
  {
    "X": 10.1305294,
    "Y": 27.34441,
    "Floor": 3
  },
  {
    "X": 10.18349,
    "Y": 27.58844,
    "Floor": 3
  },
  {
    "X": 10.222537,
    "Y": 27.83508,
    "Floor": 3
  },
  {
    "X": 10.2614555,
    "Y": 28.0812855,
    "Floor": 3
  },
  {
    "X": 10.3069181,
    "Y": 28.3268147,
    "Floor": 3
  },
  {
    "X": 10.36943,
    "Y": 28.5684471,
    "Floor": 3
  },
  {
    "X": 10.361845,
    "Y": 27.8146839,
    "Floor": 3
  },
  {
    "X": 10.4117489,
    "Y": 27.9929523,
    "Floor": 3
  },
  {
    "X": 10.4639454,
    "Y": 28.1705666,
    "Floor": 3
  },
  {
    "X": 10.5159292,
    "Y": 28.3485928,
    "Floor": 3
  },
  {
    "X": 10.574439,
    "Y": 28.52422,
    "Floor": 3
  },
  {
    "X": 10.6241894,
    "Y": 28.7024632,
    "Floor": 3
  },
  {
    "X": 10.6555843,
    "Y": 28.8848057,
    "Floor": 3
  },
  {
    "X": 10.6734581,
    "Y": 29.0690613,
    "Floor": 3
  },
  {
    "X": 10.6925373,
    "Y": 29.2535419,
    "Floor": 3
  },
  {
    "X": 10.7085371,
    "Y": 29.4379616,
    "Floor": 3
  },
  {
    "X": 10.5859156,
    "Y": 28.4883385,
    "Floor": 3
  },
  {
    "X": 10.5888109,
    "Y": 28.6177578,
    "Floor": 3
  },
  {
    "X": 10.5773888,
    "Y": 28.7468128,
    "Floor": 3
  },
  {
    "X": 10.5663137,
    "Y": 28.87591,
    "Floor": 3
  },
  {
    "X": 10.5628128,
    "Y": 29.0056725,
    "Floor": 3
  },
  {
    "X": 10.56454,
    "Y": 29.1352463,
    "Floor": 3
  },
  {
    "X": 10.559866,
    "Y": 29.2649536,
    "Floor": 3
  },
  {
    "X": 10.5488358,
    "Y": 29.3940544,
    "Floor": 3
  },
  {
    "X": 10.53191,
    "Y": 29.5225315,
    "Floor": 3
  },
  {
    "X": 10.5189438,
    "Y": 29.6516819,
    "Floor": 3
  },
  {
    "X": 10.2122774,
    "Y": 29.8629589,
    "Floor": 3
  },
  {
    "X": 10.2068691,
    "Y": 30.1185913,
    "Floor": 3
  },
  {
    "X": 10.190362,
    "Y": 30.3728447,
    "Floor": 3
  },
  {
    "X": 10.1727562,
    "Y": 30.628437,
    "Floor": 3
  },
  {
    "X": 10.1671762,
    "Y": 30.8826714,
    "Floor": 3
  },
  {
    "X": 10.1754532,
    "Y": 31.1377411,
    "Floor": 3
  },
  {
    "X": 10.1891556,
    "Y": 31.3925686,
    "Floor": 3
  },
  {
    "X": 10.1733837,
    "Y": 31.6472282,
    "Floor": 3
  },
  {
    "X": 10.1347322,
    "Y": 31.8994884,
    "Floor": 3
  },
  {
    "X": 10.1035938,
    "Y": 32.1531,
    "Floor": 3
  },
  {
    "X": 9.988187,
    "Y": 32.1683655,
    "Floor": 3
  },
  {
    "X": 10.0038023,
    "Y": 32.3923454,
    "Floor": 3
  },
  {
    "X": 10.0100813,
    "Y": 32.61715,
    "Floor": 3
  },
  {
    "X": 10.0173531,
    "Y": 32.8415527,
    "Floor": 3
  },
  {
    "X": 10.0282879,
    "Y": 33.0658264,
    "Floor": 3
  },
  {
    "X": 10.0484438,
    "Y": 33.28942,
    "Floor": 3
  },
  {
    "X": 10.0956984,
    "Y": 33.5087471,
    "Floor": 3
  },
  {
    "X": 10.1488829,
    "Y": 33.7272377,
    "Floor": 3
  },
  {
    "X": 10.187007,
    "Y": 33.94852,
    "Floor": 3
  },
  {
    "X": 10.091692,
    "Y": 33.4099579,
    "Floor": 3
  },
  {
    "X": 10.1287193,
    "Y": 33.57285,
    "Floor": 3
  },
  {
    "X": 10.1773119,
    "Y": 33.7331352,
    "Floor": 3
  },
  {
    "X": 10.2152328,
    "Y": 33.89598,
    "Floor": 3
  },
  {
    "X": 10.26684,
    "Y": 34.054863,
    "Floor": 3
  },
  {
    "X": 10.3148785,
    "Y": 34.21488,
    "Floor": 3
  },
  {
    "X": 10.3498726,
    "Y": 34.3783722,
    "Floor": 3
  },
  {
    "X": 10.369894,
    "Y": 34.54451,
    "Floor": 3
  },
  {
    "X": 10.367981,
    "Y": 34.7116623,
    "Floor": 3
  },
  {
    "X": 10.3499537,
    "Y": 34.8778229,
    "Floor": 3
  },
  {
    "X": 10.203476,
    "Y": 34.3407059,
    "Floor": 3
  },
  {
    "X": 10.1956348,
    "Y": 34.4873276,
    "Floor": 3
  },
  {
    "X": 10.1883993,
    "Y": 34.6336937,
    "Floor": 3
  },
  {
    "X": 10.1815586,
    "Y": 34.7800941,
    "Floor": 3
  },
  {
    "X": 10.1739731,
    "Y": 34.926445,
    "Floor": 3
  },
  {
    "X": 10.1607428,
    "Y": 35.0724,
    "Floor": 3
  },
  {
    "X": 10.1499615,
    "Y": 35.21882,
    "Floor": 3
  },
  {
    "X": 10.1443615,
    "Y": 35.3652573,
    "Floor": 3
  },
  {
    "X": 10.1452627,
    "Y": 35.51181,
    "Floor": 3
  },
  {
    "X": 10.1500854,
    "Y": 35.65828,
    "Floor": 3
  },
  {
    "X": 10.184576,
    "Y": 36.067646,
    "Floor": 3
  },
  {
    "X": 10.1973286,
    "Y": 36.3124771,
    "Floor": 3
  },
  {
    "X": 10.2192945,
    "Y": 36.55657,
    "Floor": 3
  },
  {
    "X": 10.2616453,
    "Y": 36.798,
    "Floor": 3
  },
  {
    "X": 10.3125191,
    "Y": 37.0378151,
    "Floor": 3
  },
  {
    "X": 10.3453884,
    "Y": 37.2811775,
    "Floor": 3
  },
  {
    "X": 10.3765554,
    "Y": 37.52426,
    "Floor": 3
  },
  {
    "X": 10.3602524,
    "Y": 37.7685432,
    "Floor": 3
  },
  {
    "X": 10.3249788,
    "Y": 38.0111275,
    "Floor": 3
  },
  {
    "X": 10.2866735,
    "Y": 38.25326,
    "Floor": 3
  },
  {
    "X": 10.0004711,
    "Y": 38.2513275,
    "Floor": 3
  },
  {
    "X": 9.981757,
    "Y": 38.4783669,
    "Floor": 3
  },
  {
    "X": 9.966188,
    "Y": 38.7052,
    "Floor": 3
  },
  {
    "X": 9.95667,
    "Y": 38.93239,
    "Floor": 3
  },
  {
    "X": 9.95476,
    "Y": 39.15974,
    "Floor": 3
  },
  {
    "X": 9.951632,
    "Y": 39.38749,
    "Floor": 3
  },
  {
    "X": 9.924078,
    "Y": 39.613,
    "Floor": 3
  },
  {
    "X": 9.866346,
    "Y": 39.8328667,
    "Floor": 3
  },
  {
    "X": 9.804487,
    "Y": 40.0516777,
    "Floor": 3
  },
  {
    "X": 9.298429,
    "Y": 40.1904144,
    "Floor": 3
  },
  {
    "X": 9.193625,
    "Y": 40.4070473,
    "Floor": 3
  },
  {
    "X": 9.058885,
    "Y": 40.60619,
    "Floor": 3
  },
  {
    "X": 8.876455,
    "Y": 40.76056,
    "Floor": 3
  },
  {
    "X": 8.663617,
    "Y": 40.8727,
    "Floor": 3
  },
  {
    "X": 8.450651,
    "Y": 40.9844055,
    "Floor": 3
  },
  {
    "X": 8.222666,
    "Y": 41.06139,
    "Floor": 3
  },
  {
    "X": 7.984676,
    "Y": 41.09546,
    "Floor": 3
  },
  {
    "X": 7.744765,
    "Y": 41.09141,
    "Floor": 3
  },
  {
    "X": 7.51386642,
    "Y": 41.0249939,
    "Floor": 3
  },
  {
    "X": 7.281726,
    "Y": 40.96275,
    "Floor": 3
  },
  {
    "X": 7.43247461,
    "Y": 40.8852348,
    "Floor": 3
  },
  {
    "X": 7.231811,
    "Y": 40.84907,
    "Floor": 3
  },
  {
    "X": 7.028787,
    "Y": 40.830307,
    "Floor": 3
  },
  {
    "X": 6.83037233,
    "Y": 40.78528,
    "Floor": 3
  },
  {
    "X": 6.638654,
    "Y": 40.71585,
    "Floor": 3
  },
  {
    "X": 6.44124842,
    "Y": 40.66346,
    "Floor": 3
  },
  {
    "X": 6.243147,
    "Y": 40.61509,
    "Floor": 3
  },
  {
    "X": 6.04437065,
    "Y": 40.56986,
    "Floor": 3
  },
  {
    "X": 5.843194,
    "Y": 40.5367241,
    "Floor": 3
  },
  {
    "X": 6.349849,
    "Y": 40.7211533,
    "Floor": 3
  },
  {
    "X": 6.19409561,
    "Y": 40.6798744,
    "Floor": 3
  },
  {
    "X": 6.03542566,
    "Y": 40.65299,
    "Floor": 3
  },
  {
    "X": 5.87706661,
    "Y": 40.62439,
    "Floor": 3
  },
  {
    "X": 5.716984,
    "Y": 40.60802,
    "Floor": 3
  },
  {
    "X": 5.55870628,
    "Y": 40.5797577,
    "Floor": 3
  },
  {
    "X": 5.40197372,
    "Y": 40.5433235,
    "Floor": 3
  },
  {
    "X": 5.24259758,
    "Y": 40.5212555,
    "Floor": 3
  },
  {
    "X": 5.08209658,
    "Y": 40.5058861,
    "Floor": 3
  },
  {
    "X": 4.92174625,
    "Y": 40.4922256,
    "Floor": 3
  },
  {
    "X": 5.2666626,
    "Y": 40.7221,
    "Floor": 3
  },
  {
    "X": 5.101033,
    "Y": 40.6869545,
    "Floor": 3
  },
  {
    "X": 4.933555,
    "Y": 40.6627045,
    "Floor": 3
  },
  {
    "X": 4.76433754,
    "Y": 40.6503029,
    "Floor": 3
  },
  {
    "X": 4.595975,
    "Y": 40.6319,
    "Floor": 3
  },
  {
    "X": 4.42760134,
    "Y": 40.6167679,
    "Floor": 3
  },
  {
    "X": 4.261503,
    "Y": 40.58503,
    "Floor": 3
  },
  {
    "X": 4.098613,
    "Y": 40.5387421,
    "Floor": 3
  },
  {
    "X": 3.932281,
    "Y": 40.5053177,
    "Floor": 3
  },
  {
    "X": 3.7673552,
    "Y": 40.46693,
    "Floor": 3
  },
  {
    "X": 4.48225069,
    "Y": 40.41908,
    "Floor": 3
  },
  {
    "X": 4.33852959,
    "Y": 40.392765,
    "Floor": 3
  },
  {
    "X": 4.197841,
    "Y": 40.353157,
    "Floor": 3
  },
  {
    "X": 4.05404472,
    "Y": 40.3260345,
    "Floor": 3
  },
  {
    "X": 3.909453,
    "Y": 40.3046951,
    "Floor": 3
  },
  {
    "X": 3.76487255,
    "Y": 40.2833672,
    "Floor": 3
  },
  {
    "X": 3.61967516,
    "Y": 40.26664,
    "Floor": 3
  },
  {
    "X": 3.47691655,
    "Y": 40.23586,
    "Floor": 3
  },
  {
    "X": 3.33671951,
    "Y": 40.194603,
    "Floor": 3
  },
  {
    "X": 3.16057444,
    "Y": 40.3194351,
    "Floor": 3
  },
  {
    "X": 2.924497,
    "Y": 40.2746773,
    "Floor": 3
  },
  {
    "X": 2.68762827,
    "Y": 40.23465,
    "Floor": 3
  },
  {
    "X": 2.44997287,
    "Y": 40.1997833,
    "Floor": 3
  },
  {
    "X": 2.22066355,
    "Y": 40.1282539,
    "Floor": 3
  },
  {
    "X": 1.98788655,
    "Y": 40.0699272,
    "Floor": 3
  },
  {
    "X": 1.7501806,
    "Y": 40.03471,
    "Floor": 3
  },
  {
    "X": 1.51553953,
    "Y": 39.9807549,
    "Floor": 3
  },
  {
    "X": 1.27897489,
    "Y": 39.93855,
    "Floor": 3
  },
  {
    "X": 1.04628992,
    "Y": 39.87918,
    "Floor": 3
  },
  {
    "X": 0.158217162,
    "Y": 40.44457,
    "Floor": 3
  },
  {
    "X": -0.167652085,
    "Y": 40.3879128,
    "Floor": 3
  },
  {
    "X": -0.4930048,
    "Y": 40.3312569,
    "Floor": 3
  },
  {
    "X": -0.8195348,
    "Y": 40.28233,
    "Floor": 3
  },
  {
    "X": -1.14593327,
    "Y": 40.23405,
    "Floor": 3
  },
  {
    "X": -1.462501,
    "Y": 40.13987,
    "Floor": 3
  },
  {
    "X": -1.78658533,
    "Y": 40.0818863,
    "Floor": 3
  },
  {
    "X": -2.11590481,
    "Y": 40.0444527,
    "Floor": 3
  },
  {
    "X": -2.44282,
    "Y": 39.9975777,
    "Floor": 3
  },
  {
    "X": -3.27401257,
    "Y": 40.6401749,
    "Floor": 3
  },
  {
    "X": -3.59288979,
    "Y": 40.5451546,
    "Floor": 3
  },
  {
    "X": -3.91755915,
    "Y": 40.4739151,
    "Floor": 3
  },
  {
    "X": -4.249868,
    "Y": 40.4545364,
    "Floor": 3
  },
  {
    "X": -4.582999,
    "Y": 40.43829,
    "Floor": 3
  },
  {
    "X": -4.915653,
    "Y": 40.4254341,
    "Floor": 3
  },
  {
    "X": -5.243671,
    "Y": 40.3707466,
    "Floor": 3
  },
  {
    "X": -5.57007551,
    "Y": 40.30575,
    "Floor": 3
  },
  {
    "X": -5.90136051,
    "Y": 40.2734451,
    "Floor": 3
  },
  {
    "X": -6.233444,
    "Y": 40.2498779,
    "Floor": 3
  },
  {
    "X": -6.34058,
    "Y": 40.8028,
    "Floor": 3
  },
  {
    "X": -6.592698,
    "Y": 40.7862053,
    "Floor": 3
  },
  {
    "X": -6.8431077,
    "Y": 40.75582,
    "Floor": 3
  },
  {
    "X": -7.09509754,
    "Y": 40.7587547,
    "Floor": 3
  },
  {
    "X": -7.346813,
    "Y": 40.775425,
    "Floor": 3
  },
  {
    "X": -7.598522,
    "Y": 40.7921143,
    "Floor": 3
  },
  {
    "X": -7.849856,
    "Y": 40.8184166,
    "Floor": 3
  },
  {
    "X": -8.101807,
    "Y": 40.81454,
    "Floor": 3
  },
  {
    "X": -8.35355949,
    "Y": 40.7995377,
    "Floor": 3
  },
  {
    "X": -7.83582258,
    "Y": 41.28326,
    "Floor": 3
  },
  {
    "X": -8.020761,
    "Y": 41.29216,
    "Floor": 3
  },
  {
    "X": -8.20558548,
    "Y": 41.3032761,
    "Floor": 3
  },
  {
    "X": -8.390563,
    "Y": 41.3079453,
    "Floor": 3
  },
  {
    "X": -8.575177,
    "Y": 41.29368,
    "Floor": 3
  },
  {
    "X": -8.760398,
    "Y": 41.2997665,
    "Floor": 3
  },
  {
    "X": -8.945001,
    "Y": 41.31406,
    "Floor": 3
  },
  {
    "X": -9.130057,
    "Y": 41.3269234,
    "Floor": 3
  },
  {
    "X": -9.314545,
    "Y": 41.342495,
    "Floor": 3
  },
  {
    "X": -9.499979,
    "Y": 41.3383827,
    "Floor": 3
  },
  {
    "X": -9.136632,
    "Y": 41.7347145,
    "Floor": 3
  },
  {
    "X": -9.330465,
    "Y": 41.76638,
    "Floor": 3
  },
  {
    "X": -9.524418,
    "Y": 41.799305,
    "Floor": 3
  },
  {
    "X": -9.716382,
    "Y": 41.8424644,
    "Floor": 3
  },
  {
    "X": -9.911699,
    "Y": 41.86502,
    "Floor": 3
  },
  {
    "X": -10.1078033,
    "Y": 41.88029,
    "Floor": 3
  },
  {
    "X": -10.3014307,
    "Y": 41.9171677,
    "Floor": 3
  },
  {
    "X": -10.4967728,
    "Y": 41.9401779,
    "Floor": 3
  },
  {
    "X": -10.69235,
    "Y": 41.9615479,
    "Floor": 3
  },
  {
    "X": -10.8882809,
    "Y": 41.9784164,
    "Floor": 3
  },
  {
    "X": -10.76592,
    "Y": 42.2474976,
    "Floor": 3
  },
  {
    "X": -10.9659548,
    "Y": 42.27958,
    "Floor": 3
  },
  {
    "X": -11.1651258,
    "Y": 42.3203,
    "Floor": 3
  },
  {
    "X": -11.3666525,
    "Y": 42.34522,
    "Floor": 3
  },
  {
    "X": -11.5674992,
    "Y": 42.3747063,
    "Floor": 3
  },
  {
    "X": -11.7701159,
    "Y": 42.36758,
    "Floor": 3
  },
  {
    "X": -11.9732714,
    "Y": 42.3640633,
    "Floor": 3
  },
  {
    "X": -12.1758614,
    "Y": 42.3769875,
    "Floor": 3
  },
  {
    "X": -12.378602,
    "Y": 42.3661842,
    "Floor": 3
  },
  {
    "X": -11.9340019,
    "Y": 42.5249863,
    "Floor": 3
  },
  {
    "X": -12.0778332,
    "Y": 42.5223846,
    "Floor": 3
  },
  {
    "X": -12.2205572,
    "Y": 42.5023346,
    "Floor": 3
  },
  {
    "X": -12.3636723,
    "Y": 42.4883423,
    "Floor": 3
  },
  {
    "X": -12.5075331,
    "Y": 42.48487,
    "Floor": 3
  },
  {
    "X": -12.651022,
    "Y": 42.47393,
    "Floor": 3
  },
  {
    "X": -12.794817,
    "Y": 42.4684639,
    "Floor": 3
  },
  {
    "X": -12.9370642,
    "Y": 42.4479027,
    "Floor": 3
  },
  {
    "X": -13.0788317,
    "Y": 42.4236374,
    "Floor": 3
  },
  {
    "X": -13.2221642,
    "Y": 42.40821,
    "Floor": 3
  },
  {
    "X": -13.0504932,
    "Y": 42.5457,
    "Floor": 3
  },
  {
    "X": -13.2177734,
    "Y": 42.5280228,
    "Floor": 3
  },
  {
    "X": -13.3855562,
    "Y": 42.51244,
    "Floor": 3
  },
  {
    "X": -13.5512457,
    "Y": 42.48725,
    "Floor": 3
  },
  {
    "X": -13.7193136,
    "Y": 42.4712677,
    "Floor": 3
  },
  {
    "X": -13.8863115,
    "Y": 42.4512253,
    "Floor": 3
  },
  {
    "X": -14.0525732,
    "Y": 42.42566,
    "Floor": 3
  },
  {
    "X": -14.2192316,
    "Y": 42.40282,
    "Floor": 3
  },
  {
    "X": -14.3847551,
    "Y": 42.3713837,
    "Floor": 3
  },
  {
    "X": -14.5496607,
    "Y": 42.3383751,
    "Floor": 3
  },
  {
    "X": -14.4619074,
    "Y": 42.50894,
    "Floor": 3
  },
  {
    "X": -14.6241589,
    "Y": 42.4930077,
    "Floor": 3
  },
  {
    "X": -14.7864609,
    "Y": 42.4697647,
    "Floor": 3
  },
  {
    "X": -14.9459591,
    "Y": 42.43384,
    "Floor": 3
  },
  {
    "X": -15.095993,
    "Y": 42.3696556,
    "Floor": 3
  },
  {
    "X": -15.2360315,
    "Y": 42.28631,
    "Floor": 3
  },
  {
    "X": -15.3702984,
    "Y": 42.19326,
    "Floor": 3
  },
  {
    "X": -15.50896,
    "Y": 42.1070137,
    "Floor": 3
  },
  {
    "X": -15.6590853,
    "Y": 42.04253,
    "Floor": 3
  },
  {
    "X": -15.2136087,
    "Y": 42.2564354,
    "Floor": 3
  },
  {
    "X": -15.326128,
    "Y": 42.2293663,
    "Floor": 3
  },
  {
    "X": -15.4342346,
    "Y": 42.1879425,
    "Floor": 3
  },
  {
    "X": -15.5411673,
    "Y": 42.14352,
    "Floor": 3
  },
  {
    "X": -15.6432371,
    "Y": 42.08889,
    "Floor": 3
  },
  {
    "X": -15.7488289,
    "Y": 42.041153,
    "Floor": 3
  },
  {
    "X": -15.8589249,
    "Y": 42.0052567,
    "Floor": 3
  },
  {
    "X": -15.9693928,
    "Y": 41.9715042,
    "Floor": 3
  },
  {
    "X": -16.084547,
    "Y": 41.9722137,
    "Floor": 3
  },
  {
    "X": -16.1911659,
    "Y": 42.0165634,
    "Floor": 3
  },
  {
    "X": -16.1917057,
    "Y": 42.33385,
    "Floor": 3
  },
  {
    "X": -16.3235149,
    "Y": 42.4428062,
    "Floor": 3
  },
  {
    "X": -16.44323,
    "Y": 42.56552,
    "Floor": 3
  },
  {
    "X": -16.55703,
    "Y": 42.69282,
    "Floor": 3
  },
  {
    "X": -16.64563,
    "Y": 42.8387756,
    "Floor": 3
  },
  {
    "X": -16.7057686,
    "Y": 42.9991531,
    "Floor": 3
  },
  {
    "X": -16.7510471,
    "Y": 43.1641846,
    "Floor": 3
  },
  {
    "X": -16.803215,
    "Y": 43.3271255,
    "Floor": 3
  },
  {
    "X": -16.8742237,
    "Y": 43.4826241,
    "Floor": 3
  },
  {
    "X": -16.9569569,
    "Y": 43.6327477,
    "Floor": 3
  },
  {
    "X": -16.9792862,
    "Y": 43.6403122,
    "Floor": 3
  },
  {
    "X": -17.0399,
    "Y": 43.781826,
    "Floor": 3
  },
  {
    "X": -17.1091976,
    "Y": 43.9196,
    "Floor": 3
  },
  {
    "X": -17.1889172,
    "Y": 44.0512543,
    "Floor": 3
  },
  {
    "X": -17.28241,
    "Y": 44.1739,
    "Floor": 3
  },
  {
    "X": -17.3656254,
    "Y": 44.3031921,
    "Floor": 3
  },
  {
    "X": -17.4359226,
    "Y": 44.4398422,
    "Floor": 3
  },
  {
    "X": -17.51827,
    "Y": 44.56984,
    "Floor": 3
  },
  {
    "X": -17.615818,
    "Y": 44.688858,
    "Floor": 3
  },
  {
    "X": -17.7249012,
    "Y": 44.7977448,
    "Floor": 3
  },
  {
    "X": -18.5619049,
    "Y": 44.7147179,
    "Floor": 3
  },
  {
    "X": -18.7195759,
    "Y": 44.8699455,
    "Floor": 3
  },
  {
    "X": -18.8837566,
    "Y": 45.0162125,
    "Floor": 3
  },
  {
    "X": -19.0649681,
    "Y": 45.14317,
    "Floor": 3
  },
  {
    "X": -19.25651,
    "Y": 45.2528343,
    "Floor": 3
  },
  {
    "X": -19.4696217,
    "Y": 45.3071365,
    "Floor": 3
  },
  {
    "X": -19.68847,
    "Y": 45.33677,
    "Floor": 3
  },
  {
    "X": -19.90546,
    "Y": 45.3778572,
    "Floor": 3
  },
  {
    "X": -20.1258583,
    "Y": 45.38998,
    "Floor": 3
  },
  {
    "X": -21.2801971,
    "Y": 45.4210243,
    "Floor": 3
  },
  {
    "X": -21.550396,
    "Y": 45.43644,
    "Floor": 3
  },
  {
    "X": -21.8208866,
    "Y": 45.43112,
    "Floor": 3
  },
  {
    "X": -22.0892315,
    "Y": 45.4723244,
    "Floor": 3
  },
  {
    "X": -22.3569069,
    "Y": 45.5150757,
    "Floor": 3
  },
  {
    "X": -22.6270237,
    "Y": 45.5442657,
    "Floor": 3
  },
  {
    "X": -22.8970261,
    "Y": 45.5678444,
    "Floor": 3
  },
  {
    "X": -23.16777,
    "Y": 45.5532532,
    "Floor": 3
  },
  {
    "X": -23.4387779,
    "Y": 45.5502243,
    "Floor": 3
  },
  {
    "X": -23.70983,
    "Y": 45.55786,
    "Floor": 3
  },
  {
    "X": -23.9809818,
    "Y": 45.55283,
    "Floor": 3
  },
  {
    "X": -24.3245449,
    "Y": 45.5474739,
    "Floor": 3
  },
  {
    "X": -24.5165386,
    "Y": 45.55767,
    "Floor": 3
  },
  {
    "X": -24.7076054,
    "Y": 45.57694,
    "Floor": 3
  },
  {
    "X": -24.8903465,
    "Y": 45.6364937,
    "Floor": 3
  },
  {
    "X": -25.0750122,
    "Y": 45.6899643,
    "Floor": 3
  },
  {
    "X": -25.2590027,
    "Y": 45.7458,
    "Floor": 3
  },
  {
    "X": -25.44516,
    "Y": 45.7931557,
    "Floor": 3
  },
  {
    "X": -25.634922,
    "Y": 45.8259659,
    "Floor": 3
  },
  {
    "X": -25.8175278,
    "Y": 45.8861771,
    "Floor": 3
  },
  {
    "X": -25.68976,
    "Y": 45.77538,
    "Floor": 3
  },
  {
    "X": -25.8242645,
    "Y": 45.8260841,
    "Floor": 3
  },
  {
    "X": -25.959343,
    "Y": 45.8750572,
    "Floor": 3
  },
  {
    "X": -26.0975952,
    "Y": 45.91529,
    "Floor": 3
  },
  {
    "X": -26.2295341,
    "Y": 45.97231,
    "Floor": 3
  },
  {
    "X": -26.3660927,
    "Y": 46.0168724,
    "Floor": 3
  },
  {
    "X": -26.5045261,
    "Y": 46.05565,
    "Floor": 3
  },
  {
    "X": -26.6434536,
    "Y": 46.09211,
    "Floor": 3
  },
  {
    "X": -26.7871513,
    "Y": 46.0983543,
    "Floor": 3
  },
  {
    "X": -26.9308643,
    "Y": 46.0979729,
    "Floor": 3
  },
  {
    "X": -27.387722,
    "Y": 45.988945,
    "Floor": 3
  },
  {
    "X": -27.5934048,
    "Y": 45.9958839,
    "Floor": 3
  },
  {
    "X": -27.7989674,
    "Y": 46.0054626,
    "Floor": 3
  },
  {
    "X": -28.0044823,
    "Y": 45.9960251,
    "Floor": 3
  },
  {
    "X": -28.2104454,
    "Y": 45.9882927,
    "Floor": 3
  },
  {
    "X": -28.4160366,
    "Y": 45.9974747,
    "Floor": 3
  },
  {
    "X": -28.6218128,
    "Y": 45.999,
    "Floor": 3
  },
  {
    "X": -28.8276176,
    "Y": 46.00002,
    "Floor": 3
  },
  {
    "X": -29.0324955,
    "Y": 45.9835739,
    "Floor": 3
  },
  {
    "X": -29.07076,
    "Y": 46.0014229,
    "Floor": 3
  },
  {
    "X": -29.2406769,
    "Y": 45.9873657,
    "Floor": 3
  },
  {
    "X": -29.4106522,
    "Y": 45.97332,
    "Floor": 3
  },
  {
    "X": -29.581,
    "Y": 45.965744,
    "Floor": 3
  },
  {
    "X": -29.75107,
    "Y": 45.95463,
    "Floor": 3
  },
  {
    "X": -29.9195824,
    "Y": 45.9283867,
    "Floor": 3
  },
  {
    "X": -30.09026,
    "Y": 45.92563,
    "Floor": 3
  },
  {
    "X": -30.26078,
    "Y": 45.92573,
    "Floor": 3
  },
  {
    "X": -30.431303,
    "Y": 45.9224319,
    "Floor": 3
  },
  {
    "X": -31.0290585,
    "Y": 46.3699646,
    "Floor": 3
  },
  {
    "X": -31.2826939,
    "Y": 46.33349,
    "Floor": 3
  },
  {
    "X": -31.53908,
    "Y": 46.3214836,
    "Floor": 3
  },
  {
    "X": -31.79495,
    "Y": 46.30827,
    "Floor": 3
  },
  {
    "X": -32.04931,
    "Y": 46.27717,
    "Floor": 3
  },
  {
    "X": -32.3043861,
    "Y": 46.2535057,
    "Floor": 3
  },
  {
    "X": -32.5523453,
    "Y": 46.1897163,
    "Floor": 3
  },
  {
    "X": -32.80081,
    "Y": 46.1279221,
    "Floor": 3
  },
  {
    "X": -33.0543175,
    "Y": 46.09377,
    "Floor": 3
  },
  {
    "X": -33.3055038,
    "Y": 46.0430565,
    "Floor": 3
  },
  {
    "X": -33.3209229,
    "Y": 46.4311447,
    "Floor": 3
  },
  {
    "X": -33.4911652,
    "Y": 46.3741531,
    "Floor": 3
  },
  {
    "X": -33.65696,
    "Y": 46.30577,
    "Floor": 3
  },
  {
    "X": -33.8298,
    "Y": 46.2579842,
    "Floor": 3
  },
  {
    "X": -34.0033379,
    "Y": 46.21252,
    "Floor": 3
  },
  {
    "X": -34.1770859,
    "Y": 46.16799,
    "Floor": 3
  },
  {
    "X": -34.35241,
    "Y": 46.1302,
    "Floor": 3
  },
  {
    "X": -34.5192375,
    "Y": 46.06425,
    "Floor": 3
  },
  {
    "X": -34.6814766,
    "Y": 45.9877777,
    "Floor": 3
  },
  {
    "X": -34.91522,
    "Y": 45.700985,
    "Floor": 3
  },
  {
    "X": -35.1357727,
    "Y": 45.5773163,
    "Floor": 3
  },
  {
    "X": -35.34468,
    "Y": 45.4343,
    "Floor": 3
  },
  {
    "X": -35.5444641,
    "Y": 45.2792435,
    "Floor": 3
  },
  {
    "X": -35.6998138,
    "Y": 45.0802956,
    "Floor": 3
  },
  {
    "X": -35.8231544,
    "Y": 44.85869,
    "Floor": 3
  },
  {
    "X": -35.9440956,
    "Y": 44.63626,
    "Floor": 3
  },
  {
    "X": -36.0496,
    "Y": 44.4062271,
    "Floor": 3
  },
  {
    "X": -36.1479034,
    "Y": 44.172924,
    "Floor": 3
  },
  {
    "X": -36.22423,
    "Y": 43.93216,
    "Floor": 3
  },
  {
    "X": -36.47265,
    "Y": 43.8177567,
    "Floor": 3
  },
  {
    "X": -36.4878769,
    "Y": 43.56788,
    "Floor": 3
  },
  {
    "X": -36.5105438,
    "Y": 43.318634,
    "Floor": 3
  },
  {
    "X": -36.5394936,
    "Y": 43.06997,
    "Floor": 3
  },
  {
    "X": -36.5514526,
    "Y": 42.82004,
    "Floor": 3
  },
  {
    "X": -36.5368347,
    "Y": 42.569706,
    "Floor": 3
  },
  {
    "X": -36.5090523,
    "Y": 42.32096,
    "Floor": 3
  },
  {
    "X": -36.47491,
    "Y": 42.0730362,
    "Floor": 3
  },
  {
    "X": -36.47258,
    "Y": 41.82283,
    "Floor": 3
  },
  {
    "X": -36.60388,
    "Y": 41.90803,
    "Floor": 3
  },
  {
    "X": -36.6157837,
    "Y": 41.6879425,
    "Floor": 3
  },
  {
    "X": -36.619873,
    "Y": 41.46761,
    "Floor": 3
  },
  {
    "X": -36.6082077,
    "Y": 41.2471,
    "Floor": 3
  },
  {
    "X": -36.60807,
    "Y": 41.0271378,
    "Floor": 3
  },
  {
    "X": -36.61688,
    "Y": 40.8069077,
    "Floor": 3
  },
  {
    "X": -36.62234,
    "Y": 40.5866547,
    "Floor": 3
  },
  {
    "X": -36.6077347,
    "Y": 40.3667336,
    "Floor": 3
  },
  {
    "X": -36.5809555,
    "Y": 40.14801,
    "Floor": 3
  },
  {
    "X": -36.6179466,
    "Y": 40.63363,
    "Floor": 3
  },
  {
    "X": -36.6099472,
    "Y": 40.4795723,
    "Floor": 3
  },
  {
    "X": -36.6069679,
    "Y": 40.32533,
    "Floor": 3
  },
  {
    "X": -36.5919,
    "Y": 40.1717758,
    "Floor": 3
  },
  {
    "X": -36.5743332,
    "Y": 40.0185051,
    "Floor": 3
  },
  {
    "X": -36.54767,
    "Y": 39.8662529,
    "Floor": 3
  },
  {
    "X": -36.525856,
    "Y": 39.7135277,
    "Floor": 3
  },
  {
    "X": -36.5116234,
    "Y": 39.559906,
    "Floor": 3
  },
  {
    "X": -36.4970627,
    "Y": 39.40631,
    "Floor": 3
  },
  {
    "X": -36.47803,
    "Y": 39.2531967,
    "Floor": 3
  },
  {
    "X": -36.8187981,
    "Y": 39.1696854,
    "Floor": 3
  },
  {
    "X": -36.7828,
    "Y": 38.9480133,
    "Floor": 3
  },
  {
    "X": -36.76632,
    "Y": 38.7253075,
    "Floor": 3
  },
  {
    "X": -36.76725,
    "Y": 38.5015259,
    "Floor": 3
  },
  {
    "X": -36.76257,
    "Y": 38.2777977,
    "Floor": 3
  },
  {
    "X": -36.7427254,
    "Y": 38.0549736,
    "Floor": 3
  },
  {
    "X": -36.7047348,
    "Y": 37.8344269,
    "Floor": 3
  },
  {
    "X": -36.68214,
    "Y": 37.6114731,
    "Floor": 3
  },
  {
    "X": -36.6823158,
    "Y": 37.38772,
    "Floor": 3
  },
  {
    "X": -36.67553,
    "Y": 37.1641121,
    "Floor": 3
  },
  {
    "X": -37.013485,
    "Y": 37.55124,
    "Floor": 3
  },
  {
    "X": -36.98702,
    "Y": 37.3943253,
    "Floor": 3
  },
  {
    "X": -36.9795876,
    "Y": 37.2351761,
    "Floor": 3
  },
  {
    "X": -36.9824142,
    "Y": 37.0760574,
    "Floor": 3
  },
  {
    "X": -36.9764824,
    "Y": 36.9171,
    "Floor": 3
  },
  {
    "X": -36.960556,
    "Y": 36.7587547,
    "Floor": 3
  },
  {
    "X": -36.94911,
    "Y": 36.6000633,
    "Floor": 3
  },
  {
    "X": -36.9631,
    "Y": 36.4414864,
    "Floor": 3
  },
  {
    "X": -36.99465,
    "Y": 36.2855148,
    "Floor": 3
  },
  {
    "X": -37.0216675,
    "Y": 36.12876,
    "Floor": 3
  },
  {
    "X": -37.2730064,
    "Y": 36.72399,
    "Floor": 3
  },
  {
    "X": -37.2762527,
    "Y": 36.6008263,
    "Floor": 3
  },
  {
    "X": -37.2807655,
    "Y": 36.4777336,
    "Floor": 3
  },
  {
    "X": -37.29993,
    "Y": 36.3558464,
    "Floor": 3
  },
  {
    "X": -37.3259468,
    "Y": 36.235424,
    "Floor": 3
  },
  {
    "X": -37.346,
    "Y": 36.1139259,
    "Floor": 3
  },
  {
    "X": -37.35656,
    "Y": 35.9911766,
    "Floor": 3
  },
  {
    "X": -37.3595963,
    "Y": 35.8680153,
    "Floor": 3
  },
  {
    "X": -37.37297,
    "Y": 35.74568,
    "Floor": 3
  },
  {
    "X": -37.4009247,
    "Y": 35.625473,
    "Floor": 3
  },
  {
    "X": -37.6214256,
    "Y": 34.5957832,
    "Floor": 3
  },
  {
    "X": -37.66259,
    "Y": 34.27992,
    "Floor": 3
  },
  {
    "X": -37.7078362,
    "Y": 33.96461,
    "Floor": 3
  },
  {
    "X": -37.7647247,
    "Y": 33.6512222,
    "Floor": 3
  },
  {
    "X": -37.834938,
    "Y": 33.34052,
    "Floor": 3
  },
  {
    "X": -37.9034081,
    "Y": 33.0288467,
    "Floor": 3
  },
  {
    "X": -37.95475,
    "Y": 32.7145081,
    "Floor": 3
  },
  {
    "X": -37.99435,
    "Y": 32.39844,
    "Floor": 3
  },
  {
    "X": -38.0526352,
    "Y": 32.0853577,
    "Floor": 3
  },
  {
    "X": -38.11497,
    "Y": 31.7730331,
    "Floor": 3
  },
  {
    "X": -38.1117058,
    "Y": 31.4000874,
    "Floor": 3
  },
  {
    "X": -38.1656075,
    "Y": 31.1760216,
    "Floor": 3
  },
  {
    "X": -38.1951,
    "Y": 30.9479542,
    "Floor": 3
  },
  {
    "X": -38.2204475,
    "Y": 30.71931,
    "Floor": 3
  },
  {
    "X": -38.25222,
    "Y": 30.4914436,
    "Floor": 3
  },
  {
    "X": -38.2835579,
    "Y": 30.2635231,
    "Floor": 3
  },
  {
    "X": -38.3287125,
    "Y": 30.0375271,
    "Floor": 3
  },
  {
    "X": -38.3691063,
    "Y": 29.8110714,
    "Floor": 3
  },
  {
    "X": -38.39349,
    "Y": 29.5823574,
    "Floor": 3
  },
  {
    "X": -38.4024,
    "Y": 29.3524761,
    "Floor": 3
  },
  {
    "X": -38.3628349,
    "Y": 29.5673,
    "Floor": 3
  },
  {
    "X": -38.3720741,
    "Y": 29.4048271,
    "Floor": 3
  },
  {
    "X": -38.37901,
    "Y": 29.2417126,
    "Floor": 3
  },
  {
    "X": -38.36231,
    "Y": 29.079607,
    "Floor": 3
  },
  {
    "X": -38.333046,
    "Y": 28.9192162,
    "Floor": 3
  },
  {
    "X": -38.29526,
    "Y": 28.7603111,
    "Floor": 3
  },
  {
    "X": -38.25171,
    "Y": 28.60318,
    "Floor": 3
  },
  {
    "X": -38.2117424,
    "Y": 28.4454327,
    "Floor": 3
  },
  {
    "X": -38.1730232,
    "Y": 28.28705,
    "Floor": 3
  },
  {
    "X": -38.1237335,
    "Y": 28.1313972,
    "Floor": 3
  },
  {
    "X": -38.0399055,
    "Y": 27.9802055,
    "Floor": 3
  },
  {
    "X": -37.9669838,
    "Y": 28.40365,
    "Floor": 3
  },
  {
    "X": -37.89495,
    "Y": 28.2786732,
    "Floor": 3
  },
  {
    "X": -37.8294029,
    "Y": 28.1501179,
    "Floor": 3
  },
  {
    "X": -37.75659,
    "Y": 28.02553,
    "Floor": 3
  },
  {
    "X": -37.68597,
    "Y": 27.8996887,
    "Floor": 3
  },
  {
    "X": -37.62505,
    "Y": 27.7686939,
    "Floor": 3
  },
  {
    "X": -37.5844,
    "Y": 27.6306114,
    "Floor": 3
  },
  {
    "X": -37.55655,
    "Y": 27.4887562,
    "Floor": 3
  },
  {
    "X": -37.5306549,
    "Y": 27.3467846,
    "Floor": 3
  },
  {
    "X": -37.5000229,
    "Y": 27.2057724,
    "Floor": 3
  },
  {
    "X": -37.46837,
    "Y": 27.06498,
    "Floor": 3
  },
  {
    "X": -37.6486053,
    "Y": 27.8265133,
    "Floor": 3
  },
  {
    "X": -37.61709,
    "Y": 27.7082672,
    "Floor": 3
  }
]