[
  {
    "X": 14.5487232,
    "Y": 10.0990086,
    "Floor": 3
  },
  {
    "X": 14.4734745,
    "Y": 10.3461161,
    "Floor": 3
  },
  {
    "X": 14.3932934,
    "Y": 10.576437,
    "Floor": 3
  },
  {
    "X": 14.2906942,
    "Y": 10.8444519,
    "Floor": 3
  },
  {
    "X": 13.8459539,
    "Y": 8.408215,
    "Floor": 3
  },
  {
    "X": 13.7917452,
    "Y": 8.609346,
    "Floor": 3
  },
  {
    "X": 13.7456989,
    "Y": 8.799427,
    "Floor": 3
  },
  {
    "X": 13.68306,
    "Y": 9.02534,
    "Floor": 3
  },
  {
    "X": 13.6117849,
    "Y": 9.207296,
    "Floor": 3
  },
  {
    "X": 13.5251122,
    "Y": 9.382259,
    "Floor": 3
  },
  {
    "X": 13.4108171,
    "Y": 9.587153,
    "Floor": 3
  },
  {
    "X": 13.3270121,
    "Y": 9.805896,
    "Floor": 3
  },
  {
    "X": 13.2704,
    "Y": 9.993005,
    "Floor": 3
  },
  {
    "X": 13.1958361,
    "Y": 10.1877584,
    "Floor": 3
  },
  {
    "X": 13.131443,
    "Y": 10.3444281,
    "Floor": 3
  },
  {
    "X": 12.5798435,
    "Y": 8.85595,
    "Floor": 3
  },
  {
    "X": 12.5451632,
    "Y": 9.004754,
    "Floor": 3
  },
  {
    "X": 12.5211372,
    "Y": 9.189059,
    "Floor": 3
  },
  {
    "X": 12.4914465,
    "Y": 9.350356,
    "Floor": 3
  },
  {
    "X": 12.4512177,
    "Y": 9.53183,
    "Floor": 3
  },
  {
    "X": 12.416214,
    "Y": 9.692094,
    "Floor": 3
  },
  {
    "X": 12.3720112,
    "Y": 9.850004,
    "Floor": 3
  },
  {
    "X": 12.346715,
    "Y": 10.0119209,
    "Floor": 3
  },
  {
    "X": 12.3398495,
    "Y": 10.1757393,
    "Floor": 3
  },
  {
    "X": 12.3208618,
    "Y": 10.3275928,
    "Floor": 3
  },
  {
    "X": 12.2795782,
    "Y": 10.5199585,
    "Floor": 3
  },
  {
    "X": 12.0528784,
    "Y": 9.047928,
    "Floor": 3
  },
  {
    "X": 12.00345,
    "Y": 9.181786,
    "Floor": 3
  },
  {
    "X": 11.9732132,
    "Y": 9.304011,
    "Floor": 3
  },
  {
    "X": 11.9491491,
    "Y": 9.436107,
    "Floor": 3
  },
  {
    "X": 11.9271469,
    "Y": 9.5601635,
    "Floor": 3
  },
  {
    "X": 11.9080839,
    "Y": 9.684579,
    "Floor": 3
  },
  {
    "X": 11.8855867,
    "Y": 9.808473,
    "Floor": 3
  },
  {
    "X": 11.8619976,
    "Y": 9.932199,
    "Floor": 3
  },
  {
    "X": 11.8508663,
    "Y": 10.0576153,
    "Floor": 3
  },
  {
    "X": 11.8489828,
    "Y": 10.200304,
    "Floor": 3
  },
  {
    "X": 11.8449507,
    "Y": 10.3598394,
    "Floor": 3
  },
  {
    "X": 11.8363037,
    "Y": 10.4854679,
    "Floor": 3
  },
  {
    "X": 11.4128008,
    "Y": 9.810658,
    "Floor": 3
  },
  {
    "X": 11.3898573,
    "Y": 10.0265846,
    "Floor": 3
  },
  {
    "X": 11.3788338,
    "Y": 10.2180195,
    "Floor": 3
  },
  {
    "X": 11.36906,
    "Y": 10.4092484,
    "Floor": 3
  },
  {
    "X": 11.33633,
    "Y": 10.6109867,
    "Floor": 3
  },
  {
    "X": 11.2852163,
    "Y": 10.79552,
    "Floor": 3
  },
  {
    "X": 11.2282286,
    "Y": 10.9785156,
    "Floor": 3
  },
  {
    "X": 11.1617441,
    "Y": 11.1582861,
    "Floor": 3
  },
  {
    "X": 11.1130619,
    "Y": 11.3434486,
    "Floor": 3
  },
  {
    "X": 11.0734978,
    "Y": 11.5310488,
    "Floor": 3
  },
  {
    "X": 11.0307446,
    "Y": 11.7308979,
    "Floor": 3
  },
  {
    "X": 10.782671,
    "Y": 11.0482655,
    "Floor": 3
  },
  {
    "X": 10.74912,
    "Y": 11.2254744,
    "Floor": 3
  },
  {
    "X": 10.720686,
    "Y": 11.3820391,
    "Floor": 3
  },
  {
    "X": 10.7025223,
    "Y": 11.5613136,
    "Floor": 3
  },
  {
    "X": 10.7048368,
    "Y": 11.7203569,
    "Floor": 3
  },
  {
    "X": 10.7032757,
    "Y": 11.8793144,
    "Floor": 3
  },
  {
    "X": 10.6887608,
    "Y": 12.0484476,
    "Floor": 3
  },
  {
    "X": 10.6867285,
    "Y": 12.20744,
    "Floor": 3
  },
  {
    "X": 10.6811447,
    "Y": 12.3665342,
    "Floor": 3
  },
  {
    "X": 10.6990261,
    "Y": 12.5244961,
    "Floor": 3
  },
  {
    "X": 10.7410822,
    "Y": 12.6885681,
    "Floor": 3
  },
  {
    "X": 10.4713278,
    "Y": 12.0706816,
    "Floor": 3
  },
  {
    "X": 10.4866276,
    "Y": 12.2015429,
    "Floor": 3
  },
  {
    "X": 10.4935923,
    "Y": 12.3175211,
    "Floor": 3
  },
  {
    "X": 10.4982977,
    "Y": 12.4569559,
    "Floor": 3
  },
  {
    "X": 10.5104876,
    "Y": 12.57237,
    "Floor": 3
  },
  {
    "X": 10.546361,
    "Y": 12.6828537,
    "Floor": 3
  },
  {
    "X": 10.5706863,
    "Y": 12.7962627,
    "Floor": 3
  },
  {
    "X": 10.5817566,
    "Y": 12.91201,
    "Floor": 3
  },
  {
    "X": 10.5969248,
    "Y": 13.0428562,
    "Floor": 3
  },
  {
    "X": 10.62399,
    "Y": 13.1718054,
    "Floor": 3
  },
  {
    "X": 10.6492987,
    "Y": 13.2692652,
    "Floor": 3
  },
  {
    "X": 10.1338921,
    "Y": 14.2710047,
    "Floor": 3
  },
  {
    "X": 10.1993666,
    "Y": 14.4902267,
    "Floor": 3
  },
  {
    "X": 10.2578077,
    "Y": 14.7117853,
    "Floor": 3
  },
  {
    "X": 10.2979527,
    "Y": 14.9370031,
    "Floor": 3
  },
  {
    "X": 10.3215551,
    "Y": 15.1647739,
    "Floor": 3
  },
  {
    "X": 10.3657694,
    "Y": 15.3895111,
    "Floor": 3
  },
  {
    "X": 10.4258862,
    "Y": 15.6104441,
    "Floor": 3
  },
  {
    "X": 10.4797554,
    "Y": 15.8330879,
    "Floor": 3
  },
  {
    "X": 10.5314226,
    "Y": 16.0563221,
    "Floor": 3
  },
  {
    "X": 10.5928993,
    "Y": 16.3554916,
    "Floor": 3
  },
  {
    "X": 10.6341619,
    "Y": 16.5807648,
    "Floor": 3
  },
  {
    "X": 10.0121136,
    "Y": 16.7565842,
    "Floor": 3
  },
  {
    "X": 10.0631371,
    "Y": 16.9086018,
    "Floor": 3
  },
  {
    "X": 10.1115,
    "Y": 17.061367,
    "Floor": 3
  },
  {
    "X": 10.1491156,
    "Y": 17.2171268,
    "Floor": 3
  },
  {
    "X": 10.1763325,
    "Y": 17.3965721,
    "Floor": 3
  },
  {
    "X": 10.1652126,
    "Y": 17.556324,
    "Floor": 3
  },
  {
    "X": 10.1333084,
    "Y": 17.7133675,
    "Floor": 3
  },
  {
    "X": 10.1006184,
    "Y": 17.8703136,
    "Floor": 3
  },
  {
    "X": 10.0741339,
    "Y": 18.02822,
    "Floor": 3
  },
  {
    "X": 10.0565424,
    "Y": 18.1768856,
    "Floor": 3
  },
  {
    "X": 10.0553045,
    "Y": 18.36909,
    "Floor": 3
  },
  {
    "X": 10.2311993,
    "Y": 21.361578,
    "Floor": 3
  },
  {
    "X": 10.205019,
    "Y": 21.8436069,
    "Floor": 3
  },
  {
    "X": 10.2204161,
    "Y": 22.3259029,
    "Floor": 3
  },
  {
    "X": 10.2943945,
    "Y": 22.7448711,
    "Floor": 3
  },
  {
    "X": 10.42583,
    "Y": 23.1499329,
    "Floor": 3
  },
  {
    "X": 10.5751743,
    "Y": 23.5486069,
    "Floor": 3
  },
  {
    "X": 10.706214,
    "Y": 23.953989,
    "Floor": 3
  },
  {
    "X": 10.8252144,
    "Y": 24.3631783,
    "Floor": 3
  },
  {
    "X": 10.9491768,
    "Y": 24.8591022,
    "Floor": 3
  },
  {
    "X": 11.0591812,
    "Y": 25.2998238,
    "Floor": 3
  },
  {
    "X": 11.0498238,
    "Y": 26.5704,
    "Floor": 3
  },
  {
    "X": 11.140522,
    "Y": 26.90606,
    "Floor": 3
  },
  {
    "X": 11.2102776,
    "Y": 27.2469711,
    "Floor": 3
  },
  {
    "X": 11.2609472,
    "Y": 27.5705986,
    "Floor": 3
  },
  {
    "X": 11.2896938,
    "Y": 27.87618,
    "Floor": 3
  },
  {
    "X": 11.30253,
    "Y": 28.1829472,
    "Floor": 3
  },
  {
    "X": 11.3056812,
    "Y": 28.4895782,
    "Floor": 3
  },
  {
    "X": 11.2988958,
    "Y": 28.7965755,
    "Floor": 3
  },
  {
    "X": 11.2894411,
    "Y": 29.1033268,
    "Floor": 3
  },
  {
    "X": 11.2879639,
    "Y": 29.40996,
    "Floor": 3
  },
  {
    "X": 11.2596855,
    "Y": 29.6746216,
    "Floor": 3
  },
  {
    "X": 11.1411285,
    "Y": 30.0739,
    "Floor": 3
  },
  {
    "X": 11.14669,
    "Y": 30.30498,
    "Floor": 3
  },
  {
    "X": 11.1145906,
    "Y": 30.5332737,
    "Floor": 3
  },
  {
    "X": 11.0545378,
    "Y": 30.7564125,
    "Floor": 3
  },
  {
    "X": 11.0060968,
    "Y": 30.9823666,
    "Floor": 3
  },
  {
    "X": 10.9675522,
    "Y": 31.194685,
    "Floor": 3
  },
  {
    "X": 10.931118,
    "Y": 31.4540825,
    "Floor": 3
  },
  {
    "X": 10.9041176,
    "Y": 31.6836929,
    "Floor": 3
  },
  {
    "X": 10.8646584,
    "Y": 31.9113827,
    "Floor": 3
  },
  {
    "X": 10.8183508,
    "Y": 32.1377373,
    "Floor": 3
  },
  {
    "X": 10.7642984,
    "Y": 32.4569664,
    "Floor": 3
  },
  {
    "X": 10.936614,
    "Y": 31.9700623,
    "Floor": 3
  },
  {
    "X": 10.91958,
    "Y": 32.168663,
    "Floor": 3
  },
  {
    "X": 10.9139328,
    "Y": 32.3680763,
    "Floor": 3
  },
  {
    "X": 10.8922548,
    "Y": 32.59301,
    "Floor": 3
  },
  {
    "X": 10.85538,
    "Y": 32.7889061,
    "Floor": 3
  },
  {
    "X": 10.828474,
    "Y": 32.986515,
    "Floor": 3
  },
  {
    "X": 10.7971077,
    "Y": 33.18341,
    "Floor": 3
  },
  {
    "X": 10.7854452,
    "Y": 33.40897,
    "Floor": 3
  },
  {
    "X": 10.789216,
    "Y": 33.63509,
    "Floor": 3
  },
  {
    "X": 10.7758875,
    "Y": 33.8338928,
    "Floor": 3
  },
  {
    "X": 10.7554941,
    "Y": 34.0456161,
    "Floor": 3
  },
  {
    "X": 10.8229694,
    "Y": 32.7641373,
    "Floor": 3
  },
  {
    "X": 10.8181429,
    "Y": 32.95612,
    "Floor": 3
  },
  {
    "X": 10.8244829,
    "Y": 33.1482162,
    "Floor": 3
  },
  {
    "X": 10.8438873,
    "Y": 33.339222,
    "Floor": 3
  },
  {
    "X": 10.8477917,
    "Y": 33.5312958,
    "Floor": 3
  },
  {
    "X": 10.855608,
    "Y": 33.72313,
    "Floor": 3
  },
  {
    "X": 10.858696,
    "Y": 33.91523,
    "Floor": 3
  },
  {
    "X": 10.8510933,
    "Y": 34.10715,
    "Floor": 3
  },
  {
    "X": 10.8639536,
    "Y": 34.299,
    "Floor": 3
  },
  {
    "X": 10.9034557,
    "Y": 34.499855,
    "Floor": 3
  },
  {
    "X": 10.95345,
    "Y": 34.69861,
    "Floor": 3
  },
  {
    "X": 10.7978916,
    "Y": 32.13908,
    "Floor": 3
  },
  {
    "X": 10.8194695,
    "Y": 32.2754326,
    "Floor": 3
  },
  {
    "X": 10.8291264,
    "Y": 32.413063,
    "Floor": 3
  },
  {
    "X": 10.8493843,
    "Y": 32.5493927,
    "Floor": 3
  },
  {
    "X": 10.8824759,
    "Y": 32.6834145,
    "Floor": 3
  },
  {
    "X": 10.9027185,
    "Y": 32.8197174,
    "Floor": 3
  },
  {
    "X": 10.90675,
    "Y": 32.957737,
    "Floor": 3
  },
  {
    "X": 10.9039621,
    "Y": 33.11397,
    "Floor": 3
  },
  {
    "X": 10.8904924,
    "Y": 33.2513275,
    "Floor": 3
  },
  {
    "X": 10.8871307,
    "Y": 33.416893,
    "Floor": 3
  },
  {
    "X": 10.8015957,
    "Y": 31.36045,
    "Floor": 3
  },
  {
    "X": 10.799469,
    "Y": 31.4570637,
    "Floor": 3
  },
  {
    "X": 10.7973309,
    "Y": 31.5407944,
    "Floor": 3
  },
  {
    "X": 10.7902842,
    "Y": 31.6629658,
    "Floor": 3
  },
  {
    "X": 10.7788248,
    "Y": 31.75895,
    "Floor": 3
  },
  {
    "X": 10.7814112,
    "Y": 31.8554745,
    "Floor": 3
  },
  {
    "X": 10.7890272,
    "Y": 31.9518051,
    "Floor": 3
  },
  {
    "X": 10.786479,
    "Y": 32.0482521,
    "Floor": 3
  },
  {
    "X": 10.7704563,
    "Y": 32.1435356,
    "Floor": 3
  },
  {
    "X": 10.7542,
    "Y": 32.23882,
    "Floor": 3
  },
  {
    "X": 10.7448387,
    "Y": 32.3219528,
    "Floor": 3
  },
  {
    "X": 10.7461081,
    "Y": 32.4185562,
    "Floor": 3
  },
  {
    "X": 10.5994778,
    "Y": 32.23955,
    "Floor": 3
  },
  {
    "X": 10.5902357,
    "Y": 32.4746971,
    "Floor": 3
  },
  {
    "X": 10.58569,
    "Y": 32.68384,
    "Floor": 3
  },
  {
    "X": 10.59005,
    "Y": 32.87986,
    "Floor": 3
  },
  {
    "X": 10.6048565,
    "Y": 33.10151,
    "Floor": 3
  },
  {
    "X": 10.639842,
    "Y": 33.29452,
    "Floor": 3
  },
  {
    "X": 10.652606,
    "Y": 33.4901466,
    "Floor": 3
  },
  {
    "X": 10.6523733,
    "Y": 33.6861534,
    "Floor": 3
  },
  {
    "X": 10.65356,
    "Y": 33.88228,
    "Floor": 3
  },
  {
    "X": 10.635726,
    "Y": 34.06446,
    "Floor": 3
  },
  {
    "X": 10.6219368,
    "Y": 34.2990036,
    "Floor": 3
  },
  {
    "X": 10.5828161,
    "Y": 33.70149,
    "Floor": 3
  },
  {
    "X": 10.5835161,
    "Y": 33.85164,
    "Floor": 3
  },
  {
    "X": 10.573801,
    "Y": 34.0014572,
    "Floor": 3
  },
  {
    "X": 10.5494747,
    "Y": 34.1700134,
    "Floor": 3
  },
  {
    "X": 10.5137682,
    "Y": 34.3364754,
    "Floor": 3
  },
  {
    "X": 10.4935,
    "Y": 34.4851875,
    "Floor": 3
  },
  {
    "X": 10.4842415,
    "Y": 34.63517,
    "Floor": 3
  },
  {
    "X": 10.472928,
    "Y": 34.7850151,
    "Floor": 3
  },
  {
    "X": 10.4501657,
    "Y": 34.94345,
    "Floor": 3
  },
  {
    "X": 10.4233818,
    "Y": 35.0812874,
    "Floor": 3
  },
  {
    "X": 10.26854,
    "Y": 35.4458771,
    "Floor": 3
  },
  {
    "X": 10.1878157,
    "Y": 35.6552544,
    "Floor": 3
  },
  {
    "X": 10.1177387,
    "Y": 35.8554,
    "Floor": 3
  },
  {
    "X": 10.04684,
    "Y": 36.02853,
    "Floor": 3
  },
  {
    "X": 9.950416,
    "Y": 36.1886063,
    "Floor": 3
  },
  {
    "X": 9.821633,
    "Y": 36.3236427,
    "Floor": 3
  },
  {
    "X": 9.649469,
    "Y": 36.4236,
    "Floor": 3
  },
  {
    "X": 9.494777,
    "Y": 36.47236,
    "Floor": 3
  },
  {
    "X": 9.288818,
    "Y": 36.5229034,
    "Floor": 3
  },
  {
    "X": 9.090611,
    "Y": 36.543766,
    "Floor": 3
  },
  {
    "X": 8.952302,
    "Y": 37.0656433,
    "Floor": 3
  },
  {
    "X": 8.763364,
    "Y": 37.06202,
    "Floor": 3
  },
  {
    "X": 8.574012,
    "Y": 37.06395,
    "Floor": 3
  },
  {
    "X": 8.362757,
    "Y": 37.0280762,
    "Floor": 3
  },
  {
    "X": 8.175818,
    "Y": 36.9979553,
    "Floor": 3
  },
  {
    "X": 7.98960352,
    "Y": 36.9638939,
    "Floor": 3
  },
  {
    "X": 7.80616,
    "Y": 36.9178467,
    "Floor": 3
  },
  {
    "X": 7.619258,
    "Y": 36.88907,
    "Floor": 3
  },
  {
    "X": 7.431909,
    "Y": 36.86308,
    "Floor": 3
  },
  {
    "X": 7.261863,
    "Y": 36.8153572,
    "Floor": 3
  },
  {
    "X": 7.699446,
    "Y": 37.4230461,
    "Floor": 3
  },
  {
    "X": 7.567213,
    "Y": 37.4145737,
    "Floor": 3
  },
  {
    "X": 7.435507,
    "Y": 37.4022026,
    "Floor": 3
  },
  {
    "X": 7.3053503,
    "Y": 37.377758,
    "Floor": 3
  },
  {
    "X": 7.17336559,
    "Y": 37.3659172,
    "Floor": 3
  },
  {
    "X": 7.04310656,
    "Y": 37.34329,
    "Floor": 3
  },
  {
    "X": 6.9177556,
    "Y": 37.300396,
    "Floor": 3
  },
  {
    "X": 6.78937054,
    "Y": 37.2680779,
    "Floor": 3
  },
  {
    "X": 6.65981627,
    "Y": 37.24058,
    "Floor": 3
  },
  {
    "X": 6.531686,
    "Y": 37.20715,
    "Floor": 3
  },
  {
    "X": 6.39256334,
    "Y": 37.1819572,
    "Floor": 3
  },
  {
    "X": 6.270201,
    "Y": 37.164608,
    "Floor": 3
  },
  {
    "X": 7.018911,
    "Y": 37.4610252,
    "Floor": 3
  },
  {
    "X": 6.91660643,
    "Y": 37.4331322,
    "Floor": 3
  },
  {
    "X": 6.810774,
    "Y": 37.426033,
    "Floor": 3
  },
  {
    "X": 6.706106,
    "Y": 37.40965,
    "Floor": 3
  },
  {
    "X": 6.60292864,
    "Y": 37.3849564,
    "Floor": 3
  },
  {
    "X": 6.48387766,
    "Y": 37.3676758,
    "Floor": 3
  },
  {
    "X": 6.38043928,
    "Y": 37.3445244,
    "Floor": 3
  },
  {
    "X": 6.280922,
    "Y": 37.30779,
    "Floor": 3
  },
  {
    "X": 6.17770958,
    "Y": 37.2836647,
    "Floor": 3
  },
  {
    "X": 6.067668,
    "Y": 37.2570763,
    "Floor": 3
  },
  {
    "X": 6.74452257,
    "Y": 37.91113,
    "Floor": 3
  },
  {
    "X": 6.647679,
    "Y": 37.8963432,
    "Floor": 3
  },
  {
    "X": 6.55143738,
    "Y": 37.87844,
    "Floor": 3
  },
  {
    "X": 6.44527626,
    "Y": 37.84617,
    "Floor": 3
  },
  {
    "X": 6.349289,
    "Y": 37.8272743,
    "Floor": 3
  },
  {
    "X": 6.25183964,
    "Y": 37.81742,
    "Floor": 3
  },
  {
    "X": 6.155291,
    "Y": 37.8009644,
    "Floor": 3
  },
  {
    "X": 6.05817032,
    "Y": 37.7889175,
    "Floor": 3
  },
  {
    "X": 5.960223,
    "Y": 37.7895622,
    "Floor": 3
  },
  {
    "X": 5.8570447,
    "Y": 37.77403,
    "Floor": 3
  },
  {
    "X": 3.84681773,
    "Y": 39.4900475,
    "Floor": 3
  },
  {
    "X": 3.48766637,
    "Y": 39.4392662,
    "Floor": 3
  },
  {
    "X": 3.13289738,
    "Y": 39.3649445,
    "Floor": 3
  },
  {
    "X": 2.731586,
    "Y": 39.2775345,
    "Floor": 3
  },
  {
    "X": 2.370603,
    "Y": 39.24507,
    "Floor": 3
  },
  {
    "X": 2.01566672,
    "Y": 39.17611,
    "Floor": 3
  },
  {
    "X": 1.63412428,
    "Y": 39.0240364,
    "Floor": 3
  },
  {
    "X": 1.23769152,
    "Y": 38.91986,
    "Floor": 3
  },
  {
    "X": 0.881737769,
    "Y": 38.8524666,
    "Floor": 3
  },
  {
    "X": 0.505518258,
    "Y": 38.7621651,
    "Floor": 3
  },
  {
    "X": -0.388642579,
    "Y": 40.18777,
    "Floor": 3
  },
  {
    "X": -0.697411537,
    "Y": 40.1110764,
    "Floor": 3
  },
  {
    "X": -0.9610295,
    "Y": 40.01287,
    "Floor": 3
  },
  {
    "X": -1.23124731,
    "Y": 39.9355545,
    "Floor": 3
  },
  {
    "X": -1.49847209,
    "Y": 39.849144,
    "Floor": 3
  },
  {
    "X": -1.7604357,
    "Y": 39.7466049,
    "Floor": 3
  },
  {
    "X": -2.03520441,
    "Y": 39.6892357,
    "Floor": 3
  },
  {
    "X": -2.31068635,
    "Y": 39.635685,
    "Floor": 3
  },
  {
    "X": -2.57623243,
    "Y": 39.5431671,
    "Floor": 3
  },
  {
    "X": -2.80834055,
    "Y": 39.468914,
    "Floor": 3
  },
  {
    "X": -2.90418553,
    "Y": 40.8027344,
    "Floor": 3
  },
  {
    "X": -3.09604073,
    "Y": 40.75957,
    "Floor": 3
  },
  {
    "X": -3.2866497,
    "Y": 40.7108154,
    "Floor": 3
  },
  {
    "X": -3.480588,
    "Y": 40.6766243,
    "Floor": 3
  },
  {
    "X": -3.6985352,
    "Y": 40.6286774,
    "Floor": 3
  },
  {
    "X": -3.89014864,
    "Y": 40.5841179,
    "Floor": 3
  },
  {
    "X": -4.11188745,
    "Y": 40.56074,
    "Floor": 3
  },
  {
    "X": -4.30786848,
    "Y": 40.5426559,
    "Floor": 3
  },
  {
    "X": -4.50304937,
    "Y": 40.5180664,
    "Floor": 3
  },
  {
    "X": -4.7127676,
    "Y": 40.508728,
    "Floor": 3
  },
  {
    "X": -4.231503,
    "Y": 41.63316,
    "Floor": 3
  },
  {
    "X": -4.3666997,
    "Y": 41.60669,
    "Floor": 3
  },
  {
    "X": -4.522231,
    "Y": 41.5929832,
    "Floor": 3
  },
  {
    "X": -4.65855837,
    "Y": 41.5732765,
    "Floor": 3
  },
  {
    "X": -4.794262,
    "Y": 41.5490036,
    "Floor": 3
  },
  {
    "X": -4.931527,
    "Y": 41.5373459,
    "Floor": 3
  },
  {
    "X": -5.06831455,
    "Y": 41.520977,
    "Floor": 3
  },
  {
    "X": -5.20287037,
    "Y": 41.4916649,
    "Floor": 3
  },
  {
    "X": -5.340035,
    "Y": 41.48037,
    "Floor": 3
  },
  {
    "X": -5.4593277,
    "Y": 41.47545,
    "Floor": 3
  },
  {
    "X": -5.62358046,
    "Y": 41.45688,
    "Floor": 3
  },
  {
    "X": -4.72521544,
    "Y": 42.1780777,
    "Floor": 3
  },
  {
    "X": -4.8373313,
    "Y": 42.16654,
    "Floor": 3
  },
  {
    "X": -4.94827461,
    "Y": 42.14725,
    "Floor": 3
  },
  {
    "X": -5.059827,
    "Y": 42.1320724,
    "Floor": 3
  },
  {
    "X": -5.179119,
    "Y": 42.1173058,
    "Floor": 3
  },
  {
    "X": -5.2902813,
    "Y": 42.0989876,
    "Floor": 3
  },
  {
    "X": -5.402622,
    "Y": 42.09089,
    "Floor": 3
  },
  {
    "X": -5.51478434,
    "Y": 42.0810356,
    "Floor": 3
  },
  {
    "X": -5.62306738,
    "Y": 42.0503769,
    "Floor": 3
  },
  {
    "X": -5.73145247,
    "Y": 42.0199776,
    "Floor": 3
  },
  {
    "X": -5.828165,
    "Y": 42.007,
    "Floor": 3
  },
  {
    "X": -4.341853,
    "Y": 42.20246,
    "Floor": 3
  },
  {
    "X": -4.450576,
    "Y": 42.1805649,
    "Floor": 3
  },
  {
    "X": -4.55978,
    "Y": 42.1605377,
    "Floor": 3
  },
  {
    "X": -4.66837263,
    "Y": 42.1377144,
    "Floor": 3
  },
  {
    "X": -4.77631235,
    "Y": 42.1120148,
    "Floor": 3
  },
  {
    "X": -4.887033,
    "Y": 42.1071968,
    "Floor": 3
  },
  {
    "X": -5.004708,
    "Y": 42.09863,
    "Floor": 3
  },
  {
    "X": -5.113431,
    "Y": 42.0765343,
    "Floor": 3
  },
  {
    "X": -5.231601,
    "Y": 42.0706863,
    "Floor": 3
  },
  {
    "X": -5.34968948,
    "Y": 42.0638428,
    "Floor": 3
  },
  {
    "X": -5.16594028,
    "Y": 42.2778244,
    "Floor": 3
  },
  {
    "X": -5.339058,
    "Y": 42.2487,
    "Floor": 3
  },
  {
    "X": -5.51474857,
    "Y": 42.2530632,
    "Floor": 3
  },
  {
    "X": -5.68723154,
    "Y": 42.21823,
    "Floor": 3
  },
  {
    "X": -5.86241961,
    "Y": 42.2061462,
    "Floor": 3
  },
  {
    "X": -6.038263,
    "Y": 42.2138863,
    "Floor": 3
  },
  {
    "X": -6.21299362,
    "Y": 42.19436,
    "Floor": 3
  },
  {
    "X": -6.38707,
    "Y": 42.16878,
    "Floor": 3
  },
  {
    "X": -6.56259441,
    "Y": 42.1558762,
    "Floor": 3
  },
  {
    "X": -6.748482,
    "Y": 42.12926,
    "Floor": 3
  },
  {
    "X": -6.367396,
    "Y": 42.29479,
    "Floor": 3
  },
  {
    "X": -6.5152297,
    "Y": 42.29424,
    "Floor": 3
  },
  {
    "X": -6.63730955,
    "Y": 42.2788239,
    "Floor": 3
  },
  {
    "X": -6.773898,
    "Y": 42.24992,
    "Floor": 3
  },
  {
    "X": -6.895316,
    "Y": 42.2288246,
    "Floor": 3
  },
  {
    "X": -7.01589346,
    "Y": 42.2035141,
    "Floor": 3
  },
  {
    "X": -7.135563,
    "Y": 42.1749,
    "Floor": 3
  },
  {
    "X": -7.257811,
    "Y": 42.15937,
    "Floor": 3
  },
  {
    "X": -7.378785,
    "Y": 42.1371651,
    "Floor": 3
  },
  {
    "X": -7.49591541,
    "Y": 42.0988541,
    "Floor": 3
  },
  {
    "X": -7.613519,
    "Y": 42.0621567,
    "Floor": 3
  },
  {
    "X": -7.75688457,
    "Y": 42.0258827,
    "Floor": 3
  },
  {
    "X": -8.250218,
    "Y": 42.2197876,
    "Floor": 3
  },
  {
    "X": -8.419263,
    "Y": 42.20092,
    "Floor": 3
  },
  {
    "X": -8.58311749,
    "Y": 42.15602,
    "Floor": 3
  },
  {
    "X": -8.745791,
    "Y": 42.1062279,
    "Floor": 3
  },
  {
    "X": -8.91367149,
    "Y": 42.0790672,
    "Floor": 3
  },
  {
    "X": -9.080714,
    "Y": 42.0463829,
    "Floor": 3
  },
  {
    "X": -9.247138,
    "Y": 42.01119,
    "Floor": 3
  },
  {
    "X": -9.416127,
    "Y": 41.991684,
    "Floor": 3
  },
  {
    "X": -9.581622,
    "Y": 41.952816,
    "Floor": 3
  },
  {
    "X": -9.750742,
    "Y": 41.887043,
    "Floor": 3
  },
  {
    "X": -9.923081,
    "Y": 41.8299828,
    "Floor": 3
  },
  {
    "X": -10.2268763,
    "Y": 42.1404457,
    "Floor": 3
  },
  {
    "X": -10.377223,
    "Y": 42.0844345,
    "Floor": 3
  },
  {
    "X": -10.5166636,
    "Y": 42.0267143,
    "Floor": 3
  },
  {
    "X": -10.640542,
    "Y": 41.941452,
    "Floor": 3
  },
  {
    "X": -10.740818,
    "Y": 41.8167267,
    "Floor": 3
  },
  {
    "X": -10.8283234,
    "Y": 41.6823349,
    "Floor": 3
  },
  {
    "X": -10.91756,
    "Y": 41.5490227,
    "Floor": 3
  },
  {
    "X": -11.0096254,
    "Y": 41.44178,
    "Floor": 3
  },
  {
    "X": -11.1074543,
    "Y": 41.353035,
    "Floor": 3
  },
  {
    "X": -11.2369022,
    "Y": 41.2430153,
    "Floor": 3
  },
  {
    "X": -12.06538,
    "Y": 41.68424,
    "Floor": 3
  },
  {
    "X": -12.2188311,
    "Y": 41.5416069,
    "Floor": 3
  },
  {
    "X": -12.3373318,
    "Y": 41.3999367,
    "Floor": 3
  },
  {
    "X": -12.4534016,
    "Y": 41.2562,
    "Floor": 3
  },
  {
    "X": -12.6013231,
    "Y": 41.17063,
    "Floor": 3
  },
  {
    "X": -12.8078022,
    "Y": 41.1379128,
    "Floor": 3
  },
  {
    "X": -12.99053,
    "Y": 41.1617,
    "Floor": 3
  },
  {
    "X": -13.1642466,
    "Y": 41.22469,
    "Floor": 3
  },
  {
    "X": -13.3308544,
    "Y": 41.30472,
    "Floor": 3
  },
  {
    "X": -13.4800024,
    "Y": 41.3915024,
    "Floor": 3
  },
  {
    "X": -13.622777,
    "Y": 41.5084267,
    "Floor": 3
  },
  {
    "X": -15.0366993,
    "Y": 42.43716,
    "Floor": 3
  },
  {
    "X": -15.2530231,
    "Y": 42.62975,
    "Floor": 3
  },
  {
    "X": -15.4332314,
    "Y": 42.81098,
    "Floor": 3
  },
  {
    "X": -15.6115294,
    "Y": 42.9942474,
    "Floor": 3
  },
  {
    "X": -15.7953348,
    "Y": 43.17182,
    "Floor": 3
  },
  {
    "X": -15.9643164,
    "Y": 43.3635521,
    "Floor": 3
  },
  {
    "X": -16.1469631,
    "Y": 43.5884628,
    "Floor": 3
  },
  {
    "X": -16.32641,
    "Y": 43.81584,
    "Floor": 3
  },
  {
    "X": -16.4766788,
    "Y": 44.0227356,
    "Floor": 3
  },
  {
    "X": -16.6029053,
    "Y": 44.2249222,
    "Floor": 3
  },
  {
    "X": -16.79602,
    "Y": 44.5262947,
    "Floor": 3
  },
  {
    "X": -19.1860065,
    "Y": 45.0421677,
    "Floor": 3
  },
  {
    "X": -19.38892,
    "Y": 45.3511353,
    "Floor": 3
  },
  {
    "X": -19.5831451,
    "Y": 45.61278,
    "Floor": 3
  },
  {
    "X": -19.7861767,
    "Y": 45.86806,
    "Floor": 3
  },
  {
    "X": -20.016367,
    "Y": 46.09819,
    "Floor": 3
  },
  {
    "X": -20.2858448,
    "Y": 46.2811737,
    "Floor": 3
  },
  {
    "X": -20.5503616,
    "Y": 46.4719429,
    "Floor": 3
  },
  {
    "X": -20.8335266,
    "Y": 46.6321564,
    "Floor": 3
  },
  {
    "X": -21.18355,
    "Y": 46.7501144,
    "Floor": 3
  },
  {
    "X": -21.5076962,
    "Y": 46.8758965,
    "Floor": 3
  },
  {
    "X": -21.8200474,
    "Y": 46.9662,
    "Floor": 3
  },
  {
    "X": -22.8131371,
    "Y": 46.6689758,
    "Floor": 3
  },
  {
    "X": -23.081749,
    "Y": 46.69034,
    "Floor": 3
  },
  {
    "X": -23.3181934,
    "Y": 46.6682968,
    "Floor": 3
  },
  {
    "X": -23.5847816,
    "Y": 46.6298027,
    "Floor": 3
  },
  {
    "X": -23.8224964,
    "Y": 46.6195946,
    "Floor": 3
  },
  {
    "X": -24.0539036,
    "Y": 46.5652962,
    "Floor": 3
  },
  {
    "X": -24.2785187,
    "Y": 46.486496,
    "Floor": 3
  },
  {
    "X": -24.5137272,
    "Y": 46.4565659,
    "Floor": 3
  },
  {
    "X": -24.7790585,
    "Y": 46.41064,
    "Floor": 3
  },
  {
    "X": -24.9807911,
    "Y": 46.36754,
    "Floor": 3
  },
  {
    "X": -25.24973,
    "Y": 46.35355,
    "Floor": 3
  },
  {
    "X": -25.3171673,
    "Y": 46.13437,
    "Floor": 3
  },
  {
    "X": -25.50233,
    "Y": 46.0987778,
    "Floor": 3
  },
  {
    "X": -25.668663,
    "Y": 46.0900154,
    "Floor": 3
  },
  {
    "X": -25.8340416,
    "Y": 46.07015,
    "Floor": 3
  },
  {
    "X": -25.9993515,
    "Y": 46.04979,
    "Floor": 3
  },
  {
    "X": -26.1655521,
    "Y": 46.03679,
    "Floor": 3
  },
  {
    "X": -26.33092,
    "Y": 46.01719,
    "Floor": 3
  },
  {
    "X": -26.4952221,
    "Y": 45.9907455,
    "Floor": 3
  },
  {
    "X": -26.6615829,
    "Y": 45.9941978,
    "Floor": 3
  },
  {
    "X": -26.8276825,
    "Y": 46.0063362,
    "Floor": 3
  },
  {
    "X": -26.9716473,
    "Y": 46.01676,
    "Floor": 3
  },
  {
    "X": -26.3955078,
    "Y": 45.912735,
    "Floor": 3
  },
  {
    "X": -26.5237427,
    "Y": 45.9349861,
    "Floor": 3
  },
  {
    "X": -26.6628284,
    "Y": 45.9345169,
    "Floor": 3
  },
  {
    "X": -26.8099213,
    "Y": 45.9465752,
    "Floor": 3
  },
  {
    "X": -26.9383469,
    "Y": 45.96901,
    "Floor": 3
  },
  {
    "X": -27.06765,
    "Y": 45.98585,
    "Floor": 3
  },
  {
    "X": -27.1967945,
    "Y": 46.0033,
    "Floor": 3
  },
  {
    "X": -27.3259869,
    "Y": 46.0208244,
    "Floor": 3
  },
  {
    "X": -27.456337,
    "Y": 46.02164,
    "Floor": 3
  },
  {
    "X": -27.5779362,
    "Y": 46.0194778,
    "Floor": 3
  },
  {
    "X": -26.6348839,
    "Y": 45.804657,
    "Floor": 3
  },
  {
    "X": -26.7599926,
    "Y": 45.8025551,
    "Floor": 3
  },
  {
    "X": -26.8701973,
    "Y": 45.7975273,
    "Floor": 3
  },
  {
    "X": -26.98054,
    "Y": 45.79903,
    "Floor": 3
  },
  {
    "X": -27.097311,
    "Y": 45.7859421,
    "Floor": 3
  },
  {
    "X": -27.2197247,
    "Y": 45.7600327,
    "Floor": 3
  },
  {
    "X": -27.3443,
    "Y": 45.74932,
    "Floor": 3
  },
  {
    "X": -27.454155,
    "Y": 45.73905,
    "Floor": 3
  },
  {
    "X": -27.56329,
    "Y": 45.7226944,
    "Floor": 3
  },
  {
    "X": -27.6806316,
    "Y": 45.7132,
    "Floor": 3
  },
  {
    "X": -26.96653,
    "Y": 45.8205566,
    "Floor": 3
  },
  {
    "X": -27.1101913,
    "Y": 45.78594,
    "Floor": 3
  },
  {
    "X": -27.2546921,
    "Y": 45.7552757,
    "Floor": 3
  },
  {
    "X": -27.4016075,
    "Y": 45.7383232,
    "Floor": 3
  },
  {
    "X": -27.5478973,
    "Y": 45.71729,
    "Floor": 3
  },
  {
    "X": -27.6952953,
    "Y": 45.70613,
    "Floor": 3
  },
  {
    "X": -27.8430347,
    "Y": 45.70106,
    "Floor": 3
  },
  {
    "X": -27.9887314,
    "Y": 45.6765633,
    "Floor": 3
  },
  {
    "X": -28.1244564,
    "Y": 45.65246,
    "Floor": 3
  },
  {
    "X": -28.291851,
    "Y": 45.65408,
    "Floor": 3
  },
  {
    "X": -29.0133476,
    "Y": 45.82603,
    "Floor": 3
  },
  {
    "X": -29.2498913,
    "Y": 45.83611,
    "Floor": 3
  },
  {
    "X": -29.48528,
    "Y": 45.8618546,
    "Floor": 3
  },
  {
    "X": -29.7213955,
    "Y": 45.8544731,
    "Floor": 3
  },
  {
    "X": -29.95298,
    "Y": 45.8057556,
    "Floor": 3
  },
  {
    "X": -30.1888447,
    "Y": 45.79366,
    "Floor": 3
  },
  {
    "X": -30.4255733,
    "Y": 45.7891121,
    "Floor": 3
  },
  {
    "X": -30.6608524,
    "Y": 45.7608566,
    "Floor": 3
  },
  {
    "X": -30.8970947,
    "Y": 45.74657,
    "Floor": 3
  },
  {
    "X": -31.1336536,
    "Y": 45.73658,
    "Floor": 3
  },
  {
    "X": -31.3265018,
    "Y": 45.8275757,
    "Floor": 3
  },
  {
    "X": -31.52677,
    "Y": 45.76458,
    "Floor": 3
  },
  {
    "X": -31.686409,
    "Y": 45.71958,
    "Floor": 3
  },
  {
    "X": -31.845562,
    "Y": 45.6735268,
    "Floor": 3
  },
  {
    "X": -32.0288734,
    "Y": 45.63274,
    "Floor": 3
  },
  {
    "X": -32.1906471,
    "Y": 45.597126,
    "Floor": 3
  },
  {
    "X": -32.339695,
    "Y": 45.52548,
    "Floor": 3
  },
  {
    "X": -32.47832,
    "Y": 45.4349632,
    "Floor": 3
  },
  {
    "X": -32.61914,
    "Y": 45.34729,
    "Floor": 3
  },
  {
    "X": -32.77033,
    "Y": 45.2362938,
    "Floor": 3
  },
  {
    "X": -33.70379,
    "Y": 45.98067,
    "Floor": 3
  },
  {
    "X": -33.84874,
    "Y": 45.7854424,
    "Floor": 3
  },
  {
    "X": -33.93331,
    "Y": 45.5578232,
    "Floor": 3
  },
  {
    "X": -33.9740067,
    "Y": 45.3177528,
    "Floor": 3
  },
  {
    "X": -33.9827843,
    "Y": 45.09081,
    "Floor": 3
  },
  {
    "X": -33.9705544,
    "Y": 44.81499,
    "Floor": 3
  },
  {
    "X": -33.9862328,
    "Y": 44.5394859,
    "Floor": 3
  },
  {
    "X": -34.0214844,
    "Y": 44.2983665,
    "Floor": 3
  },
  {
    "X": -34.0329,
    "Y": 44.0554466,
    "Floor": 3
  },
  {
    "X": -34.0113068,
    "Y": 43.7800941,
    "Floor": 3
  },
  {
    "X": -34.4977341,
    "Y": 44.906456,
    "Floor": 3
  },
  {
    "X": -34.4873123,
    "Y": 44.72493,
    "Floor": 3
  },
  {
    "X": -34.49983,
    "Y": 44.5436821,
    "Floor": 3
  },
  {
    "X": -34.54186,
    "Y": 44.3668251,
    "Floor": 3
  },
  {
    "X": -34.56764,
    "Y": 44.1873665,
    "Floor": 3
  },
  {
    "X": -34.5518379,
    "Y": 44.0184364,
    "Floor": 3
  },
  {
    "X": -34.5143356,
    "Y": 43.81576,
    "Floor": 3
  },
  {
    "X": -34.47718,
    "Y": 43.6377029,
    "Floor": 3
  },
  {
    "X": -34.4501457,
    "Y": 43.4578438,
    "Floor": 3
  },
  {
    "X": -34.43024,
    "Y": 43.28948,
    "Floor": 3
  },
  {
    "X": -34.9137535,
    "Y": 44.1314163,
    "Floor": 3
  },
  {
    "X": -34.8776321,
    "Y": 43.9540672,
    "Floor": 3
  },
  {
    "X": -34.8197441,
    "Y": 43.75731,
    "Floor": 3
  },
  {
    "X": -34.75834,
    "Y": 43.5870361,
    "Floor": 3
  },
  {
    "X": -34.7087669,
    "Y": 43.41297,
    "Floor": 3
  },
  {
    "X": -34.6731834,
    "Y": 43.2356033,
    "Floor": 3
  },
  {
    "X": -34.6511879,
    "Y": 43.05586,
    "Floor": 3
  },
  {
    "X": -34.6123543,
    "Y": 42.879158,
    "Floor": 3
  },
  {
    "X": -34.55834,
    "Y": 42.70669,
    "Floor": 3
  },
  {
    "X": -34.4759636,
    "Y": 42.53206,
    "Floor": 3
  },
  {
    "X": -34.4091,
    "Y": 42.35102,
    "Floor": 3
  },
  {
    "X": -34.645607,
    "Y": 43.6527367,
    "Floor": 3
  },
  {
    "X": -34.61121,
    "Y": 43.53113,
    "Floor": 3
  },
  {
    "X": -34.56618,
    "Y": 43.4126434,
    "Floor": 3
  },
  {
    "X": -34.52245,
    "Y": 43.2937469,
    "Floor": 3
  },
  {
    "X": -34.4698067,
    "Y": 43.1784821,
    "Floor": 3
  },
  {
    "X": -34.4132729,
    "Y": 43.0465355,
    "Floor": 3
  },
  {
    "X": -34.37501,
    "Y": 42.92583,
    "Floor": 3
  },
  {
    "X": -34.340332,
    "Y": 42.8038864,
    "Floor": 3
  },
  {
    "X": -34.3062019,
    "Y": 42.6818581,
    "Floor": 3
  },
  {
    "X": -34.275,
    "Y": 42.5677834,
    "Floor": 3
  },
  {
    "X": -35.2133942,
    "Y": 42.39709,
    "Floor": 3
  },
  {
    "X": -35.1348457,
    "Y": 42.1692238,
    "Floor": 3
  },
  {
    "X": -35.0881042,
    "Y": 41.90018,
    "Floor": 3
  },
  {
    "X": -35.03841,
    "Y": 41.63151,
    "Floor": 3
  },
  {
    "X": -34.9627571,
    "Y": 41.3689461,
    "Floor": 3
  },
  {
    "X": -34.8796577,
    "Y": 41.1425667,
    "Floor": 3
  },
  {
    "X": -34.79045,
    "Y": 40.9182968,
    "Floor": 3
  },
  {
    "X": -34.7284851,
    "Y": 40.6854057,
    "Floor": 3
  },
  {
    "X": -34.697937,
    "Y": 40.446228,
    "Floor": 3
  },
  {
    "X": -34.6698227,
    "Y": 40.2229767,
    "Floor": 3
  },
  {
    "X": -35.68764,
    "Y": 38.41128,
    "Floor": 3
  },
  {
    "X": -35.6282463,
    "Y": 38.1060448,
    "Floor": 3
  },
  {
    "X": -35.5369225,
    "Y": 37.7101974,
    "Floor": 3
  },
  {
    "X": -35.4627953,
    "Y": 37.35928,
    "Floor": 3
  },
  {
    "X": -35.43228,
    "Y": 37.00192,
    "Floor": 3
  },
  {
    "X": -35.41251,
    "Y": 36.6675758,
    "Floor": 3
  },
  {
    "X": -35.34224,
    "Y": 36.267128,
    "Floor": 3
  },
  {
    "X": -35.28373,
    "Y": 35.9132843,
    "Floor": 3
  },
  {
    "X": -35.1997528,
    "Y": 35.5643654,
    "Floor": 3
  },
  {
    "X": -35.1522675,
    "Y": 35.16126,
    "Floor": 3
  },
  {
    "X": -35.15644,
    "Y": 34.85047,
    "Floor": 3
  },
  {
    "X": -36.2495956,
    "Y": 34.2593727,
    "Floor": 3
  },
  {
    "X": -36.2080078,
    "Y": 34.0119247,
    "Floor": 3
  },
  {
    "X": -36.1552544,
    "Y": 33.7323532,
    "Floor": 3
  },
  {
    "X": -36.09078,
    "Y": 33.4896622,
    "Floor": 3
  },
  {
    "X": -36.0466,
    "Y": 33.2426758,
    "Floor": 3
  },
  {
    "X": -36.0272942,
    "Y": 32.9923058,
    "Floor": 3
  },
  {
    "X": -35.9896851,
    "Y": 32.74449,
    "Floor": 3
  },
  {
    "X": -35.9343529,
    "Y": 32.46542,
    "Floor": 3
  },
  {
    "X": -35.89266,
    "Y": 32.20087,
    "Floor": 3
  },
  {
    "X": -35.8708,
    "Y": 31.984457,
    "Floor": 3
  },
  {
    "X": -36.7782745,
    "Y": 32.2317047,
    "Floor": 3
  },
  {
    "X": -36.786068,
    "Y": 32.0519753,
    "Floor": 3
  },
  {
    "X": -36.7761154,
    "Y": 31.8731174,
    "Floor": 3
  },
  {
    "X": -36.7372,
    "Y": 31.69761,
    "Floor": 3
  },
  {
    "X": -36.6998558,
    "Y": 31.5217533,
    "Floor": 3
  },
  {
    "X": -36.6535645,
    "Y": 31.348259,
    "Floor": 3
  },
  {
    "X": -36.63133,
    "Y": 31.1699352,
    "Floor": 3
  },
  {
    "X": -36.63013,
    "Y": 30.99019,
    "Floor": 3
  },
  {
    "X": -36.6295433,
    "Y": 30.8105946,
    "Floor": 3
  },
  {
    "X": -36.6016273,
    "Y": 30.6450863,
    "Floor": 3
  },
  {
    "X": -37.2989464,
    "Y": 31.21805,
    "Floor": 3
  },
  {
    "X": -37.25903,
    "Y": 31.08984,
    "Floor": 3
  },
  {
    "X": -37.2342834,
    "Y": 30.9664936,
    "Floor": 3
  },
  {
    "X": -37.225853,
    "Y": 30.8409557,
    "Floor": 3
  },
  {
    "X": -37.22312,
    "Y": 30.7152233,
    "Floor": 3
  },
  {
    "X": -37.2075272,
    "Y": 30.59031,
    "Floor": 3
  },
  {
    "X": -37.1877,
    "Y": 30.4660912,
    "Floor": 3
  },
  {
    "X": -37.1497154,
    "Y": 30.34614,
    "Floor": 3
  },
  {
    "X": -37.1159172,
    "Y": 30.2076225,
    "Floor": 3
  },
  {
    "X": -37.10236,
    "Y": 30.02361,
    "Floor": 3
  },
  {
    "X": -37.0857773,
    "Y": 29.8906059,
    "Floor": 3
  },
  {
    "X": -37.06556,
    "Y": 29.7663231,
    "Floor": 3
  },
  {
    "X": -37.4181328,
    "Y": 30.0675621,
    "Floor": 3
  },
  {
    "X": -37.3867035,
    "Y": 29.8885422,
    "Floor": 3
  },
  {
    "X": -37.364254,
    "Y": 29.6967754,
    "Floor": 3
  },
  {
    "X": -37.3385124,
    "Y": 29.5283833,
    "Floor": 3
  },
  {
    "X": -37.2983971,
    "Y": 29.3743477,
    "Floor": 3
  },
  {
    "X": -37.2522659,
    "Y": 29.1867123,
    "Floor": 3
  },
  {
    "X": -37.2026863,
    "Y": 29.0236111,
    "Floor": 3
  },
  {
    "X": -37.15598,
    "Y": 28.8598061,
    "Floor": 3
  },
  {
    "X": -37.11716,
    "Y": 28.69386,
    "Floor": 3
  },
  {
    "X": -37.08509,
    "Y": 28.5148678,
    "Floor": 3
  },
  {
    "X": -37.03843,
    "Y": 28.339159,
    "Floor": 3
  },
  {
    "X": -36.9790077,
    "Y": 28.1794376,
    "Floor": 3
  },
  {
    "X": -37.21005,
    "Y": 29.4180527,
    "Floor": 3
  },
  {
    "X": -37.1605225,
    "Y": 29.30954,
    "Floor": 3
  },
  {
    "X": -37.1166534,
    "Y": 29.1816921,
    "Floor": 3
  },
  {
    "X": -37.07995,
    "Y": 29.0516987,
    "Floor": 3
  },
  {
    "X": -37.0304832,
    "Y": 28.9430923,
    "Floor": 3
  },
  {
    "X": -36.98938,
    "Y": 28.8311081,
    "Floor": 3
  },
  {
    "X": -36.9484749,
    "Y": 28.719038,
    "Floor": 3
  },
  {
    "X": -36.9021339,
    "Y": 28.59194,
    "Floor": 3
  },
  {
    "X": -36.86421,
    "Y": 28.4788361,
    "Floor": 3
  },
  {
    "X": -36.836544,
    "Y": 28.3545971,
    "Floor": 3
  },
  {
    "X": -36.81424,
    "Y": 28.2535973,
    "Floor": 3
  },
  {
    "X": -36.7736,
    "Y": 28.1162872,
    "Floor": 3
  },
  {
    "X": -36.7361565,
    "Y": 28.0199547,
    "Floor": 3
  },
  {
    "X": -36.9976959,
    "Y": 28.837389,
    "Floor": 3
  },
  {
    "X": -36.98037,
    "Y": 28.7366867,
    "Floor": 3
  },
  {
    "X": -36.9743843,
    "Y": 28.6278267,
    "Floor": 3
  },
  {
    "X": -36.96633,
    "Y": 28.525938,
    "Floor": 3
  },
  {
    "X": -36.9465141,
    "Y": 28.42564,
    "Floor": 3
  },
  {
    "X": -36.9182663,
    "Y": 28.3133354,
    "Floor": 3
  },
  {
    "X": -36.90244,
    "Y": 28.19865,
    "Floor": 3
  },
  {
    "X": -36.8966637,
    "Y": 28.1102028,
    "Floor": 3
  },
  {
    "X": -36.894577,
    "Y": 28.0011616,
    "Floor": 3
  },
  {
    "X": -36.8897934,
    "Y": 27.87177,
    "Floor": 3
  },
  {
    "X": -36.876236,
    "Y": 27.7636261,
    "Floor": 3
  },
  {
    "X": -37.1016273,
    "Y": 28.4613857,
    "Floor": 3
  },
  {
    "X": -37.0906,
    "Y": 28.36789,
    "Floor": 3
  },
  {
    "X": -37.088707,
    "Y": 28.2894535,
    "Floor": 3
  },
  {
    "X": -37.0858727,
    "Y": 28.20576,
    "Floor": 3
  },
  {
    "X": -37.0722542,
    "Y": 28.1178532,
    "Floor": 3
  },
  {
    "X": -37.05527,
    "Y": 28.0358658,
    "Floor": 3
  },
  {
    "X": -37.03788,
    "Y": 27.9539452,
    "Floor": 3
  },
  {
    "X": -37.02593,
    "Y": 27.8764057,
    "Floor": 3
  },
  {
    "X": -37.01825,
    "Y": 27.7930031,
    "Floor": 3
  },
  {
    "X": -37.01149,
    "Y": 27.7147655,
    "Floor": 3
  },
  {
    "X": -36.9996719,
    "Y": 27.6266155,
    "Floor": 3
  },
  {
    "X": -37.1872444,
    "Y": 28.2519512,
    "Floor": 3
  },
  {
    "X": -37.1720772,
    "Y": 28.1915531,
    "Floor": 3
  },
  {
    "X": -37.15204,
    "Y": 28.1364918,
    "Floor": 3
  },
  {
    "X": -37.12828,
    "Y": 28.0868988,
    "Floor": 3
  },
  {
    "X": -37.1021729,
    "Y": 28.0386028,
    "Floor": 3
  },
  {
    "X": -37.07341,
    "Y": 27.9875355,
    "Floor": 3
  },
  {
    "X": -37.04993,
    "Y": 27.9338474,
    "Floor": 3
  },
  {
    "X": -37.0345573,
    "Y": 27.8811169,
    "Floor": 3
  },
  {
    "X": -37.02006,
    "Y": 27.82434,
    "Floor": 3
  },
  {
    "X": -37.00033,
    "Y": 27.76529,
    "Floor": 3
  },
  {
    "X": -36.96632,
    "Y": 27.7136669,
    "Floor": 3
  },
  {
    "X": -35.752594,
    "Y": 28.39175,
    "Floor": 3
  },
  {
    "X": -35.6058655,
    "Y": 28.3277531,
    "Floor": 3
  },
  {
    "X": -35.4457436,
    "Y": 28.2689667,
    "Floor": 3
  },
  {
    "X": -35.3005676,
    "Y": 28.2024136,
    "Floor": 3
  },
  {
    "X": -35.188324,
    "Y": 28.0899734,
    "Floor": 3
  },
  {
    "X": -35.1118431,
    "Y": 27.9376469,
    "Floor": 3
  },
  {
    "X": -35.04862,
    "Y": 27.7907314,
    "Floor": 3
  },
  {
    "X": -34.98356,
    "Y": 27.64444,
    "Floor": 3
  },
  {
    "X": -34.91632,
    "Y": 27.49935,
    "Floor": 3
  },
  {
    "X": -34.8501358,
    "Y": 27.330492,
    "Floor": 3
  },
  {
    "X": -35.3067741,
    "Y": 23.5591,
    "Floor": 3
  },
  {
    "X": -35.1622658,
    "Y": 22.995533,
    "Floor": 3
  },
  {
    "X": -34.9820137,
    "Y": 22.4421864,
    "Floor": 3
  },
  {
    "X": -34.76345,
    "Y": 21.9393063,
    "Floor": 3
  },
  {
    "X": -34.61306,
    "Y": 21.4488335,
    "Floor": 3
  },
  {
    "X": -34.5254135,
    "Y": 20.9077587,
    "Floor": 3
  },
  {
    "X": -34.49053,
    "Y": 20.395422,
    "Floor": 3
  },
  {
    "X": -34.43354,
    "Y": 19.8853683,
    "Floor": 3
  },
  {
    "X": -34.3144951,
    "Y": 19.3858356,
    "Floor": 3
  },
  {
    "X": -34.1290779,
    "Y": 18.9067764,
    "Floor": 3
  },
  {
    "X": -33.9009056,
    "Y": 18.4088116,
    "Floor": 3
  },
  {
    "X": -34.6047058,
    "Y": 16.7771568,
    "Floor": 3
  },
  {
    "X": -34.57304,
    "Y": 16.4189625,
    "Floor": 3
  },
  {
    "X": -34.56136,
    "Y": 16.0355453,
    "Floor": 3
  },
  {
    "X": -34.5675964,
    "Y": 15.6520262,
    "Floor": 3
  },
  {
    "X": -34.5829849,
    "Y": 15.2928352,
    "Floor": 3
  },
  {
    "X": -34.59107,
    "Y": 14.9091358,
    "Floor": 3
  },
  {
    "X": -34.6121864,
    "Y": 14.5500765,
    "Floor": 3
  },
  {
    "X": -34.62722,
    "Y": 14.1668787,
    "Floor": 3
  },
  {
    "X": -34.601162,
    "Y": 13.7842407,
    "Floor": 3
  },
  {
    "X": -34.5723572,
    "Y": 13.4497509,
    "Floor": 3
  },
  {
    "X": -34.5613937,
    "Y": 12.9944477,
    "Floor": 3
  },
  {
    "X": -35.243988,
    "Y": 12.7599182,
    "Floor": 3
  },
  {
    "X": -35.17697,
    "Y": 12.4746475,
    "Floor": 3
  },
  {
    "X": -35.0814972,
    "Y": 12.2153578,
    "Floor": 3
  },
  {
    "X": -34.9919777,
    "Y": 11.9726667,
    "Floor": 3
  },
  {
    "X": -34.90288,
    "Y": 11.7113066,
    "Floor": 3
  },
  {
    "X": -34.8443451,
    "Y": 11.4591637,
    "Floor": 3
  },
  {
    "X": -34.76185,
    "Y": 11.1958361,
    "Floor": 3
  },
  {
    "X": -34.6589775,
    "Y": 10.9774942,
    "Floor": 3
  },
  {
    "X": -34.52893,
    "Y": 10.6955738,
    "Floor": 3
  },
  {
    "X": -34.463253,
    "Y": 10.4278774,
    "Floor": 3
  },
  {
    "X": -34.4290161,
    "Y": 10.17124,
    "Floor": 3
  },
  {
    "X": -35.18436,
    "Y": 10.7423553,
    "Floor": 3
  },
  {
    "X": -35.1092453,
    "Y": 10.5437727,
    "Floor": 3
  },
  {
    "X": -35.0390968,
    "Y": 10.3566866,
    "Floor": 3
  },
  {
    "X": -34.99151,
    "Y": 10.1625519,
    "Floor": 3
  },
  {
    "X": -34.96742,
    "Y": 10.00193,
    "Floor": 3
  },
  {
    "X": -34.9326172,
    "Y": 9.779657,
    "Floor": 3
  },
  {
    "X": -34.8865929,
    "Y": 9.598023,
    "Floor": 3
  },
  {
    "X": -34.81773,
    "Y": 9.410427,
    "Floor": 3
  },
  {
    "X": -34.750145,
    "Y": 9.209025,
    "Floor": 3
  },
  {
    "X": -34.70544,
    "Y": 9.039896,
    "Floor": 3
  },
  {
    "X": -35.8613625,
    "Y": 9.772543,
    "Floor": 3
  },
  {
    "X": -35.81895,
    "Y": 9.623381,
    "Floor": 3
  },
  {
    "X": -35.7608643,
    "Y": 9.468531,
    "Floor": 3
  },
  {
    "X": -35.7109871,
    "Y": 9.321852,
    "Floor": 3
  },
  {
    "X": -35.67166,
    "Y": 9.150651,
    "Floor": 3
  },
  {
    "X": -35.62847,
    "Y": 8.991199,
    "Floor": 3
  },
  {
    "X": -35.5648041,
    "Y": 8.849903,
    "Floor": 3
  },
  {
    "X": -35.4872551,
    "Y": 8.715839,
    "Floor": 3
  },
  {
    "X": -35.3980141,
    "Y": 8.589068,
    "Floor": 3
  },
  {
    "X": -35.32772,
    "Y": 8.462666,
    "Floor": 3
  },
  {
    "X": -35.2655258,
    "Y": 8.287632,
    "Floor": 3
  },
  {
    "X": -35.92102,
    "Y": 9.506148,
    "Floor": 3
  },
  {
    "X": -35.8623734,
    "Y": 9.305688,
    "Floor": 3
  },
  {
    "X": -35.7752953,
    "Y": 9.116294,
    "Floor": 3
  },
  {
    "X": -35.6880722,
    "Y": 8.911723,
    "Floor": 3
  },
  {
    "X": -35.64942,
    "Y": 8.73489,
    "Floor": 3
  },
  {
    "X": -35.61962,
    "Y": 8.485958,
    "Floor": 3
  },
  {
    "X": -35.58983,
    "Y": 8.250999,
    "Floor": 3
  },
  {
    "X": -35.5487823,
    "Y": 8.031893,
    "Floor": 3
  },
  {
    "X": -35.4961433,
    "Y": 7.82978058,
    "Floor": 3
  },
  {
    "X": -35.45648,
    "Y": 7.596488,
    "Floor": 3
  },
  {
    "X": -35.4181366,
    "Y": 7.29706955,
    "Floor": 3
  },
  {
    "X": -35.9767723,
    "Y": 8.365629,
    "Floor": 3
  },
  {
    "X": -35.9499626,
    "Y": 8.205707,
    "Floor": 3
  },
  {
    "X": -35.913414,
    "Y": 8.04772949,
    "Floor": 3
  },
  {
    "X": -35.8853836,
    "Y": 7.898368,
    "Floor": 3
  },
  {
    "X": -35.8773346,
    "Y": 7.746677,
    "Floor": 3
  },
  {
    "X": -35.8740654,
    "Y": 7.58474731,
    "Floor": 3
  },
  {
    "X": -35.8437233,
    "Y": 7.425401,
    "Floor": 3
  },
  {
    "X": -35.7930031,
    "Y": 7.26096869,
    "Floor": 3
  },
  {
    "X": -35.73386,
    "Y": 7.109915,
    "Floor": 3
  },
  {
    "X": -35.6891022,
    "Y": 6.94356155,
    "Floor": 3
  },
  {
    "X": -36.2194672,
    "Y": 7.227675,
    "Floor": 3
  },
  {
    "X": -36.1685066,
    "Y": 7.059588,
    "Floor": 3
  },
  {
    "X": -36.104332,
    "Y": 6.907774,
    "Floor": 3
  },
  {
    "X": -36.01899,
    "Y": 6.75403929,
    "Floor": 3
  },
  {
    "X": -35.9463577,
    "Y": 6.60629,
    "Floor": 3
  },
  {
    "X": -35.8938026,
    "Y": 6.43859768,
    "Floor": 3
  },
  {
    "X": -35.8610344,
    "Y": 6.265798,
    "Floor": 3
  },
  {
    "X": -35.8121223,
    "Y": 6.09691429,
    "Floor": 3
  },
  {
    "X": -35.7565422,
    "Y": 5.941748,
    "Floor": 3
  },
  {
    "X": -35.6765862,
    "Y": 5.772895,
    "Floor": 3
  },
  {
    "X": -35.6035843,
    "Y": 5.62506533,
    "Floor": 3
  },
  {
    "X": -36.1092072,
    "Y": 6.08591747,
    "Floor": 3
  },
  {
    "X": -36.076622,
    "Y": 5.97524738,
    "Floor": 3
  },
  {
    "X": -36.04308,
    "Y": 5.85676575,
    "Floor": 3
  },
  {
    "X": -36.0110054,
    "Y": 5.745917,
    "Floor": 3
  },
  {
    "X": -35.961338,
    "Y": 5.633268,
    "Floor": 3
  },
  {
    "X": -35.92147,
    "Y": 5.5168705,
    "Floor": 3
  },
  {
    "X": -35.88835,
    "Y": 5.40630054,
    "Floor": 3
  },
  {
    "X": -35.8452377,
    "Y": 5.29097557,
    "Floor": 3
  },
  {
    "X": -35.792263,
    "Y": 5.179923,
    "Floor": 3
  },
  {
    "X": -35.7196426,
    "Y": 5.07144737,
    "Floor": 3
  },
  {
    "X": -35.64496,
    "Y": 4.98338,
    "Floor": 3
  },
  {
    "X": -36.14667,
    "Y": 4.53732538,
    "Floor": 3
  },
  {
    "X": -36.0409164,
    "Y": 4.36911535,
    "Floor": 3
  },
  {
    "X": -35.9510765,
    "Y": 4.218555,
    "Floor": 3
  },
  {
    "X": -35.86224,
    "Y": 4.05410337,
    "Floor": 3
  },
  {
    "X": -35.7696724,
    "Y": 3.89159179,
    "Floor": 3
  },
  {
    "X": -35.7022,
    "Y": 3.71762824,
    "Floor": 3
  },
  {
    "X": -35.659668,
    "Y": 3.54766655,
    "Floor": 3
  },
  {
    "X": -35.6195259,
    "Y": 3.36508942,
    "Floor": 3
  },
  {
    "X": -35.5568352,
    "Y": 3.18888164,
    "Floor": 3
  },
  {
    "X": -35.4615669,
    "Y": 2.962737,
    "Floor": 3
  },
  {
    "X": -35.3785477,
    "Y": 2.78230548,
    "Floor": 3
  },
  {
    "X": -35.84917,
    "Y": 1.34492624,
    "Floor": 3
  },
  {
    "X": -35.75373,
    "Y": 1.0767051,
    "Floor": 3
  },
  {
    "X": -35.6157646,
    "Y": 0.8077315,
    "Floor": 3
  },
  {
    "X": -35.46492,
    "Y": 0.5874191,
    "Floor": 3
  },
  {
    "X": -35.29018,
    "Y": 0.3624873,
    "Floor": 3
  },
  {
    "X": -35.1242867,
    "Y": 0.1533625,
    "Floor": 3
  },
  {
    "X": -34.9493446,
    "Y": -0.0712974444,
    "Floor": 3
  },
  {
    "X": -34.74243,
    "Y": -0.238550961,
    "Floor": 3
  },
  {
    "X": -34.4783058,
    "Y": -0.3427606,
    "Floor": 3
  },
  {
    "X": -34.1818466,
    "Y": -0.402694643,
    "Floor": 3
  },
  {
    "X": -34.78617,
    "Y": -1.03334939,
    "Floor": 3
  },
  {
    "X": -34.5759544,
    "Y": -1.03450835,
    "Floor": 3
  },
  {
    "X": -34.37843,
    "Y": -1.044196,
    "Floor": 3
  },
  {
    "X": -34.1681366,
    "Y": -1.05345154,
    "Floor": 3
  },
  {
    "X": -33.9840469,
    "Y": -1.04648638,
    "Floor": 3
  },
  {
    "X": -33.760582,
    "Y": -1.033058,
    "Floor": 3
  },
  {
    "X": -33.55161,
    "Y": -1.00798857,
    "Floor": 3
  },
  {
    "X": -33.3426552,
    "Y": -0.9824421,
    "Floor": 3
  },
  {
    "X": -33.13244,
    "Y": -0.9708283,
    "Floor": 3
  },
  {
    "X": -32.9106331,
    "Y": -0.941712558,
    "Floor": 3
  },
  {
    "X": -33.1440773,
    "Y": -2.457165,
    "Floor": 3
  },
  {
    "X": -32.8670578,
    "Y": -2.419694,
    "Floor": 3
  },
  {
    "X": -32.5921745,
    "Y": -2.36732841,
    "Floor": 3
  },
  {
    "X": -32.3141,
    "Y": -2.339118,
    "Floor": 3
  },
  {
    "X": -32.03495,
    "Y": -2.323455,
    "Floor": 3
  },
  {
    "X": -31.7558346,
    "Y": -2.30356812,
    "Floor": 3
  },
  {
    "X": -31.49373,
    "Y": -2.30143332,
    "Floor": 3
  },
  {
    "X": -31.2316437,
    "Y": -2.29541135,
    "Floor": 3
  },
  {
    "X": -30.9524555,
    "Y": -2.27866435,
    "Floor": 3
  },
  {
    "X": -30.6553383,
    "Y": -2.28767347,
    "Floor": 3
  },
  {
    "X": -31.4442978,
    "Y": -3.757901,
    "Floor": 3
  },
  {
    "X": -31.2523766,
    "Y": -3.74876547,
    "Floor": 3
  },
  {
    "X": -31.0346851,
    "Y": -3.73868775,
    "Floor": 3
  },
  {
    "X": -30.8431721,
    "Y": -3.72166753,
    "Floor": 3
  },
  {
    "X": -30.6253319,
    "Y": -3.71529412,
    "Floor": 3
  },
  {
    "X": -30.43308,
    "Y": -3.71753263,
    "Floor": 3
  },
  {
    "X": -30.2154331,
    "Y": -3.706645,
    "Floor": 3
  },
  {
    "X": -30.01084,
    "Y": -3.69283223,
    "Floor": 3
  },
  {
    "X": -29.7950726,
    "Y": -3.66222715,
    "Floor": 3
  },
  {
    "X": -29.6038551,
    "Y": -3.643355,
    "Floor": 3
  },
  {
    "X": -29.3859425,
    "Y": -3.64058852,
    "Floor": 3
  },
  {
    "X": -29.1684189,
    "Y": -3.62988,
    "Floor": 3
  },
  {
    "X": -30.5042534,
    "Y": -4.613815,
    "Floor": 3
  },
  {
    "X": -30.36078,
    "Y": -4.61213,
    "Floor": 3
  },
  {
    "X": -30.2175236,
    "Y": -4.60269833,
    "Floor": 3
  },
  {
    "X": -30.0650845,
    "Y": -4.602425,
    "Floor": 3
  },
  {
    "X": -29.9215069,
    "Y": -4.60401964,
    "Floor": 3
  },
  {
    "X": -29.7780437,
    "Y": -4.6005826,
    "Floor": 3
  },
  {
    "X": -29.62577,
    "Y": -4.59309959,
    "Floor": 3
  },
  {
    "X": -29.483448,
    "Y": -4.574528,
    "Floor": 3
  },
  {
    "X": -29.34026,
    "Y": -4.56460667,
    "Floor": 3
  },
  {
    "X": -29.1886444,
    "Y": -4.548374,
    "Floor": 3
  },
  {
    "X": -29.6693974,
    "Y": -4.95748,
    "Floor": 3
  },
  {
    "X": -29.4961834,
    "Y": -4.91923475,
    "Floor": 3
  },
  {
    "X": -29.3035,
    "Y": -4.86168242,
    "Floor": 3
  },
  {
    "X": -29.1191025,
    "Y": -4.819402,
    "Floor": 3
  },
  {
    "X": -28.9339237,
    "Y": -4.78032446,
    "Floor": 3
  },
  {
    "X": -28.73454,
    "Y": -4.755483,
    "Floor": 3
  },
  {
    "X": -28.54546,
    "Y": -4.74773026,
    "Floor": 3
  },
  {
    "X": -28.3562584,
    "Y": -4.74135828,
    "Floor": 3
  },
  {
    "X": -28.1672153,
    "Y": -4.73431,
    "Floor": 3
  },
  {
    "X": -27.9662457,
    "Y": -4.727413,
    "Floor": 3
  },
  {
    "X": -28.69456,
    "Y": -5.3262167,
    "Floor": 3
  },
  {
    "X": -28.555706,
    "Y": -5.34547043,
    "Floor": 3
  },
  {
    "X": -28.416378,
    "Y": -5.35945654,
    "Floor": 3
  },
  {
    "X": -28.2849255,
    "Y": -5.361898,
    "Floor": 3
  },
  {
    "X": -28.1360378,
    "Y": -5.36267376,
    "Floor": 3
  },
  {
    "X": -28.0046329,
    "Y": -5.36579275,
    "Floor": 3
  },
  {
    "X": -27.855772,
    "Y": -5.370335,
    "Floor": 3
  },
  {
    "X": -27.71576,
    "Y": -5.365433,
    "Floor": 3
  },
  {
    "X": -27.5770187,
    "Y": -5.345752,
    "Floor": 3
  },
  {
    "X": -27.4306355,
    "Y": -5.3180604,
    "Floor": 3
  },
  {
    "X": -28.58004,
    "Y": -5.42877865,
    "Floor": 3
  },
  {
    "X": -28.4745235,
    "Y": -5.43087,
    "Floor": 3
  },
  {
    "X": -28.3641472,
    "Y": -5.4507637,
    "Floor": 3
  },
  {
    "X": -28.2602673,
    "Y": -5.46983862,
    "Floor": 3
  },
  {
    "X": -28.1583252,
    "Y": -5.497337,
    "Floor": 3
  },
  {
    "X": -28.05739,
    "Y": -5.52860975,
    "Floor": 3
  },
  {
    "X": -27.95372,
    "Y": -5.54861,
    "Floor": 3
  },
  {
    "X": -27.8485641,
    "Y": -5.55882835,
    "Floor": 3
  },
  {
    "X": -27.7499065,
    "Y": -5.56741858,
    "Floor": 3
  },
  {
    "X": -27.6509342,
    "Y": -5.570729,
    "Floor": 3
  },
  {
    "X": -28.5479164,
    "Y": -5.596403,
    "Floor": 3
  },
  {
    "X": -28.4716072,
    "Y": -5.59912968,
    "Floor": 3
  },
  {
    "X": -28.3900757,
    "Y": -5.59783936,
    "Floor": 3
  },
  {
    "X": -28.3035812,
    "Y": -5.59625673,
    "Floor": 3
  },
  {
    "X": -28.2224426,
    "Y": -5.58839941,
    "Floor": 3
  },
  {
    "X": -28.1361275,
    "Y": -5.582493,
    "Floor": 3
  },
  {
    "X": -28.059885,
    "Y": -5.58746862,
    "Floor": 3
  },
  {
    "X": -27.97341,
    "Y": -5.59068346,
    "Floor": 3
  },
  {
    "X": -27.88683,
    "Y": -5.59086847,
    "Floor": 3
  },
  {
    "X": -27.79524,
    "Y": -5.588213,
    "Floor": 3
  },
  {
    "X": -27.7239971,
    "Y": -5.584252,
    "Floor": 3
  },
  {
    "X": -26.3224564,
    "Y": -5.50911951,
    "Floor": 3
  },
  {
    "X": -26.0888023,
    "Y": -5.528246,
    "Floor": 3
  },
  {
    "X": -25.8231373,
    "Y": -5.53052473,
    "Floor": 3
  },
  {
    "X": -25.5729313,
    "Y": -5.52587366,
    "Floor": 3
  },
  {
    "X": -25.32373,
    "Y": -5.5043416,
    "Floor": 3
  },
  {
    "X": -25.0745945,
    "Y": -5.482966,
    "Floor": 3
  },
  {
    "X": -24.8244324,
    "Y": -5.486539,
    "Floor": 3
  },
  {
    "X": -24.57445,
    "Y": -5.487241,
    "Floor": 3
  },
  {
    "X": -24.3398323,
    "Y": -5.49203,
    "Floor": 3
  },
  {
    "X": -24.0899,
    "Y": -5.49417448,
    "Floor": 3
  },
  {
    "X": -23.8244877,
    "Y": -5.47882748,
    "Floor": 3
  },
  {
    "X": -23.5106239,
    "Y": -5.42437,
    "Floor": 3
  },
  {
    "X": -23.3360729,
    "Y": -5.439582,
    "Floor": 3
  },
  {
    "X": -23.16128,
    "Y": -5.448592,
    "Floor": 3
  },
  {
    "X": -22.9763165,
    "Y": -5.46818256,
    "Floor": 3
  },
  {
    "X": -22.8015556,
    "Y": -5.47489262,
    "Floor": 3
  },
  {
    "X": -22.6378365,
    "Y": -5.485386,
    "Floor": 3
  },
  {
    "X": -22.4544849,
    "Y": -5.51627731,
    "Floor": 3
  },
  {
    "X": -22.29181,
    "Y": -5.53773642,
    "Floor": 3
  },
  {
    "X": -22.1172161,
    "Y": -5.551191,
    "Floor": 3
  },
  {
    "X": -21.9530849,
    "Y": -5.54947424,
    "Floor": 3
  },
  {
    "X": -20.6892433,
    "Y": -5.41496325,
    "Floor": 3
  },
  {
    "X": -20.45289,
    "Y": -5.42027235,
    "Floor": 3
  },
  {
    "X": -20.1850166,
    "Y": -5.42584324,
    "Floor": 3
  },
  {
    "X": -19.9328136,
    "Y": -5.42791128,
    "Floor": 3
  },
  {
    "X": -19.6821327,
    "Y": -5.40172338,
    "Floor": 3
  },
  {
    "X": -19.4346733,
    "Y": -5.35287666,
    "Floor": 3
  },
  {
    "X": -19.1716328,
    "Y": -5.302134,
    "Floor": 3
  },
  {
    "X": -18.9230232,
    "Y": -5.260384,
    "Floor": 3
  },
  {
    "X": -18.6766224,
    "Y": -5.206624,
    "Floor": 3
  },
  {
    "X": -18.4468346,
    "Y": -5.15080547,
    "Floor": 3
  },
  {
    "X": -17.15776,
    "Y": -5.05307055,
    "Floor": 3
  },
  {
    "X": -16.8985,
    "Y": -4.97921753,
    "Floor": 3
  },
  {
    "X": -16.648613,
    "Y": -4.934014,
    "Floor": 3
  },
  {
    "X": -16.4157467,
    "Y": -4.88438749,
    "Floor": 3
  },
  {
    "X": -16.1679134,
    "Y": -4.828479,
    "Floor": 3
  },
  {
    "X": -15.9042873,
    "Y": -4.770925,
    "Floor": 3
  },
  {
    "X": -15.6559229,
    "Y": -4.718934,
    "Floor": 3
  },
  {
    "X": -15.4031286,
    "Y": -4.694156,
    "Floor": 3
  },
  {
    "X": -15.1506786,
    "Y": -4.667124,
    "Floor": 3
  },
  {
    "X": -14.9308262,
    "Y": -4.634844,
    "Floor": 3
  },
  {
    "X": -14.6310816,
    "Y": -4.60124731,
    "Floor": 3
  },
  {
    "X": -14.307498,
    "Y": -4.735616,
    "Floor": 3
  },
  {
    "X": -14.11924,
    "Y": -4.72099447,
    "Floor": 3
  },
  {
    "X": -13.94166,
    "Y": -4.71299171,
    "Floor": 3
  },
  {
    "X": -13.7640085,
    "Y": -4.70489931,
    "Floor": 3
  },
  {
    "X": -13.5868769,
    "Y": -4.690592,
    "Floor": 3
  },
  {
    "X": -13.4214,
    "Y": -4.670746,
    "Floor": 3
  },
  {
    "X": -13.2460918,
    "Y": -4.64086437,
    "Floor": 3
  },
  {
    "X": -13.05857,
    "Y": -4.617681,
    "Floor": 3
  },
  {
    "X": -12.8810291,
    "Y": -4.607642,
    "Floor": 3
  },
  {
    "X": -12.7144938,
    "Y": -4.60754538,
    "Floor": 3
  }
]